Workbook
Name ProjectStage: 'Dropdowns'!$A$7:INDEX('Dropdowns'!$A$7:$A$106,COUNTA('Dropdowns'!$A$7:$A$106))
Name LeadStatus: 'Dropdowns'!$B$7:INDEX('Dropdowns'!$B$7:$B$106,COUNTA('Dropdowns'!$B$7:$B$106))
Name EndUserType: 'Dropdowns'!$C$7:INDEX('Dropdowns'!$C$7:$C$106,COUNTA('Dropdowns'!$C$7:$C$106))
Name DecisionInfluencer: 'Dropdowns'!$D$7:INDEX('Dropdowns'!$D$7:$D$106,COUNTA('Dropdowns'!$D$7:$D$106))
Name Market: 'Dropdowns'!$E$7:INDEX('Dropdowns'!$E$7:$E$106,COUNTA('Dropdowns'!$E$7:$E$106))
Name Segment: 'Dropdowns'!$F$7:INDEX('Dropdowns'!$F$7:$F$106,COUNTA('Dropdowns'!$F$7:$F$106))
Name Application: 'Dropdowns'!$G$7:INDEX('Dropdowns'!$G$7:$G$106,COUNTA('Dropdowns'!$G$7:$G$106))
Name DemandDriver: 'Dropdowns'!$H$7:INDEX('Dropdowns'!$H$7:$H$106,COUNTA('Dropdowns'!$H$7:$H$106))
Name OEMCategory: 'Dropdowns'!$I$7:INDEX('Dropdowns'!$I$7:$I$106,COUNTA('Dropdowns'!$I$7:$I$106))
Name SiteType: 'Dropdowns'!$J$7:INDEX('Dropdowns'!$J$7:$J$106,COUNTA('Dropdowns'!$J$7:$J$106))
Name PowerNeeds: 'Dropdowns'!$K$7:INDEX('Dropdowns'!$K$7:$K$106,COUNTA('Dropdowns'!$K$7:$K$106))
Name EnergySource: 'Dropdowns'!$L$7:INDEX('Dropdowns'!$L$7:$L$106,COUNTA('Dropdowns'!$L$7:$L$106))
Name AIFacility: 'Dropdowns'!$M$7:INDEX('Dropdowns'!$M$7:$M$106,COUNTA('Dropdowns'!$M$7:$M$106))
Name YesNo: 'Dropdowns'!$N$7:INDEX('Dropdowns'!$N$7:$N$106,COUNTA('Dropdowns'!$N$7:$N$106))
Name Occupation: 'Dropdowns'!$O$7:INDEX('Dropdowns'!$O$7:$O$106,COUNTA('Dropdowns'!$O$7:$O$106))
Name Industry: 'Dropdowns'!$P$7:INDEX('Dropdowns'!$P$7:$P$106,COUNTA('Dropdowns'!$P$7:$P$106))
Name LeadSource: 'Dropdowns'!$Q$7:INDEX('Dropdowns'!$Q$7:$Q$106,COUNTA('Dropdowns'!$Q$7:$Q$106))
Name Country: 'Dropdowns'!$R$7:INDEX('Dropdowns'!$R$7:$R$106,COUNTA('Dropdowns'!$R$7:$R$106))
Name Salutation: 'Dropdowns'!$S$7:INDEX('Dropdowns'!$S$7:$S$106,COUNTA('Dropdowns'!$S$7:$S$106))
Name WinLoss: 'Dropdowns'!$T$7:INDEX('Dropdowns'!$T$7:$T$106,COUNTA('Dropdowns'!$T$7:$T$106))
Name Solutions: 'Dropdowns'!$U$7:INDEX('Dropdowns'!$U$7:$U$106,COUNTA('Dropdowns'!$U$7:$U$106))
Name CanadaProvince: 'Dropdowns'!$V$7:INDEX('Dropdowns'!$V$7:$V$106,COUNTA('Dropdowns'!$V$7:$V$106))
Name CanadianRegion: 'Dropdowns'!$W$7:INDEX('Dropdowns'!$W$7:$W$106,COUNTA('Dropdowns'!$W$7:$W$106))
Name Products: 'Dropdowns'!$X$7:INDEX('Dropdowns'!$X$7:$X$106,COUNTA('Dropdowns'!$X$7:$X$106))
Name ProjectNames: 'Projects'!$A$7:$A$206

Sheet Projects
A1: Stephan Hardt | Power Generation
A2: Projects template
A3: One project per row. Select multiple products on Project Products.
A4: Amber cells = dropdowns. * = required in the recording. Blank rows are ready for entry. See Guide for source limits.
A5: Key Details | R5: Date + Location | Z5: Market + Application | AJ5: Sales Updates | AO5: Additional Project Details | AS5: Project Metadata
A6: Project Name * | B6: End User | C6: Stage | D6: Other Project Aliases | E6: End User Type | F6: End User Contact | G6: Site Owner | H6: Site Owner Contact | I6: Main Decision Influencer | J6: Solutions | K6: Construction Status | L6: Win/Loss Reason | M6: Amount ($) | N6: Project Pipeline Amount | O6: Estimated Lbs | P6: Estimated Power Capacity (MW) | Q6: Estimated Voltage (KV) | R6: City | S6: County | T6: State | U6: Country | V6: Canada Province/Territory | W6: Est. Commission Date | X6: Est. Close Date * | Y6: Est. Award Date | Z6: Market | AA6: Segment | AB6: Application | AC6: Demand Driver | AD6: OEM Category | AE6: Proposed Project Application | AF6: Brownfield/Greenfield | AG6: Power Needs | AH6: Primary Energy Source | AI6: AI Facility | AJ6: Sales Comments | AK6: Top Next Steps | AL6: Project Description | AM6: Internal NDA Active | AN6: Customer NDA Required | AO6: Total Transmission Line Miles | AP6: Transmission Line Endpoint 1 | AQ6: Transmission Line Endpoint 2 | AR6: Data Center Building Name | AS6: External Project ID | AT6: Building ID (Data Centers Only) | AU6: End User ID | AV6: Site Owner ID | AW6: RTO/ISO/Regional Group ID
A7: Forest Junction Energy Center | B7: Invenergy | C7: Open | D7: Forest Junction Energy Center Project (Yes Energy); Forest Junction Energy Center LLC; MISO J4014; paired w/ Union Depot Energy Center (750 MW CC) | E7: IPP | F7: Daniel Birmingham, Lead Developer | G7: Invenergy (private land lease) | I7: Developer | K7: Advanced Development - pre-CPCN application (WI PSC REF#606657) | M7: =P7*1000*Guide!$B$81 | P7: 1203 | Q7: 345 | R7: Brillion (Town of) | S7: Calumet | T7: WI | U7: United States | W7: 48213 | X7: 48395 | Y7: 47483 | Z7: Power Generation | AA7: Generation | AB7: New Capacity/New Build | AC7: New Load Growth | AD7: Generation | AE7: Natural gas generation - electrical BoP (MV/LV power, tray/control & instrumentation cable, substation) | AF7: Greenfield | AG7: Traditional | AH7: Natural Gas | AI7: No | AJ7: *RPBD* AWARD (PO) DATE BASIS: CPCN filing expected fall 2026 (PSC docket 5-CE-162), construction start Q4 2027, COD Dec 2031 -> BOP cable likely released in phases Q4 2028-Q2 2030 (award date set to COD-24 mo). EPC not named (Invenergy has used Kiewit elsewhere - unconfirmed). We Energies (Brendan Conway, spokesperson) may acquire; precedent: PSC approved Invenergy Red Oak Ridge/Foundry Ridge for We Energies Oct 15, 2026. Yes Energy shows 2030 COD; public sources Dec 2031. | AK7: Build relationship with Daniel Birmingham (Invenergy); watch PSC 5-CE-162 CPCN for EPC; get on EPC approved-vendor list in 2027. | AL7: *RPBD* OVERVIEW: Proposed ~1,203 MW natural-gas simple-cycle PEAKING plant by Invenergy, planned alongside the 750 MW Union Depot Energy Center combined cycle on an adjacent site (~1.95 GW total campus). Alternate site identified in Town of Woodville. TECHNOLOGY & EQUIPMENT: 5x GE 7F.05 combustion turbines with GE H35 generators, each with generator step-up transformer; designed for continuous duty but expected to run mainly at peak. SITE: GREENFIELD - privately owned agricultural land east of WI-57, north of US-10, Town of Brillion, Calumet County (acreage not yet published; see PSC engineering plan). INTERCONNECTION: three 345 kV overhead gen-tie lines to ATC's Forest Junction 345 kV substation (ATC also expanding 345 kV lines south to new Sheboygan River substation). OWNERSHIP/STATUS: Developer Invenergy; We Energies listed it in rate-case planning (possible acquirer, needs PSC approval). Engineering plan filed Aug 2026; CPCN application expected fall 2026 (PSC docket 5-CE-162); construction start targeted Q4 2027; COD ~Dec 2031. EPC not yet selected. INVESTMENT: Total project investment Not disclosed; est. W&C value $9,624,000 ($8/kW). W&C NEEDS (simple-cycle peaker): MV power cable (5-35 kV) for auxiliary transformers, MV switchgear, fuel-gas compressors and black-start/aux systems; 600V power & TC-ER tray cable for turbine packages, MCCs, fuel oil forwarding (if dual fuel) and SCR/ammonia systems; shielded instrumentation & control cable; bare copper grounding grid per unit and switchyard; switchyard control/relay cable; building wire for control/admin buildings. Less cable per MW than a CC (no HRSG/steam cycle). Plus overhead conductor for 3x 345 kV gen-ties; large opportunity if bundled with Union Depot CC. Ref: https://dailyreporter.com/2026/08/31/invenergy-proposes-two-natural-gas-plants-calumet-county/ | https://fox11online.com/news/local/calumet-county-power-plant-proposed-energy-centers-town-of-brillion-power-megawatts-gigawatts-we-energies-invenergy-town-of-woodville-forest-junction-union-depot | https://forestjunctionenergycenter.invenergy.com/ | https://www.nbc26.com/lakeshore/neighbors-push-back-against-proposed-natural-gas-facility-in-town-of-brillion | AO7: 1.2 | AP7: Forest Junction Energy Center | AQ7: ATC Forest Junction 345 kV Substation | AS7: 10019673557
A8: Orange County Advanced Power Station (OCAPS) | B8: Entergy Texas | C8: Closed | D8: Orange County Advanced Power Station Project (Yes Energy); OCAPS; Sabine Power Plant site; PUCT Docket 52487 | E8: IOU | F8: Keith Pollock, Project Director, OCAPS | G8: Entergy Texas | I8: EPC | K8: In service ~Oct 14, 2026 (was Under Construction in Yes Energy) | M8: =P8*1000*Guide!$B$81 | P8: 1215 | R8: Bridge City | S8: Orange | T8: TX | U8: United States | W8: 46309 | X8: 46491 | Y8: 45944 | Z8: Power Generation | AA8: Generation | AB8: New Capacity/New Build | AC8: New Load Growth | AD8: Generation | AE8: Natural gas generation - electrical BoP (MV/LV power, tray/control & instrumentation cable, substation) | AF8: Brownfield | AG8: Traditional | AH8: Natural Gas | AI8: No | AJ8: *RPBD* In service Oct 14, 2026 - new-build window passed (~2023-24). New-build award passed; aftermarket/MRO opportunity (first spring outage ~Apr 2027 - estimate, not sourced). Other contacts: David Borde (CEO, Entergy Texas); James Malone (Dir. Business Development, Sargent & Lundy). | AK8: Aftermarket/spares with Keith Pollock and Entergy fossil ops supply chain; use TIC/S&L relationship for Entergy program plants. | AL8: *RPBD* OVERVIEW: 1,215 MW natural-gas COMBINED-CYCLE plant, Entergy Texas' newest unit; entered commercial service Oct 14, 2026; serves ~230,000 homes in industrial Southeast Texas. TECHNOLOGY & EQUIPMENT: Mitsubishi Power powertrain - 2x M501JAC gas turbines, HRSGs and steam turbine (2x1 configuration); dual-fuel, hydrogen-capable (30% H2 at start, designed for up to 100%). SITE: BROWNFIELD - ~26.2-acre footprint inside/adjacent to Entergy Texas' existing Sabine Power Plant in Bridge City, Orange County (existing gas plant with transmission and water infrastructure). OWNERSHIP/EPC: Entergy Texas; EPC consortium Mitsubishi Power (powertrain), Sargent & Lundy (engineer of record), TIC - The Industrial Company (constructor). STATUS: Construction Apr 2023-2026, first fire Apr 2026, in service Oct 2026. INVESTMENT: Total project investment ~$1.2B (power-eng.com); Yes Energy $555M not confirmed; est. W&C value $9,720,000 ($8/kW). W&C NEEDS: New-build cable scope complete. Remaining: MRO/spares (MV, 600V, tray & instrumentation cable), outage and warranty/punch-list work; reference project for the same TIC/S&L/Mitsubishi team now building Entergy's LA/MS/AR plants. Ref: https://www.click2houston.com/news/local/2026/10/14/entergy-texas-orange-county-advanced-power-station-now-delivering-power-to-southeast-texas/ | https://www.power-eng.com/gas/turbines/entergy-texas-1-2-gw-ccgt-plant-is-now-online/ | https://www.sargentlundy.com/projects/orange-county-advanced-power-station/ | AS8: 10017200239
A9: Vast Sands Power I (Vistra Permian Basin expansion) | B9: Vistra Corp (Luminant) | C9: Open | D9: Vast Sands Power I (TEF - Due Diligence) (Yes Energy); ERCOT 28INR0105 (+ Vast Sands II 28INR0109); Permian Power I & II; Permian Power I LLC | E9: IPP | F9: Jim Burke, President & CEO | G9: Vistra / Luminant Generation Co | I9: IPP | K9: Advanced Development - FID Sep 2025; TEF loan Jun 2026 | M9: =P9*1000*Guide!$B$81 | P9: 440 | R9: Monahans | S9: Ward | T9: TX | U9: United States | W9: 46874 | X9: 47058 | Y9: 46418 | Z9: Power Generation | AA9: Generation | AB9: New Capacity/New Build | AC9: New Load Growth | AD9: Generation | AE9: Natural gas generation - electrical BoP (MV/LV power, tray/control & instrumentation cable, substation) | AF9: Brownfield | AG9: Traditional | AH9: Natural Gas | AI9: No | AJ9: *RPBD* AWARD (PO) DATE BASIS: FID Sep 2025; $583M TEF loan (Jun 2026) with $172M drawn by 6/30/26 = heavy early spend; COD May/Jun 2028 -> cable window Dec 2026-Jun 2027, early packages may already be placed. EPC/OEM not public. No project-level contact public - Jim Burke is exec-level only (quoted in releases). TCEQ NAPD for permit 178462 should list applicant contact (Luminant Generation Co). | AK9: URGENT: identify EPC via TCEQ 178462 NAPD / Industrial Info; find Luminant project contact; quote both units (880 MW). | AL9: *RPBD* OVERVIEW: Vistra/Luminant expansion of the existing Permian Basin Power Plant in Monahans - two new large natural-gas SIMPLE-CYCLE units totaling 860 MW (ERCOT queue: Vast Sands Power I 28INR0105 and II 28INR0109, ~440 MW each), taking the site from 325 MW to 1,185 MW. Driven by Permian oil & gas load growth. TECHNOLOGY & EQUIPMENT: 2x dual-fuel (gas/oil) advanced-class combustion turbine generators with SCR and oxidation catalyst (TCEQ permit 178462); ~440 MW per unit implies H/J-class frames (OEM not published). SITE: BROWNFIELD - existing operating gas plant at 600 N Yucca Dr, Monahans, Ward County (existing 5x 65 MW CTs, gas supply and ERCOT interconnection in place); acreage not published. OWNERSHIP/STATUS: Permian Power I LLC (Vistra). FID Sep 29, 2025; $583M Texas Energy Fund loan Jun 2026 ($172M drawn by Jun 30, 2026); COD May/Jun 2028. EPC not public. INVESTMENT: Total project investment Not disclosed; financed in part by $583M Texas Energy Fund loan (3.0%, Jun 2026); est. W&C value $3,520,000 ($8/kW). W&C NEEDS (simple-cycle peaker): MV power cable (5-35 kV) for auxiliary transformers, MV switchgear, fuel-gas compressors and black-start/aux systems; 600V power & TC-ER tray cable for turbine packages, MCCs, fuel oil forwarding (if dual fuel) and SCR/ammonia systems; shielded instrumentation & control cable; bare copper grounding grid per unit and switchyard; switchyard control/relay cable; building wire for control/admin buildings. Less cable per MW than a CC (no HRSG/steam cycle). Dual-fuel adds fuel-oil system cabling. Ref: https://gov.texas.gov/news/post/governor-abbott-announces-texas-energy-fund-loan-for-860-mw-of-new-power-in-west-texas | https://investor.vistracorp.com/2025-09-29-Vistra-Announces-Plans-to-Build-New-Gas-Fueled-Dispatchable-Power-Units-in-the-Permian-Basin | https://www.gem.wiki/Permian_Power_power_station | https://www.tceq.texas.gov/downloads/permitting/air/bilingual/pending-permit-notices/178462-pls-english.pdf | AS9: 10018470514
A10: Plant Yates Unit 9 (Yates CT Units 8-10) | B10: Georgia Power (Southern Company) | C10: In Progress | D10: Plant Yates Project (June 2027) (Yes Energy); Yates CT Units 8, 9, 10 | E10: IOU | F10: Rick Anderson, SVP & Senior Production Officer | G10: Georgia Power | I10: EPC | K10: Under Construction - Unit 9 equipment on site Dec 2025 | M10: =P10*1000*Guide!$B$81 | P10: 482.8 | R10: Newnan | S10: Coweta | T10: GA | U10: United States | W10: 46568 | X10: 46751 | Y10: 46203 | Z10: Power Generation | AA10: Generation | AB10: New Capacity/New Build | AC10: New Load Growth | AD10: Generation | AE10: Natural gas generation - electrical BoP (MV/LV power, tray/control & instrumentation cable, substation) | AF10: Brownfield | AG10: Traditional | AH10: Natural Gas | AI10: No | AJ10: *RPBD* LOW PROBABILITY: Unit 8 COD Q4 2026, Unit 9 Q2 2027, Unit 10 Q3 2027 (Southern Q2 2026 10-Q). Bulk cable likely bought 2024-25 by Mitsubishi/B&V consortium (award date set to COD-12 mo; already passed). Remaining: Unit 10 top-ups, change orders, spares. Other contacts: Cheryl Boddiford (SVP Mfg & Supply Chain, Mitsubishi Power); Rick Janik (B&V PM on Plant Barry Unit 8 - same EPC pairing, not confirmed for Yates). GA PSC docket 55931. | AK10: Relationship/spares play via B&V site procurement; position with Mitsubishi/B&V for next Georgia Power CT/CC builds. | AL10: *RPBD* OVERVIEW: Georgia Power's first new gas turbines in a decade - three simple-cycle PEAKING units (~1,300 MW total, ~442-463 MW each) at Plant Yates; this record is Unit 9 (COD Q2 2027). Unit 8 Q4 2026, Unit 10 Q3 2027. ~600 construction jobs. Driven by Georgia load growth (data centers/industrial). TECHNOLOGY & EQUIPMENT: 3x Mitsubishi Power M501JAC air-cooled combustion turbines with Mitsubishi Electric VP-X generators (assembled in Savannah, GA); dual-fuel gas/oil; ~30-minute start; hydrogen-capable with modifications. SITE: BROWNFIELD - existing Plant Yates generating site (former coal/gas station on the Chattahoochee River), Newnan, Coweta County, with existing transmission yard. OWNERSHIP/EPC: Georgia Power (Southern Company); EPC consortium Mitsubishi Power Americas + Black & Veatch Construction (contract Jan 12, 2024). Cost not public (PSC staff ~$1B for 3 units). GA PSC monitoring docket 55931. INVESTMENT: Total project investment Not public; PSC staff ~$1B for 3 units; est. W&C value $3,862,400 ($8/kW). W&C NEEDS (simple-cycle peaker): MV power cable (5-35 kV) for auxiliary transformers, MV switchgear, fuel-gas compressors and black-start/aux systems; 600V power & TC-ER tray cable for turbine packages, MCCs, fuel oil forwarding (if dual fuel) and SCR/ammonia systems; shielded instrumentation & control cable; bare copper grounding grid per unit and switchyard; switchyard control/relay cable; building wire for control/admin buildings. Less cable per MW than a CC (no HRSG/steam cycle). Window: bulk cable for all 3 units most likely purchased 2024-25; remaining top-ups, change orders, spares. Ref: https://www.georgiapower.com/news-hub/press-releases/turbine-generator-unit-9-plant-yates.html | https://www.energy.gov/sites/default/files/2026-07/20260622_EnvReview_Completion_Yates.pdf | https://www.modernpowersystems.com/news/progress-at-1-3-gw-plant-yates-gas-fired-plant/ | AS10: 10018823691
A11: Ironwood Power Station | B11: Entergy Arkansas | C11: In Progress | D11: Ironwood Power Station 1A Project (Yes Energy); Lake Catherine 5 (LC5); EIA 69750 | E11: IOU | F11: Carlos Ruiz, VP, Power Development - New Generation | G11: Entergy Arkansas | I11: EPC | K11: Under Construction - groundbreaking Aug 20, 2026 | M11: =P11*1000*Guide!$B$81 | P11: 446 | R11: Jones Mill (Malvern) | S11: Hot Spring | T11: AR | U11: United States | W11: 47118 | X11: 47299 | Y11: 46477 | Z11: Power Generation | AA11: Generation | AB11: New Capacity/New Build | AC11: Replacement / End-of-Life | AD11: Generation | AE11: Natural gas generation - electrical BoP (MV/LV power, tray/control & instrumentation cable, substation) | AF11: Brownfield | AG11: Traditional | AH11: Natural Gas | AI11: No | AJ11: *RPBD* AWARD (PO) DATE BASIS: site construction Q2 2026-Q2 2028, groundbreaking Aug 20 2026, COD Q4 2028 -> bulk cable after underground/foundations ~Q1-Q2 2027. Best new-buy opportunity. TSL procures in its own name; S&L writes cable specs/BOMs. TSL address: 8900 Renner Blvd, Lenexa KS 66219. Other contacts: Laura Landreaux (CEO, Entergy AR); Louise Duncan (VP Power Plant Ops, Entergy AR); Jason Rees (Dir. Procurement, Entergy - LinkedIn, verify). Entergy supplier registration: esupplier@entergy.com. | AK11: Get on TSL Power Partners bidder list (Kiewit/TIC Lenexa) and S&L approved-manufacturer list; register with Entergy supplier program. | AL11: *RPBD* OVERVIEW: 446 MW natural-gas SIMPLE-CYCLE combustion turbine (Entergy Arkansas 'Next Generation Arkansas'), replacing the 50+ year-old Lake Catherine Unit 4 (retiring end-2027). Formerly 'Lake Catherine 5'. ~260 peak construction jobs; Entergy prioritizing Arkansas contractors (vendor fair Mar 18, 2026). TECHNOLOGY & EQUIPMENT: single advanced-class combustion turbine generator, hydrogen-capable (30% co-fire, future 100% conversion); Mitsubishi implied by the TSL/Mitsubishi Entergy program. SITE: BROWNFIELD - ~20 acres within the existing Lake Catherine Power Generation site, Jones Mill near Malvern, Hot Spring County; reuses existing gas, water and transmission infrastructure. OWNERSHIP/EPC: Entergy Arkansas; EPC TSL Power Partners (TIC/Kiewit + Sargent & Lundy) with Mitsubishi Power Americas (per TIC Entergy Program page). APSC CCN approved Apr 2025; site construction Q2 2026-Q2 2028; groundbreaking Aug 20, 2026; COD Q4 2028. Cost recovered via GAJA rider (not disclosed). INVESTMENT: Total project investment Not disclosed (GAJA rider); est. W&C value $3,568,000 ($8/kW). W&C NEEDS (simple-cycle peaker): MV power cable (5-35 kV) for auxiliary transformers, MV switchgear, fuel-gas compressors and black-start/aux systems; 600V power & TC-ER tray cable for turbine packages, MCCs, fuel oil forwarding (if dual fuel) and SCR/ammonia systems; shielded instrumentation & control cable; bare copper grounding grid per unit and switchyard; switchyard control/relay cable; building wire for control/admin buildings. Less cable per MW than a CC (no HRSG/steam cycle). Ref: https://www.entergy.com/news/entergy-arkansas-breaks-ground-on-ironwood-power-station | https://www.modernpowersystems.com/news/entergy-arkansas-starts-construction-on-446-mw-ironwood-power-station/ | https://www.entergy.com/news/ironwood-power-plant-vendor-fair-for-arkansas-contractors-announced | AS11: 10019705142
A12: Person County Combined Cycle 1 (CC1) | B12: Duke Energy Progress | C12: In Progress | D12: Person County Advanced CC1 (Yes Energy); Person County Energy Complex (Roxboro site); NCUC E-2 Sub 1318; sister CC2 E-2 Sub 1349 | E12: IOU | F12: John Robert Smith Jr., General Manager, New Gas Generation Development | G12: Duke Energy Progress / NCEMC (co-owner ~225 MW) | I12: EPC | K12: Under Construction - groundbreaking Feb 2026; GTs arriving 2026 | M12: =P12*1000*Guide!$B$81 | P12: 1360 | R12: Semora (Roxboro) | S12: Person | T12: NC | U12: United States | W12: 47118 | X12: 47299 | Y12: 46416 | Z12: Power Generation | AA12: Generation | AB12: New Capacity/New Build | AC12: New Load Growth | AD12: Generation | AE12: Natural gas generation - electrical BoP (MV/LV power, tray/control & instrumentation cable, substation) | AF12: Brownfield | AG12: Traditional | AH12: Natural Gas | AI12: No | AJ12: *RPBD* AWARD (PO) DATE BASIS: Zachry EPC Aug 2025, groundbreaking Feb 13 2026, first GE Vernova GT on site Jul 23 2026, Zachry craft hiring from Jul 2026; COD Q4 2028 (SC ORS) -> bulk MV/600V/tray bid likely now; act immediately. CC2 (Q4 2029, likely Zachry) -> separate close ~12/15/2027. Other contacts: Ralph Biediger (EPC Group President, Zachry); Bill Norton (Duke spokesperson). Utility is Duke Energy Progress (not DEC). | AK12: Engage Zachry procurement now for CC1 (+CC2 combined buy); contact John Robert Smith Jr. (Duke PM&C). | AL12: *RPBD* OVERVIEW: 1,360 MW natural-gas COMBINED-CYCLE block (first of two identical blocks, 2,720 MW total) at Duke's 'Person County Energy Complex' (Roxboro plant), enabling retirement of Roxboro coal units 1 & 4. NCEMC co-owns ~225 MW. Nearby Microsoft-owned Person County Mega Park (~1,350 acres). TECHNOLOGY & EQUIPMENT: 2x1 advanced-class, hydrogen-capable CC - 2x GE Vernova gas turbines, 2x HRSGs, 1x GE Vernova steam turbine generator (~450 tons); first GT on site Jul 23, 2026. SITE: BROWNFIELD - ~50 acres of undeveloped land within the existing Roxboro coal plant property, Semora Road side, Semora/Roxboro, Person County. OWNERSHIP/EPC: Duke Energy Progress (majority) + NCEMC; full EPC Zachry Group (awarded Aug 2025). NCUC CPCN Oct 2025; groundbreaking Feb 13, 2026; COD Q4 2028 (CC2 Q4 2029). Cost ~$2.13B (CC1). Two new tie lines from the site. INVESTMENT: Total project investment ~$2.13B (CC1, DEP Class 3 estimate); est. W&C value $10,880,000 ($8/kW). W&C NEEDS (combined cycle): MV power cable (5-35 kV) from unit auxiliary/station service transformers to plant MV switchgear and large motors (boiler feed pumps, condensate & circulating water pumps, cooling tower/ACC fans, gas compressors); 600V power & TC-ER tray cable for MCCs, HRSG/steam-turbine auxiliaries, BOP and water treatment; shielded instrumentation & control cable (DCS, turbine controls, CEMS); bare copper grounding grid; switchyard control/relay cable; lighting, building wire and fire-alarm in admin/warehouse/control buildings. CC2 doubles the scope ~1 year later with the same EPC. Ref: https://zachrygroup.com/press-releases/Duke_Energy_Awards_EPC_Contract_for_the_first_Person_County_Combined_Cycle_Project_to_Zachry_Group.html | https://www.duke-energy.com/info/person | https://www.theassemblync.com/news/business/person-county-microsoft-data-center-nondisclosure-agreements/ | AP12: Person County CC1 | AQ12: Duke Energy Progress grid (two new tie lines) | AS12: 10017400436
A13: Delta Blues Advanced Power Station | B13: Entergy Mississippi | C13: In Progress | D13: Delta Blues Power Project (May 2028) (Yes Energy); EIA 67914; Superpower Mississippi; replaces Gerald Andrus plant | E13: IOU | F13: Ernest Rufus, Senior Manager, Capital Projects (Delta Blues & Vicksburg) | G13: Entergy Mississippi | I13: EPC | K13: Under Construction - HRSG erection underway | M13: =P13*1000*Guide!$B$81 | P13: 754 | R13: Greenville | S13: Washington | T13: MS | U13: United States | W13: 46874 | X13: 47058 | Y13: 46356 | Z13: Power Generation | AA13: Generation | AB13: New Capacity/New Build | AC13: Replacement / End-of-Life | AD13: Generation | AE13: Natural gas generation - electrical BoP (MV/LV power, tray/control & instrumentation cable, substation) | AF13: Brownfield | AG13: Traditional | AH13: Natural Gas | AI13: No | AJ13: *RPBD* MAIN WINDOW LIKELY PASSED: HRSG erection May 2026 ("anchor bolts up"), COD May 2028 -> bulk cable likely bought; remaining late releases, change orders, I&C top-ups. EPC TSL Power Partners (Kiewit/TIC), Kiewit 200+ on site. Use as entry to TSL Entergy program buy for sister plants. Yes Energy 879 MW/$651M vs Entergy 754 MW/$1.2B. | AK13: Contact Ernest Rufus and TSL/TIC procurement now - target program buy for Vicksburg/Ironwood/Waterford. | AL13: *RPBD* OVERVIEW: 754 MW natural-gas COMBINED-CYCLE plant ('Superpower Mississippi'), replacing the aging Gerald Andrus Steam Electric Station; serves ~385,000 homes across Entergy Mississippi's 45 counties. TECHNOLOGY & EQUIPMENT: 1x1 combined cycle - Mitsubishi Power M501JAC gas turbine (per GEM), HRSG (modules being lifted May 2026), steam turbine; dual-fuel, hydrogen-blend capable. SITE: BROWNFIELD-ADJACENT - new footprint within ~1 mile of the Andrus plant, 85 Stokes King Road, Greenville, Washington County; reuses Andrus transmission and gas infrastructure (acreage not published). INTERCONNECTION: ~1.5 miles of new transmission line to the existing substation next to Andrus; new Delta Blues substation. OWNERSHIP/EPC: Entergy Mississippi; EPC TSL Power Partners (Kiewit Power Constructors / TIC; Kiewit 200+ on site). Groundbreaking Nov 2024; COD May 2028; ~$1.2B. INVESTMENT: Total project investment ~$1.2B (Entergy); Yes Energy $651M not confirmed; est. W&C value $6,032,000 ($8/kW). W&C NEEDS (combined cycle): MV power cable (5-35 kV) from unit auxiliary/station service transformers to plant MV switchgear and large motors (boiler feed pumps, condensate & circulating water pumps, cooling tower/ACC fans, gas compressors); 600V power & TC-ER tray cable for MCCs, HRSG/steam-turbine auxiliaries, BOP and water treatment; shielded instrumentation & control cable (DCS, turbine controls, CEMS); bare copper grounding grid; switchyard control/relay cable; lighting, building wire and fire-alarm in admin/warehouse/control buildings. Plus ~1.5 mi transmission line conductor and substation cable. Status: above-ground erection since May 2026 - bulk cable likely ordered. Ref: https://www.power-eng.com/gas/combined-cycle/entergy-mississippi-breaks-ground-on-754-mw-combined-cycle-plant/ | https://www.entergy.com/blog/delta-blues-reaches-important-milestone-in-construction | https://www.gem.wiki/Delta_Blues_Advanced_Power_Station | https://opcgis.deq.state.ms.us/ensearchonline/ai_info.aspx?ai=86260 | AO13: 1.5 | AP13: Delta Blues Advanced Power Station | AQ13: Existing substation at Gerald Andrus station | AS13: 10018299981
A14: Vicksburg Advanced Power Station | B14: Entergy Mississippi | C14: In Progress | D14: Vicksburg Advanced Power Project (Aug 2028) (Yes Energy); EIA 69223; former Baxter Wilson site; Superpower Mississippi | E14: IOU | F14: Ernest Rufus, Senior Manager, Capital Projects (Vicksburg role to confirm) | G14: Entergy Mississippi | I14: EPC | K14: Under Construction - groundbreaking Oct 2025 | M14: =P14*1000*Guide!$B$81 | P14: 754 | R14: Vicksburg | S14: Warren | T14: MS | U14: United States | W14: 46966 | X14: 47150 | Y14: 46371 | Z14: Power Generation | AA14: Generation | AB14: New Capacity/New Build | AC14: New Load Growth | AD14: Generation | AE14: Natural gas generation - electrical BoP (MV/LV power, tray/control & instrumentation cable, substation) | AF14: Brownfield | AG14: Traditional | AH14: Natural Gas | AI14: No | AJ14: *RPBD* URGENT: groundbreaking Oct 21 2025, Baxter Wilson demolition Dec 2025, COD Aug 2028 -> cable window now through ~Feb 2027; may be partly placed if TSL bought with Delta Blues. Linked contextually to AWS $3B Vicksburg campus. Entergy MS media line 769-262-0745. | AK14: Engage TSL/TIC procurement now; confirm Ernest Rufus covers Vicksburg (confirmed on Delta Blues only) and ask for the named project buyer. | AL14: *RPBD* OVERVIEW: 754 MW natural-gas COMBINED-CYCLE plant, next phase of 'Superpower Mississippi'; ~560 construction jobs, 21 permanent. Contextually linked to Amazon/AWS's $3B Vicksburg data-center campus (AWS covers its service-extension costs). TECHNOLOGY & EQUIPMENT: combined cycle (gas turbine + HRSG + steam turbine), hydrogen-blend capable and carbon-capture enabled; turbine OEM not confirmed (Mitsubishi likely via TSL/Mitsubishi Entergy program). SITE: BROWNFIELD - former Baxter Wilson Steam Electric Station (1960s gas/oil plant, retired 2022; large structures demolished Dec 17, 2025), 770 Kemp Bottom Rd, Vicksburg, Warren County, on the Mississippi River; existing transmission/gas corridors (acreage not published). OWNERSHIP/EPC: Entergy Mississippi; EPC TSL Power Partners (TIC/Kiewit + Sargent & Lundy) with Mitsubishi Power Americas (per TIC Entergy Program page). Groundbreaking Oct 21, 2025; COD Aug 2028; ~$1.2B. INVESTMENT: Total project investment ~$1.2B (Entergy); Yes Energy $700M not confirmed; est. W&C value $6,032,000 ($8/kW). W&C NEEDS (combined cycle): MV power cable (5-35 kV) from unit auxiliary/station service transformers to plant MV switchgear and large motors (boiler feed pumps, condensate & circulating water pumps, cooling tower/ACC fans, gas compressors); 600V power & TC-ER tray cable for MCCs, HRSG/steam-turbine auxiliaries, BOP and water treatment; shielded instrumentation & control cable (DCS, turbine controls, CEMS); bare copper grounding grid; switchyard control/relay cable; lighting, building wire and fire-alarm in admin/warehouse/control buildings. Ref: https://www.entergymississippi.com/generation/vicksburg | https://www.powermag.com/entergy-mississippi-adding-third-gas-fired-power-plant-to-superpower-strategy/ | https://www.datacenterdynamics.com/en/news/amazon-to-build-3bn-data-center-campus-in-vicksburg-mississippi/ | AS14: 10019088992
A15: Sycamore Riverside Energy Center | B15: Indiana Michigan Power (AEP) | C15: Open | D15: Sullivan Generating Station (May 2027) (Yes Energy); Sullivan Generating Station 1 & 2 (PJM AB1-087/AB1-088); IURC Cause 46389 | E15: IOU | F15: John E. Niland, VP, New Technology & Thermal Development | G15: Invenergy (to be acquired by I&M at COD) | I15: Developer | K15: Advanced Development - IURC CPCN order expected end-2026 | M15: =P15*1000*Guide!$B$81 | P15: 918 | Q15: 345 | R15: Fairbanks Township | S15: Sullivan | T15: IN | U15: United States | W15: 47208 | X15: 47391 | Y15: 46568 | Z15: Power Generation | AA15: Generation | AB15: New Capacity/New Build | AC15: New Load Growth | AD15: Generation | AE15: Natural gas generation - electrical BoP (MV/LV power, tray/control & instrumentation cable, substation) | AF15: Brownfield | AG15: Traditional | AH15: Natural Gas | AI15: No | AJ15: *RPBD* AWARD (PO) DATE BASIS: Boldt lists construction Sep 2026-Feb 2029 (built at risk before IURC order expected end-2026); COD Mar 31 2029 -> cable window Q1-Q3 2027; Invenergy/Boldt buy, not I&M. Other contacts: Daniel Runyan (SVP Development, Invenergy); Steve Baker (President & COO, I&M); Timothy B. Gaul (Dir. Regulated Infrastructure Development, AEPSC); Timothy C. Kerns (Sterling Industrial - owner's engineer witness). PJM (not MISO), 918 MW SC (not 1,150 MW CC). Existing Salesforce opportunity (CRM: 930 MW combined cycle, award 10/1/2026) - update CRM to 918 MW simple cycle; merge Sullivan Generating Station 1 & 2 duplicates. | AK15: Engage Boldt procurement and Invenergy thermal construction now (Q4 2026-Q1 2027) for MV/600V/tray bid lists. | AL15: *RPBD* OVERVIEW: ~918-935 MW natural-gas SIMPLE-CYCLE PEAKING plant developed by Invenergy and to be acquired by Indiana Michigan Power (AEP) at COD (Mar 31, 2029) to meet data-center-driven load growth (AWS, Google, Microsoft). Formerly queued as Sullivan Generating Station 1 & 2 (1,150 MW CC concept). TECHNOLOGY & EQUIPMENT: 4x GE Vernova 7F.05 combustion turbines (~232 MW each), dual-fuel natural gas with ultra-low-sulfur distillate backup; gas via ~5.5-mile 24-inch ONEOK lateral. SITE: BROWNFIELD-ADJACENT - next to I&M's retired, demolished Breed coal plant, CR 925N, Fairbanks Township, Sullivan County; ~64-acre plant footprint within ~356-acre parcel (local meeting summary - verify). Invenergy holds land under purchase option. INTERCONNECTION: AEP/I&M Sullivan 345 kV station (new 345 kV breakers), PJM. OWNERSHIP/STATUS: Invenergy (developer) -> I&M; IURC Cause 46389 order expected end-2026; constructor The Boldt Company lists construction Sep 2026-Feb 2029; ~$500M capital (Invenergy). INVESTMENT: Total project investment ~$500M capital investment (Invenergy); est. W&C value $7,344,000 ($8/kW). W&C NEEDS (simple-cycle peaker): MV power cable (5-35 kV) for auxiliary transformers, MV switchgear, fuel-gas compressors and black-start/aux systems; 600V power & TC-ER tray cable for turbine packages, MCCs, fuel oil forwarding (if dual fuel) and SCR/ammonia systems; shielded instrumentation & control cable; bare copper grounding grid per unit and switchyard; switchyard control/relay cable; building wire for control/admin buildings. Less cable per MW than a CC (no HRSG/steam cycle). Dual-fuel adds fuel-oil system cabling. Ref: https://www.aep.com/news/stories/view/11850/ | https://sycamoreriverside.invenergy.com/about-project | https://www.pjm.com/pub/planning/project-queues/facilities/ab1087_fac.pdf | https://www.gem.wiki/Sycamore_Riverside_Energy_Center | AS15: 10019254864
A16: Franklin Farms Power Station (Units 1 & 2) | B16: Entergy Louisiana | C16: In Progress | D16: Titanium Advanced Power Station CCCT Project (Yes Energy / air permit); EIA 68214; MISO E0014; LPSC U-37425 | E16: IOU | F16: Nicholas D. Pressler, Director, Power Development | G16: Entergy Louisiana (state-owned Franklin Farms site) | I16: EPC | K16: Under Construction - groundbreaking Dec 1, 2025 | M16: =P16*1000*Guide!$B$81 | P16: 1508 | Q16: 500 | R16: Holly Ridge | S16: Richland Parish | T16: LA | U16: United States | W16: 47088 | X16: 47270 | Y16: 46416 | Z16: Power Generation | AA16: Generation | AB16: New Capacity/New Build | AC16: Load Interconnection | AD16: Generation | AE16: Natural gas generation - electrical BoP (MV/LV power, tray/control & instrumentation cable, substation) | AF16: Greenfield | AG16: Traditional | AH16: Natural Gas | AI16: Yes | AJ16: *RPBD* AWARD (PO) DATE BASIS: groundbreaking Dec 1 2025, COD Dec 2028; IMI valve order Sep 2026 says detailed engineering still active -> cable window Dec 2026-Jun 2027, early MV/grounding packages possibly Q4 2026. EPC TSL Power Partners/Kiewit + Mitsubishi. Other contacts: Phillip May (CEO, Entergy LA); Carlos Ruiz (VP Power Development, Entergy); Jim Niemiec (VP & Chief Supply Chain Officer, Entergy); media Brandon Scardigli 504-576-4132. Separate 500 kV transmission opportunity. | AK16: Engage TSL/TIC procurement now; contact Nicholas Pressler; open separate 500 kV transmission opportunity. | AL16: *RPBD* OVERVIEW: ~1,508 MW natural-gas COMBINED-CYCLE station (two units) built to power Meta's Hyperion AI data-center campus; Meta pays the plants' full revenue requirement for 15 years. Air permit name 'Titanium Advanced Power Station'. ~7 more Hyperion plants (~5.2 GW) proposed, LPSC vote Dec 2026. TECHNOLOGY & EQUIPMENT: 2x 1x1 combined-cycle blocks - Mitsubishi Power M501JAC gas turbines, HRSGs, steam turbines (~754-780 MW each); hydrogen-capable (30% co-fire), carbon-capture ready; IMI valve package (Sep 2026). SITE: GREENFIELD - former agricultural land on the state-owned Franklin Farms megasite (~1,400-2,250 acres total incl. Meta campus) along LA Hwy 183 near Holly Ridge, Richland Parish. INTERCONNECTION: Entergy 500 kV system - ~100 miles of new 500 kV lines (~$1.2B), eight new 230 kV lines, Sterlington 500 kV upgrades. OWNERSHIP/EPC: Entergy Louisiana; EPC TSL Power Partners (TIC/Kiewit + Sargent & Lundy) with Mitsubishi Power. LPSC approval Aug 2025; groundbreaking Dec 1, 2025; COD Dec 2028; ~$2.39B for both units. INVESTMENT: Total project investment ~$2.39B (Franklin Farms 1 & 2, LPSC testimony); est. W&C value $12,064,000 ($8/kW). W&C NEEDS (combined cycle): MV power cable (5-35 kV) from unit auxiliary/station service transformers to plant MV switchgear and large motors (boiler feed pumps, condensate & circulating water pumps, cooling tower/ACC fans, gas compressors); 600V power & TC-ER tray cable for MCCs, HRSG/steam-turbine auxiliaries, BOP and water treatment; shielded instrumentation & control cable (DCS, turbine controls, CEMS); bare copper grounding grid; switchyard control/relay cable; lighting, building wire and fire-alarm in admin/warehouse/control buildings. Separate opportunity: HV/500 kV transmission conductor and substation cable. Ref: https://www.entergy.com/news/entergy-louisiana-breaks-ground-on-new-state-of-the-art-generation-facilities-to-power-reliability-growth-and-innovation | https://www.ticus.com/entergy-program/ | https://www.gem.wiki/Franklin_Farms_power_station | https://www.datacenterdynamics.com/en/news/entergy-breaks-ground-on-two-natural-gas-plants-for-metas-2gw-data-center-in-richland-parish-louisiana/ | AS16: 10019228423
A17: Waterford 5 Power Station | B17: Entergy Louisiana | C17: Open | D17: Waterford 5 Project (June 2029) (Yes Energy); EIA 69184; MISO E0029; Waterford 5 & 6 | E17: IOU | F17: Nicholas D. Pressler, Director, Power Development | G17: Entergy Louisiana | I17: EPC | K17: Advanced Development - site prep since Nov 2025; construction late 2026 | M17: =P17*1000*Guide!$B$81 | P17: 754 | Q17: 500 | R17: Killona / Taft | S17: St. Charles Parish | T17: LA | U17: United States | W17: 47270 | X17: 47453 | Y17: 46660 | Z17: Power Generation | AA17: Generation | AB17: New Capacity/New Build | AC17: Load Interconnection | AD17: Generation | AE17: Natural gas generation - electrical BoP (MV/LV power, tray/control & instrumentation cable, substation) | AF17: Brownfield | AG17: Traditional | AH17: Natural Gas | AI17: Yes | AJ17: *RPBD* AWARD (PO) DATE BASIS: site prep since Nov 2025, main construction late 2026, COD 2029 -> cable window mid-2027-mid-2028. Waterford 6 (754 MW, ~Jul 2030, LPSC vote Dec 16 2026, same EPC) - pitch combined WF5+6 buy (~$3.75B program). Other contact: Michelle Berg (Entergy, parish council briefing - secondary source). | AK17: Pitch combined Waterford 5+6 cable package to TSL; contact Nicholas Pressler. | AL17: *RPBD* OVERVIEW: ~754-820 MW natural-gas COMBINED-CYCLE unit approved with Franklin Farms to support Meta's Hyperion load; paired with proposed Waterford 6 (754 MW, ~Jul 2030, LPSC vote Dec 16, 2026) - ~$3.75B WF5+6 program, 700+ construction jobs 2026-2030. TECHNOLOGY & EQUIPMENT: 1x1 combined cycle - Mitsubishi Power M501JAC gas turbine, HRSG, steam turbine (EIA: 2 generators, 820 MW nameplate). SITE: BROWNFIELD - existing Entergy Waterford generating complex at Killona/Taft, St. Charles Parish, on the Mississippi River (home to Waterford 1 & 2 gas/oil units and Waterford 3 nuclear); soft soils require ~100,000 truckloads of surcharge fill (site prep since Nov 2025). INTERCONNECTION: Waterford 500 kV substation via ~0.25-mile 500 kV gen-tie (MISO E0029). OWNERSHIP/EPC: Entergy Louisiana; EPC TSL Power Partners (TIC + Sargent & Lundy) per LPSC Waterford 6 filing. Main construction late 2026; COD 2029. Cost ~ $1.2B implied. INVESTMENT: Total project investment ~$1.2B implied (similar to each Franklin Farms unit); Yes Energy $1.75B not confirmed; est. W&C value $6,032,000 ($8/kW). W&C NEEDS (combined cycle): MV power cable (5-35 kV) from unit auxiliary/station service transformers to plant MV switchgear and large motors (boiler feed pumps, condensate & circulating water pumps, cooling tower/ACC fans, gas compressors); 600V power & TC-ER tray cable for MCCs, HRSG/steam-turbine auxiliaries, BOP and water treatment; shielded instrumentation & control cable (DCS, turbine controls, CEMS); bare copper grounding grid; switchyard control/relay cable; lighting, building wire and fire-alarm in admin/warehouse/control buildings. Plus 500 kV gen-tie; bundle Waterford 5 + 6 as one cable package. Ref: https://www.entergylouisiana.com/waterford5-6 | https://www.interconnection.fyi/project/miso-e0029 | https://www.entergy.com/blog/the-dirt-on-dirt-from-digging-soil-to-boosting-louisianas-economy | AO17: 0.25 | AP17: Waterford 5 Power Station | AQ17: Waterford 500 kV Substation | AS17: 10019089005
A18: AES Petersburg Unit 4 Repowered | B18: AES Indiana | C18: In Progress | D18: Petersburg Generating Station Unit 4 coal-to-gas conversion; IURC Cause 46022 (Units 3 & 4) | E18: IOU | F18: Brandi Davis-Handy, President | G18: AES Indiana | I18: EPC | K18: Under Construction - Unit 4 conversion outage 2026 | M18: =P18*1000*Guide!$B$81 | P18: 526 | R18: Petersburg | S18: Pike | T18: IN | U18: United States | W18: 46387 | X18: 46568 | Y18: 45930 | Z18: Power Generation | AA18: Generation | AB18: New Capacity/New Build | AC18: Regulatory / Policy | AD18: Generation | AE18: Natural gas generation - electrical BoP (MV/LV power, tray/control & instrumentation cable, substation) | AF18: Brownfield | AG18: Traditional | AH18: Natural Gas | AI18: No | AJ18: AWARD (PO) DATE BASIS: B&W full NTP Nov 2024, CDM Smith BOP NTP Aug 2025; Unit 4 outage Jun-Oct 2026, COD end-2026 (B&W: Q1 2027) -> BOP cable likely bought Q3-Q4 2025; window passed. Remaining: Unit 4 punch-list/change orders. MW (526) from CRM - unverified. Other contacts: Chris Riker (SVP, B&W Thermal); Todd Hillman (SVP, AES Indiana). | AK18: Chase remaining Unit 4 fill-in orders via B&W Construction / CDM Smith; leverage for future B&W coal-to-gas conversions. | AL18: OVERVIEW: Coal-to-natural-gas repowering of AES Indiana's Petersburg Unit 4 (with Unit 3), ending coal at the plant; IURC approved 5-0 Nov 2024 within AES's ~$1.1B Pike County package (incl. nearby 250 MW solar + 180 MWh storage). TECHNOLOGY & EQUIPMENT: boiler fuel switch on existing 1986 coal unit (not new CTs) - new B&W gas burners, ignitors and controls; gas heaters, flue-gas recirculation for NOx, process piping; new 1-mile Midwestern Gas Transmission lateral. SITE: BROWNFIELD - existing Petersburg coal generating station on the White River, Petersburg, Pike County. INTERCONNECTION: existing unit interconnection (no new gen-tie), MISO. OWNERSHIP/STATUS: AES Indiana; EPC Babcock & Wilcox (B&W Construction Co.), BOP by CDM Smith; Unit 3 outage Feb-May 2026, Unit 4 outage Jun-Oct 2026, COD end-2026/Q1 2027. INVESTMENT: ~$293M (excl. AFUDC). W&C NEEDS (coal-to-gas boiler conversion): MV power cable for new gas heaters, FGR fans and modified auxiliaries; 600V power & TC-ER tray cable for new burner management, ignitors, valves and BOP; shielded instrumentation & control cable for burner management system/DCS tie-ins; grounding for new gas yard. Retrofit scope - smaller than a new build, outage-driven buying. Ref: https://www.babcock.com/home/about/corporate/news/babcock-and-wilcox-receives-full-notice-to-proceed-on-246-million-contract-for-indiana-power-plant-coal-to-gas-fuel-switching-project | https://www.cdmsmith.com/en/projects/aes-coal-to-gas | https://aesindiana.com/press-release/aes-indiana-receives-approval-repower-remaining-petersburg-units-coal-natural-gas
A19: Trumbull Energy Center | B19: Clean Energy Future, LLC (KOSPO / KIND / Siemens Energy owners) | C19: Closed | D19: Trumbull Energy Center (adjacent to Lordstown Energy Center); Clean Energy Future-Trumbull; PJM AB1-105 | E19: IPP | F19: Logan Choi, President & CEO | G19: Trumbull Energy Center owners (KOSPO, KIND, Siemens Energy) | I19: EPC | K19: Operating - COD Jan 2026; completion ceremony Jun 24, 2026 | M19: =P19*1000*Guide!$B$81 | P19: 950 | Q19: 345 | R19: Lordstown | S19: Trumbull | T19: OH | U19: United States | W19: 46053 | X19: 46234 | Y19: 45322 | Z19: Power Generation | AA19: Generation | AB19: New Capacity/New Build | AC19: New Load Growth | AD19: Generation | AE19: Natural gas generation - electrical BoP (MV/LV power, tray/control & instrumentation cable, substation) | AF19: Greenfield | AG19: Traditional | AH19: Natural Gas | AI19: No | AJ19: Operating since Jan 2026 - new-build window passed (cable bought ~2023 after Nov 2022 NTP). Re-target as MRO/outage account (Hanwha/Siemens O&M) and use Gemma relationship for Argan pipeline (CPV Basin Ranch, Sandow Lakes). Developer is Clean Energy Future (William Siderewicz), not CPV. MW 940-977 by source. | AK19: Move to Closed/Operating; pursue MRO with plant team; leverage Gemma for current CCGT jobs. | AL19: OVERVIEW: ~940-953 MW (EIA 977 MW nameplate) baseload merchant combined-cycle plant next to the Lordstown Energy Center; commercial operation Jan 2026, completion celebrated Jun 24, 2026; framed around Midwest AI/data-center demand (no named offtaker). TECHNOLOGY & EQUIPMENT: dual-fuel 2x2x1 combined cycle - 2x Siemens Energy SGT6-8000H gas turbines, 2x HRSGs, 1x Siemens SST6-5000 steam turbine; 3x Hanwha fuel-gas compressors (9-yr maintenance contract). SITE: ~127 acres in Lordstown, Trumbull County (7733 Tod Ave SW, Warren OH 44481 - third-party). INTERCONNECTION: PJM AB1-105, Highland-Hanna 345 kV line (ATSI/FirstEnergy). OWNERSHIP/STATUS: owners KOSPO, KIND and Siemens Energy; developer Clean Energy Future LLC; EPC Gemma Power Systems (full NTP Nov 2022). INVESTMENT: ~$1.2B. W&C NEEDS: new-build scope complete; MRO/spares (MV, 600V, tray, instrumentation cable) for outages. Ref: https://www.tribtoday.com/news/local-news/2026/06/trumbull-energy-center-complete/ | https://www.gemmapower.com/our-work/combined-cycle/trumbull-energy-center/ | https://www.interconnection.fyi/project/pjm-ab1-105
A20: Socrates South Power Generation | B20: Will-Power OH, LLC (Williams) | C20: Closed | D20: Socrates South (Williams Power Innovation); OPSB 25-0185-EL-BLN | E20: IPP | F20: Chad Zamarin, President & CEO | G20: Will-Power OH, LLC | I20: Owner/End User | K20: Operating - placed in service late Jul 2026 | M20: =P20*1000*Guide!$B$81 | P20: 200 | R20: New Albany | S20: Licking | T20: OH | U20: United States | W20: 46234 | X20: 46418 | Y20: 45838 | Z20: Power Generation | AA20: Generation | AB20: New Capacity/New Build | AC20: Load Interconnection | AD20: Generation | AE20: Natural gas generation - electrical BoP (MV/LV power, tray/control & instrumentation cable, substation) | AF20: Greenfield | AG20: Traditional | AH20: Natural Gas | AI20: Yes | AJ20: Operating since late Jul 2026 (~14 months site-to-power) - window passed. Use as reference case to get on Williams approved-vendor list for its next Power Innovation behind-the-meter projects (Blackstone JV covers 5 projects). EPC not public (check OPSB dockets). | AK20: Mark Closed; pursue Williams Power Innovation follow-on sites; find EPC via OPSB 25-0185 docket. | AL20: OVERVIEW: 200 MW behind-the-meter gas generation plant dedicated to Meta (Sidecat LLC) at the New Albany data-center campus (Prometheus AI cluster) under a 10-yr fixed-price deal (+5-yr option); in service late Jul 2026, on time and on budget. TECHNOLOGY & EQUIPMENT: simple-cycle aeroderivative/industrial turbines + reciprocating engines - filed fleet 3x Solar Titan 250, 9x PGM 130, 3x Siemens SGT-400, 15x Caterpillar 3520 engines, 8x Cat C15 500 kW diesel backup (split between North/South not public). SITE: GREENFIELD - ~20 acres in New Albany International Business Park, Licking County; two 24-inch gas laterals. INTERCONNECTION: no grid connection (OPSB condition) - on-site switching/internal substations feed Meta's adjacent campus. OWNERSHIP/STATUS: Will-Power OH LLC (Williams); Blackstone holds 49% of Power Innovation JV. INVESTMENT: ~$1.6B (North + South + pipeline). W&C NEEDS (behind-the-meter / on-site generation): MV power cable (5-35 kV) collecting many turbine/engine units to on-site switching and plant substations and feeders to the data-center campus; 600V power & TC-ER tray cable for unit packages, MCCs, gas conditioning/compression, BESS and cooling; shielded instrumentation & control cable (unit controls, microgrid/SCADA); extensive bare copper grounding; switchgear/substation control cable; building wire for control and admin buildings. High unit count = high cable density per MW. Status: built - MRO and follow-on sites. Ref: https://www.sec.gov/Archives/edgar/data/0000107263/000010726326000026/wmb-20260630.htm | https://www.power-eng.com/onsite-power/onsite-gas-turbines-reciprocating-engines-to-power-meta-data-center/ | https://www.williams.com/wp-content/uploads/sites/14/2026/02/Socrates-North-and-South-Fact-Sheet-1.pdf
A21: Socrates North Power Generation | B21: Will-Power OH, LLC (Williams) | C21: In Progress | D21: Socrates North (Williams Power Innovation); OPSB 25-0188-EL-BGN | E21: IPP | F21: Chad Zamarin, President & CEO | G21: Will-Power OH, LLC | I21: Owner/End User | K21: Under Construction - in service expected Q4 2026 | M21: =P21*1000*Guide!$B$81 | P21: 200 | R21: New Albany | S21: Licking | T21: OH | U21: United States | W21: 46387 | X21: 46568 | Y21: 45961 | Z21: Power Generation | AA21: Generation | AB21: New Capacity/New Build | AC21: Load Interconnection | AD21: Generation | AE21: Natural gas generation - electrical BoP (MV/LV power, tray/control & instrumentation cable, substation) | AF21: Greenfield | AG21: Traditional | AH21: Natural Gas | AI21: Yes | AJ21: AWARD (PO) DATE BASIS: OPSB approval Sep 18, 2025 + ~14-month fast track -> main cable likely awarded Q3-Q4 2025; window passed. Only possible open scope: BESS amendment (check OPSB docket timing). Williams 10-Q gives 556 MW combined North+South. | AK21: Check OPSB 25-0188 BESS amendment for remaining cable; target Williams next Power Innovation sites. | AL21: OVERVIEW: second 200 MW behind-the-meter gas plant for Meta's New Albany campus (Phase 2), on track for Q4 2026 per Williams; BESS amendment pending. TECHNOLOGY & EQUIPMENT: simple-cycle aeroderivative/industrial gas turbines + reciprocating engines (same design as Socrates South) plus planned battery storage (~173 MW reported across project). SITE: GREENFIELD - ~20 acres, New Albany, Licking County. INTERCONNECTION: behind the meter, no grid connection; on-site substation. OWNERSHIP/STATUS: Will-Power OH LLC (Williams); OPSB approved Sep 18, 2025. INVESTMENT: part of ~$1.6B program. W&C NEEDS (behind-the-meter / on-site generation): MV power cable (5-35 kV) collecting many turbine/engine units to on-site switching and plant substations and feeders to the data-center campus; 600V power & TC-ER tray cable for unit packages, MCCs, gas conditioning/compression, BESS and cooling; shielded instrumentation & control cable (unit controls, microgrid/SCADA); extensive bare copper grounding; switchgear/substation control cable; building wire for control and admin buildings. High unit count = high cable density per MW. Plus BESS DC/AC collection cable if amendment proceeds. Ref: https://opsb.ohio.gov/cases/25-0188-el-bgn | https://investor.williams.com/news-releases/news-release-details/williams-delivers-strong-second-quarter-2026-results-announces
A22: Homer City Energy Campus | B22: Homer City Redevelopment (Homer City Generation, L.P.) | C22: In Progress | D22: Homer City Generation, L.P.; legacy Homer City Generating Station site | E22: IPP | F22: Corey Hessen, CEO | G22: Homer City Redevelopment (Knighthead Capital-led) | I22: EPC | K22: Under Construction - HRSGs installed, first GT set Oct 2026; 2,000+ workers | M22: =P22*1000*Guide!$B$81 | P22: 4400 | R22: Homer City | S22: Indiana | T22: PA | U22: United States | W22: 46752 | X22: 46934 | Y22: 46203 | Z22: Power Generation | AA22: Generation | AB22: New Capacity/New Build | AC22: Load Interconnection | AD22: Generation | AE22: Natural gas generation - electrical BoP (MV/LV power, tray/control & instrumentation cable, substation) | AF22: Brownfield | AG22: Traditional | AH22: Natural Gas | AI22: Yes | AJ22: AWARD (PO) DATE BASIS: Kiewit on site since Oct 2025, HRSG delivery Sep-Oct 2026, first GT set Oct 2026, first power late 2027/early 2028 -> main power-block cable POs very likely placed; remaining releases/change orders through Q1 2027. Bigger long-tail: Amazon 36-building data-center campus plan (construction from Dec 2026, build-out to 2036; tabled by county Sep 2026). Other contacts: Brian Reinhart (VP, Kiewit Power Constructors); Kiewit vendor inbox HomerCity.Info@Kiewit.com; press@homercityredevelopment.com. | AK22: Call Kiewit procurement for remaining power-block MV/LV/control releases; pivot to Amazon data-center phases. | AL22: OVERVIEW: ~4.4-4.5 GW natural-gas power plant + AI data-center campus - the largest gas-powered data-center campus in the U.S. - on the former Homer City coal station; Amazon Data Services has filed a preliminary plan for a 36-building data-center campus (phased Dec 2026-2036). TECHNOLOGY & EQUIPMENT: 7x GE Vernova 7HA.02 hydrogen-capable gas turbines in combined cycle with HRSGs (15 HRSG components delivered Sep-Oct 2026); GIS switchgear building (first steel Apr 2026); possible additional simple-cycle units (unverified). SITE: BROWNFIELD - ~3,200-acre former Homer City coal generating station, Indiana County; demolition/excavation completed Jun 2026; reuses legacy transmission lines and substations. INTERCONNECTION: PJM via new GIS switchyard (existing PJM/NYISO ties); supplies campus behind-the-meter and grid. OWNERSHIP/STATUS: Homer City Redevelopment (Knighthead Capital), EQT gas supply; EPC Kiewit Power Constructors (on site Oct 2025, 1,000 workers Mar 2026, 2,000+ Oct 2026); first power late 2027/early 2028. INVESTMENT: >$10B. W&C NEEDS (combined cycle, 7 blocks): MV power cable to aux transformers, MV switchgear and large motors; 600V power & TC-ER tray cable for HRSG/ST auxiliaries and BOP; shielded I&C cable; bare copper grounding; GIS/switchyard control cable; building wire - plus data-center campus MV distribution, building wire and grounding for 36 buildings (separate long-tail opportunity). Ref: https://www.businesswire.com/news/home/20260401716982/en/Homer-City-Redevelopment-Crosses-the-First-Steel-Threshold | https://www.gevernova.com/news/press-releases/homer-city-redevelopment-kiewit-announce-country-largest-natural-gas-powered-data-center-support-ai-hpc-demand | https://marcellusdrilling.com/2026/10/homer-city-update-first-turbine-set-amazon-plan-now-under-review/
A23: Sandow Lakes Energy Station | B23: Sandow Lakes Energy Company (SLEC) | C23: Open | D23: SL Energy Power Plant I, LLC; ERCOT/EIA 68504; Sandow Lakes CC (CRM Luminant Phase 1/2 duplicates) | E23: IPP | F23: Edward "Ned" Ross III, Executive Vice President | G23: SLEC / Xebec (project reportedly sold Apr 2026 - buyer not public) | I23: EPC | K23: EPC NTP Apr 2025; construction status unclear (sold Apr 2026 per Xebec bio) | M23: =P23*1000*Guide!$B$81 | P23: 1200 | Q23: 345 | R23: Rockdale | S23: Lee / Milam | T23: TX | U23: United States | W23: 47088 | X23: 47270 | Y23: 46477 | Z23: Power Generation | AA23: Generation | AB23: New Capacity/New Build | AC23: Load Interconnection | AD23: Generation | AE23: Natural gas generation - electrical BoP (MV/LV power, tray/control & instrumentation cable, substation) | AF23: Brownfield | AG23: Traditional | AH23: Natural Gas | AI23: Yes | AJ23: AWARD (PO) DATE BASIS: Gemma EPC Feb 2025, NTP Apr 2025, completion 2028 -> cable window Dec 2026-Dec 2027, target ~Q1 2027. RISK: Xebec bio says project sold Apr 2026 (buyer unknown) - confirm owner/schedule. Luminant link only historical (old Sandow coal plant) - merge CRM Luminant duplicates. Other contacts: Tommy Hodges (COO, SL Energy Power Plant I LLC - tommyh@slenergyco.com, TCEQ 2025 filing); Charles E. Collins IV (CEO, Gemma). | AK23: Ask Gemma Power Systems who owns the project now and current schedule; position for MV/LV/control packages Q1 2027. | AL23: OVERVIEW: 1,200 MW net natural-gas combined-cycle plant built mainly to serve private (likely data-center/industrial) customers in the 'Texas Triangle'; only ~80 MW temporary grid export in permits. TECHNOLOGY & EQUIPMENT: 2x Siemens Energy SGT6-9000HL H-class, hydrogen-adaptable gas turbines (two ~645 MW units / 1x1 blocks), NEM Energy HRSGs (Siemens Energy USA client), steam turbines. SITE: BROWNFIELD/industrial - former Alcoa Sandow aluminum smelter and Luminant Sandow coal plant area on the Sandow Lakes Ranch (~33,000 acres, ~28,800 after Apr 2026 sale), Rockdale area, Lee/Milam County. INTERCONNECTION: ERCOT; nearest 345 kV line ~12.2 miles (estimate); Oncor territory. OWNERSHIP/STATUS: SLEC (SL Energy Power Plant I LLC), Xebec affiliate - reportedly sold Apr 2026; EPC Gemma Power Systems (NTP Apr 2025); COD Dec 2028. INVESTMENT: ~$1.2B. W&C NEEDS (combined cycle): MV power cable to aux transformers, MV switchgear and large motors; 600V power & TC-ER tray cable for HRSG/ST auxiliaries and BOP; shielded I&C cable; bare copper grounding; switchyard control cable; private-customer MV feeders; possible 345 kV line. Ref: https://www.businesswire.com/news/home/20250206210188/en/Argan-Inc.s-Gemma-Power-Systems-Executes-EPC-Contract-for-a-1.2-GW-Power-Project-in-Texas | https://www.powermag.com/new-1-2-gw-natural-gas-fired-plant-announced-for-texas/ | https://interchange.puc.texas.gov/Documents/56455_62_1398423.PDF | AO23: 12.2 | AP23: Sandow Lakes Energy Station | AQ23: Nearest 345 kV line (~12.2 mi est.)
A24: Wolf Summit Energy Center | B24: Kindle Energy (Blackstone Energy Transition Partners) | C24: In Progress | D24: ESC Harrison County; Kindle Energy / Blackstone Energy Transition Partners | E24: IPP | F24: Lee Davis, CEO | G24: Kindle Energy / Blackstone | I24: Developer | K24: Under Construction - groundbreaking Apr 22, 2026; concrete phase mid-2026 | M24: =P24*1000*Guide!$B$81 | P24: 610 | R24: Clarksburg (Wolf Summit) | S24: Harrison | T24: WV | U24: United States | W24: 46934 | X24: 47117 | Y24: 46418 | Z24: Power Generation | AA24: Generation | AB24: New Capacity/New Build | AC24: New Load Growth | AD24: Generation | AE24: Natural gas generation - electrical BoP (MV/LV power, tray/control & instrumentation cable, substation) | AF24: Greenfield | AG24: Traditional | AH24: Natural Gas | AI24: No | AJ24: AWARD (PO) DATE BASIS: FID Nov 2025, groundbreaking Apr 2026, concrete pours mid-2026, COD 2028 -> cable window open now, target Dec 2026-Mar 2027 (if COD 2027 per ENR, act immediately). Delivered as Kindle EPCM with four principal contractors (names not published) - identify the electrical contractor. CRM 579 MW not supported; sources say ~600-625 MW (610 MW used). Project contact: info@wolf-summit.com, (304) 576-8717. Other: Chris Cosby (CEO, ODEC); Bilal Khan (SMD, Blackstone). | AK24: Ask Kindle (EPCM) which principal contractor holds electrical; use Kindle Energy / project line (304) 576-8717 / WV Building Trades; position MV, control & I&C cable before bulk electrical buy. | AL24: OVERVIEW: ~600 MW natural-gas combined-cycle plant - West Virginia's first gas power plant - backed by $1.2B from Blackstone Energy Transition Partners, developed/operated by Kindle Energy, fully contracted to Old Dominion Electric Cooperative; ~500 construction jobs. TECHNOLOGY & EQUIPMENT: GE Vernova 7HA.02 gas turbine in combined cycle (likely 1x1 with HRSG and steam turbine - inferred); GE Vernova Financial Services also financing. SITE: Pinnickinnick Hill area near Clarksburg/Wolf Summit, Harrison County (PILOT/lease Jan 2025); acreage not published. INTERCONNECTION: PJM grid sale to ODEC; substation/voltage not published. OWNERSHIP/STATUS: FID Nov 2025; groundbreaking Apr 22, 2026; site prep and roadwork Jun 2026; COD 2028. Kindle EPCM with four principal contractors (not published). INVESTMENT: $1.2B. W&C NEEDS (combined cycle): MV power cable to aux transformers, MV switchgear and large motors; 600V power & TC-ER tray cable for HRSG/ST auxiliaries and BOP; shielded I&C cable; bare copper grounding; switchyard control cable; building wire. Ref: https://www.businesswire.com/news/home/20260422186042/en/Kindle-Energy-Breaks-Ground-on-Blackstone-Backed-$1.2-Billion-Natural-Gas-Power-Generation-Facility-in-West-Virginia | https://wolf-summit.com/ | https://www.powermag.com/blackstone-investing-1-2-billion-for-600-mw-gas-fired-plant-in-west-virginia/
A25: Cedar Bayou Unit 5 | B25: NRG Energy | C25: In Progress | D25: Cedar Bayou 5; NRG Cedar Bayou Generating Station expansion | E25: IPP | F25: Robert J. Gaudette, EVP & President, Business & Wholesale Operations | G25: NRG Energy | I25: Owner/End User | K25: Under Construction - on track (NRG Q1 2026); TEF loan closed | M25: =P25*1000*Guide!$B$81 | P25: 689 | R25: Baytown | S25: Chambers | T25: TX | U25: United States | W25: 46965 | X25: 47149 | Y25: 46418 | Z25: Power Generation | AA25: Generation | AB25: New Capacity/New Build | AC25: New Load Growth | AD25: Generation | AE25: Natural gas generation - electrical BoP (MV/LV power, tray/control & instrumentation cable, substation) | AF25: Brownfield | AG25: Traditional | AH25: Natural Gas | AI25: No | AJ25: AWARD (PO) DATE BASIS: TEF loan closed Q3 2025, under construction, COD mid-2028 (NRG) -> cable window Jul 2026-Jul 2027, target Nov 2026-Feb 2027. EPC not public (NRG GE Vernova/Kiewit venture is for 7HA units, not this Mitsubishi unit). CRM correction: 689 MW (NRG) vs 721 MW (state), Mitsubishi not GE, COD mid-2028 not 2029. Owner contact on 2026 TDLR project registration: Dudley D. Zahn (NRG / Cedar Bayou 5 LLC, 713-537-3290; email historical). | AK25: Engage NRG construction/procurement to identify Cedar Bayou 5 EPC/BOP electrical contractor now. | AL25: OVERVIEW: 689 MW (NRG; state cites 721 MW) natural-gas combined-cycle unit added at NRG's existing Cedar Bayou Generating Station, one of NRG's largest Texas assets, backed by a Texas Energy Fund loan. TECHNOLOGY & EQUIPMENT: 1x1 combined cycle - Mitsubishi Power M501JAC J-class gas turbine (TCEQ permit), HRSG and steam turbine (OEMs not published). SITE: BROWNFIELD - existing operating Cedar Bayou plant on Galveston Bay, Baytown, Chambers County (existing gas, water and transmission). INTERCONNECTION: ERCOT grid unit; voltage not published. OWNERSHIP/STATUS: NRG Energy; TEF loan announced Sep 26, 2025; under construction; COD mid/summer 2028. INVESTMENT: $936M. W&C NEEDS (combined cycle): MV power cable to aux transformers, MV switchgear and large motors; 600V power & TC-ER tray cable for HRSG/ST auxiliaries and BOP; shielded I&C cable; bare copper grounding; switchyard control cable. Ref: https://gov.texas.gov/news/post/governor-abbott-announces-texas-energy-fund-loan-to-721-mw-natural-gas-facility-in-southeast-texas | https://www.utilitydive.com/news/nrg-close-to-completing-415-mw-gas-plant-backed-by-texas-energy-fund/819587/ | https://www.texastribune.org/2025/09/26/texas-energy-fund-loan-nrg-baytown
A26: CPV Basin Ranch Energy Center | B26: CPV Group (OPC Energy / Kenon) | C26: In Progress | D26: CPV Basin Ranch Holdings LLC; ERCOT 25INR0008 (BASRANCH) | E26: IPP | F26: Peter Podurgiel, President, Low Carbon Generation | G26: CPV Basin Ranch Holdings LLC (CPV 100%) | I26: EPC | K26: Under Construction - Gemma full NTP Oct 30, 2025; groundbreaking Nov 20, 2025 | M26: =P26*1000*Guide!$B$81 | P26: 1350 | Q26: 345 | R26: Barstow | S26: Ward | T26: TX | U26: United States | W26: 47088 | X26: 47270 | Y26: 46477 | Z26: Power Generation | AA26: Generation | AB26: New Capacity/New Build | AC26: New Load Growth | AD26: Generation | AE26: Natural gas generation - electrical BoP (MV/LV power, tray/control & instrumentation cable, substation) | AF26: Greenfield | AG26: Traditional | AH26: Natural Gas | AI26: No | AJ26: AWARD (PO) DATE BASIS: full NTP Oct 2025, construction since Nov 2025, COD Dec 2028 (ERCOT; CPV says 2029) -> target Q1 2027; early packages may already be placed. CRM correction: utility is Oncor (not AEP Texas). Other contacts: Sherman Knight (CEO, CPV); Charles E. Collins IV (CEO, Gemma); David Watson (Argan company contact, 301-315-0027). | AK26: Get in front of Gemma procurement now for MV/LV power, control & I&C packages before Q1 2027. | AL26: OVERVIEW: 1,350 MW natural-gas combined-cycle plant in the Permian Basin, CPV's first Texas project, backed by a ~$1.1B Texas Energy Fund loan; CPV bought the remaining 30% in Feb 2026 (100% owner). TECHNOLOGY & EQUIPMENT: two 1x1 combined-cycle blocks with GE Vernova 7HA.03 gas turbines, HRSGs and steam turbines; permitted carbon-capture option for later phases (CPV Basin Ranch Capture LLC). SITE: GREENFIELD - near Barstow, Ward County (acreage not published). INTERCONNECTION: 345 kV into an Oncor switchyard tapping the Riverton-Sand Lake 345 kV line; ERCOT. OWNERSHIP/STATUS: CPV Group (OPC Energy/Kenon); EPC Gemma Power Systems, detailed engineering POWER Engineers; groundbreaking Nov 20, 2025; COD Dec 2028-2029. INVESTMENT: ~$2B. W&C NEEDS (combined cycle): MV power cable to aux transformers, MV switchgear and large motors; 600V power & TC-ER tray cable for HRSG/ST auxiliaries and BOP; shielded I&C cable; bare copper grounding; 345 kV switchyard control cable; future carbon-capture plant cabling. Ref: https://cpv.com/2025/11/20/cpv-basin-ranch-energy-center-breaks-ground-in-ward-county-texas/ | https://www.businesswire.com/news/home/20251030500209/en/Argan-Inc.s-Gemma-Power-Systems-Receives-Full-Notice-to-Proceed-on-EPC-Contract-for-1350-MW-Combined-Cycle-Power-Plant-in-Texas | https://cpv.com/our-fleet/cpv-basin-ranch-energy-center/ | AP26: CPV Basin Ranch Energy Center | AQ26: Oncor 345 kV switchyard (tap Riverton-Sand Lake 345 kV)
A27: CPV Shay Energy Center | B27: CPV Group (OPC Energy / Kenon) | C27: Open | D27: CPV Shay, LLC; CPV Shay Clean Energy Center | E27: IPP | F27: Peter Podurgiel, President (per Aug 2026 release) | G27: CPV Shay, LLC | I27: Developer | K27: Development - WV PSC siting Apr 2024; air permit applied Jan 2026; EQT gas deal Aug 2026 | M27: =P27*1000*Guide!$B$81 | P27: 2100 | Q27: 500 | R27: West Union (Blandville) | S27: Doddridge | T27: WV | U27: United States | W27: 48213 | X27: 48395 | Y27: 47483 | Z27: Power Generation | AA27: Generation | AB27: New Capacity/New Build | AC27: New Load Growth | AD27: Generation | AE27: Natural gas generation - electrical BoP (MV/LV power, tray/control & instrumentation cable, substation) | AF27: Greenfield | AG27: Traditional | AH27: Natural Gas | AI27: No | AJ27: AWARD (PO) DATE BASIS: construction start est. Q1 2027, COD est. 2031 (CPV fact sheet Mar 2026) -> award window ~2029-2030. Could accelerate if selected in PJM Reliability Backstop procurement (auction postponed after FERC order Sep 29, 2026). EPC not yet named. CRM COD 12/31/2029 updated to 2031. Other: Toby Rice (CEO, EQT). | AK27: Track WVDEP air permit and EPC award (likely 2027); spec in early with engineer. | AL27: OVERVIEW: ~2,060-2,100 MW natural-gas combined-cycle plant with amine-based carbon capture capability (90-95% capture target), one of the largest gas plants planned in PJM; 10-yr EQT gas supply (>100 BCF/yr) signed Aug 2026. TECHNOLOGY & EQUIPMENT: three 1x1 combined-cycle blocks with GE Vernova 7HA.03 gas turbines (~687 MW each), HRSGs and steam turbines; post-combustion amine carbon capture plant (can run with or without capture). SITE: GREENFIELD - 54-acre footprint within a 230-acre parcel along WV Route 18, ~5 miles SE of West Union, Doddridge County. INTERCONNECTION: new ~9-mile 500 kV line to Mon Power's Flint Run 500 kV substation; PJM. OWNERSHIP/STATUS: CPV Shay LLC; WV PSC siting certificate Apr 2024; WVDEP air permit application Jan 2026; construction start est. 2027; COD est. 2031. INVESTMENT: ~$3-3.3B. W&C NEEDS (combined cycle x3 + carbon capture): MV power cable to aux transformers, MV switchgear and large motors (incl. capture-plant compressors/blowers/pumps); 600V power & TC-ER tray cable; shielded I&C cable; bare copper grounding; 500 kV switchyard control cable; 9-mile 500 kV transmission conductor. Ref: https://cpv.com/our-fleet/cpv-shay-energy-center/ | https://cpv.com/2026/08/12/cpv-secures-10-year-gas-netback-with-eqt-to-supply-2-gw-cpv-shay-energy-center/ | https://cpv.com/wp-content/uploads/2026/03/CPV-Shay-Energy-Center-Project-Fact-Sheet-March-2026-1.pdf | AO27: 9 | AP27: CPV Shay Energy Center | AQ27: Mon Power Flint Run 500 kV Substation
A28: CPV Clean Energy Future - Oregon (Oregon Energy Center) | B28: CPV Group (CPV Oregon Holdings) | C28: Delayed | D28: CPV Oregon Energy Center; Clean Energy Future - Oregon; OPSB 17-0530-EL-BGN | E28: IPP | F28: TBD | G28: CPV Oregon Holdings | I28: Developer | K28: Stalled / at risk - PJM queue reportedly withdrawn (Aurora, Feb 2026); OPSB certificate may have lapsed | M28: =P28*1000*Guide!$B$81 | P28: 1475 | Q28: 345 | R28: Oregon | S28: Lucas | T28: OH | U28: United States | W28: 48213 | X28: 48395 | Y28: 47483 | Z28: Power Generation | AA28: Generation | AB28: New Capacity/New Build | AC28: New Load Growth | AD28: Generation | AE28: Natural gas generation - electrical BoP (MV/LV power, tray/control & instrumentation cable, substation) | AF28: Brownfield | AG28: Traditional | AH28: Natural Gas | AI28: No | AJ28: ON HOLD: OPSB certificate (955 MW, 2017) extended to ~mid-2026; selected for PJM RRI May 2025 and redesigned to 1,475 MW / 2031 COD; Aurora (Feb 2026) reports queue request withdrawn after $878/kW cost estimate (single source). Neighboring Oregon Clean Energy Center (870 MW) now owned by I&M/AEP (Mar 2026) - not CPV. ALTERNATIVE CPV LEAD: CPV Walker Energy Center, Fayette County OH (1,450-1,465 MW CC, ~150 acres, construction Q2 2028, COD Q4 2031, AES Ohio 345 kV). Other contact: Joel Mazur (City Administrator, Oregon OH). | AK28: Confirm with CPV whether Oregon is alive; open new lead for CPV Walker Energy Center (Fayette Co., OH). | AL28: OVERVIEW: planned ~1,475 MW natural-gas combined-cycle plant (redesigned from the 955 MW certificate) by CPV, selected for PJM's Reliability Resource Initiative (May 2025) with a 2031 target - currently stalled (queue reportedly withdrawn). TECHNOLOGY & EQUIPMENT: combined cycle; original design two combustion turbines + HRSGs + steam turbine; OEM for redesign not published. SITE: BROWNFIELD-ADJACENT industrial parcel next to the existing 870 MW Oregon Clean Energy Center (now I&M/AEP), north of Parkway Rd, Oregon, Lucas County. INTERCONNECTION: 138 kV and 345 kV lines (955 MW case); PJM. OWNERSHIP/STATUS: CPV Oregon Holdings (transfer Jan 2024); OPSB extensions Dec 2023 and May 2025; status uncertain. INVESTMENT: not published for redesign. W&C NEEDS (combined cycle, if revived): MV power cable, 600V power & TC-ER tray cable, shielded I&C cable, grounding, switchyard control cable. Ref: https://opsb.ohio.gov/news/opsb-extends-certificate-for-lucas-county-natural-gas-fired-power-plant | https://www.presspublications.com/stories/natural-gas-power-plant-oregon-ohio-reliability-resource-initiative-pjm,58407 | https://www.recordherald.com/2026/05/04/cpv-walker-energy-center-begins-state-review-for-new-power-plant/
A29: Lincoln Land Energy Center (LLEC) | B29: EmberClear Corp. | C29: Delayed | D29: Lincoln Land Energy Center LLC; MISO 62022_GEN1/GEN2 | E29: IPP | F29: John Kinnamon, VP, LLEC Project Leader | G29: EmberClear (Lincoln Land Energy Center LLC) | I29: Developer | K29: Dormant / at risk - construction not started; IEPA permit expires Jan 1, 2027; data-center offtaker withdrew Aug 2026 | M29: =P29*1000*Guide!$B$81 | P29: 1190 | Q29: 345 | R29: Pawnee | S29: Sangamon | T29: IL | U29: United States | W29: 47635 | X29: 47818 | Y29: 47118 | Z29: Power Generation | AA29: Generation | AB29: New Capacity/New Build | AC29: New Load Growth | AD29: Generation | AE29: Natural gas generation - electrical BoP (MV/LV power, tray/control & instrumentation cable, substation) | AF29: Greenfield | AG29: Traditional | AH29: Natural Gas | AI29: No | AJ29: ON HOLD: IEPA construction permit (2022, extended twice) expires Jan 1, 2027; construction not begun; EmberClear/Kindle not responding to press; Eagle Rock Partners abandoned its Christian County data center (offtaker) Aug 12, 2026. CRM correction: RTO is MISO Zone 4 (Ameren), not PJM; EIA COD Jun 2030. Re-check after Jan 1, 2027. | AK29: Re-check IEPA permit status after Jan 1, 2027; move to dormant if not extended; watch for Kindle/Blackstone revival. | AL29: OVERVIEW: ~1,190 MW (EIA/MISO 1,277 MW) natural-gas combined-cycle plant near Pawnee, IL, developed by EmberClear with Siemens Energy, Siemens Financial Services, Bechtel (BDC Power Holdings) and Kindle Energy; designed for 30% hydrogen blend with path to 100%. Linked data-center offtaker (Eagle Rock Meridian Technology Park, ~1 GW) withdrew Aug 2026. TECHNOLOGY & EQUIPMENT: two combined-cycle blocks (2x ~560-638 MW) with Siemens Energy gas turbines, HRSGs and steam turbines. SITE: GREENFIELD - 160 acres, half a mile south of the Village of Pawnee, Sangamon County. INTERCONNECTION: adjacent to Ameren's Illinois Rivers 345 kV substation; MISO Zone 4 (interconnection agreement 2023). OWNERSHIP/STATUS: EmberClear (Lincoln Land Energy Center LLC); IEPA permit expires Jan 1, 2027; EIA COD Jun 2030. INVESTMENT: ~$1.4-1.5B. W&C NEEDS (combined cycle, if revived): MV power cable, 600V power & TC-ER tray cable, shielded I&C cable, grounding, 345 kV switchyard control cable. Ref: https://emberclear.com/lincoln-land-2/ | https://www.illinoistimes.com/news/data-center-development-linked-to-power-plant-construction/ | https://www.springfieldbusinessjournal.com/news/data-center-developer-abandons-plans-for-christian-county/
A30: Project Kilby (Chevron West Texas Power) | B30: Chevron (Energy Forge One LLC) / Joulent (Engine No. 1, National Grid Ventures) | C30: Open | D30: Kilby Power Plant; Energy Forge One LLC; Kilby Chevron West Texas Natural Gas (CRM); TCEQ 181895/PSDTX1684 | E30: IPP | F30: Daniel Droog, VP, Power Solutions | G30: Energy Forge One LLC (Chevron) | I30: Owner/End User | K30: Pre-FID - Microsoft 20-yr PPA Jun 22, 2026; FID targeted end-2026; TCEQ air permit pending | M30: =P30*1000*Guide!$B$81 | P30: 2670 | R30: Pecos (Verhalen area) | S30: Reeves | T30: TX | U30: United States | W30: 46934 | X30: 47117 | Y30: 46477 | Z30: Power Generation | AA30: Generation | AB30: New Capacity/New Build | AC30: Load Interconnection | AD30: Generation | AE30: Natural gas generation - electrical BoP (MV/LV power, tray/control & instrumentation cable, substation) | AF30: Greenfield | AG30: Traditional | AH30: Natural Gas | AI30: Yes | AJ30: AWARD (PO) DATE BASIS: PPA signed Jun 2026, FID targeted end-2026, first power 2028 with phased ramp to ~2.67 GW (~2029-30) -> award window Jun 2026-Jun 2027, target ~Q1 2027 (early-power Titan 130 units drive first packages). CRM COD 6/30/2027 corrected to 2028. Bechtel May 2026 Project Opportunity Report lists Kilby job 26776 with procurement (Birju Vasani, bvasani@bechtel.com) and subcontracts (Mark Bingaman, mabingam@bechtel.com, 713-235-1662) prequalification contacts; full NTP not confirmed. Full capacity 2031 per kilby.com. Other contacts: Jeff Gustavson (President, Chevron New Energies); Chris James (Founder & CEO, Engine No. 1 / Joulent). | AK30: Prequalify with Bechtel now: Birju Vasani (procurement) and Mark Bingaman (subcontracts) for Kilby job 26776; get specified before FID (Dec 2026); engage Chevron Power Solutions (Daniel Droog). | AL30: OVERVIEW: ~2.67 GW (permit ~2.87 GW, possible scale to 5 GW) off-grid natural-gas power plant dedicated to Microsoft's up-to-2 GW Pecos AI data-center campus under a 20-year PPA (Jun 22, 2026); developed by Chevron (Energy Forge One) with Engine No. 1's Joulent and National Grid Ventures ($1.75B for 35% of Joulent). TECHNOLOGY & EQUIPMENT: ~46 gas turbines - GE Vernova 7HA (7 reserved; permit analysis 5x 7HA.02) plus Solar Turbines Titan 350 (12) and Titan 130 (29, added Dec 2025 for early power); SCR and oxidation catalysts; combined/simple-cycle split not confirmed. SITE: GREENFIELD - Reeves County, SE of Pecos near Verhalen (Pecos TX 79780), off US-285 / FM 112; Microsoft campus ~7,000 acres (tracker, unverified). INTERCONNECTION: behind-the-meter, co-located with Microsoft campus (ERCOT region, no grid export disclosed). OWNERSHIP/STATUS: Energy Forge One LLC (Chevron/Joulent 50:50); EPC Bechtel (job 26776, procurement/early works); pre-FID; TCEQ air permit draft Apr 2026, public meeting Jun 10, 2026, pending; FID end-2026; first power 2028. INVESTMENT: ~$7-9B (analyst estimates). W&C NEEDS (behind-the-meter / on-site generation): MV power cable (5-35 kV) collecting many turbine/engine units to on-site switching and plant substations and feeders to the data-center campus; 600V power & TC-ER tray cable for unit packages, MCCs, gas conditioning/compression, BESS and cooling; shielded instrumentation & control cable (unit controls, microgrid/SCADA); extensive bare copper grounding; switchgear/substation control cable; building wire for control and admin buildings. High unit count = high cable density per MW. Very large scope: 46 turbine packages plus data-center campus feeders. Ref: https://www.chevron.com/newsroom/2026/q2/chevron-signs-20-year-power-agreement-with-microsoft-for-west-texas-data-center | https://www.tceq.texas.gov/downloads/permitting/air/bilingual/pending-permit-notices/181895-pls-english.pdf | https://blogs.microsoft.com/blog/2026/06/22/powering-the-next-wave-of-ai-expanding-capacity-with-our-new-datacenter-in-pecos/
A31: Shippingport Power Station Phase II | B31: The Frontier Group of Companies (FGC) | C31: Open | D31: Shippingport Power Station, LLC; former Bruce Mansfield Power Plant conversion; Shippingport Industrial Park | E31: IPP | F31: Chris Cox, VP, Power Generation | G31: Shippingport Power Station, LLC (Frontier) | I31: Design / Build | K31: Development / permitting - DEP fuel-yard stormwater permit comment to Nov 23, 2026; PJM approval expected mid-2028 | M31: =P31*1000*Guide!$B$81 | P31: 2550 | Q31: 345 | R31: Shippingport | S31: Beaver | T31: PA | U31: United States | W31: 47208 | X31: 47391 | Y31: 46568 | Z31: Power Generation | AA31: Generation | AB31: New Capacity/New Build | AC31: Load Interconnection | AD31: Generation | AE31: Natural gas generation - electrical BoP (MV/LV power, tray/control & instrumentation cable, substation) | AF31: Brownfield | AG31: Traditional | AH31: Natural Gas | AI31: Yes | AJ31: AWARD (PO) DATE BASIS: Frontier targets PJM approval mid-2028 and units online early 2029 with ~3-year construction -> award window Mar 2027-Mar 2028, target ~Q2 2027. CRM COD 12/31/2030 updated to early 2029. Capacity conflicts: 2,550 MW export / 2.7 GW conversion + 900 MW Phase I = 3.6 GW. Aligned Data Centers broke ground on 2 GW Project Phoenix (~$10B) Sep 10, 2026 next door. Other contacts: David Franjoine (Founder & CEO); Robert Zuchlewski (COO); Anthony Basil (Project Manager) and Peter Violante (Dir. Logistics & BD) - Shippingport assignment not confirmed. Owner's engineer: Wood. | AK31: Meet Chris Cox (Frontier) on Phase II steam-unit refurbishment and 34.5 kV substation cable packages. | AL31: OVERVIEW: conversion of the former 2.5-2.7 GW Bruce Mansfield coal plant (operated 1976-2019) into a natural-gas power station; Phase I adds ~900 MW new simple-cycle gas turbines + switchyard, Phase II (this record) converts the coal units (~2.7 GW) - up to ~3.6 GW total available to the park; EQT gas supply ~800 MMcf/d via new 7.2-mile National Fuel lateral. TECHNOLOGY & EQUIPMENT: refurbish 3x existing GE steam turbine-generators (~850 MW each) re-powered with new gas turbines (repowering), new cooling towers, transformers and switchgear, on-site gas receiving station and 34.5 kV substation; coal handling demolished. SITE: BROWNFIELD - former Bruce Mansfield coal plant in the 660-acre Shippingport Industrial Park, Shippingport Borough, Beaver County; 14.5-acre gas fuel yard. Aligned Data Centers' 2 GW Project Phoenix campus under construction on site. INTERCONNECTION: PJM Cycle 01 (existing Bruce Mansfield 345 kV substation, Penn Power/FirstEnergy) plus behind-the-meter supply to the park. OWNERSHIP/STATUS: Frontier Group (self-performs engineering and construction; Wood owner's engineer); permitting underway; PJM approval mid-2028; units online early 2029; >1,500 construction workers. INVESTMENT: >$1.8B. W&C NEEDS (repowered steam units + new GTs): MV power cable for new GT/aux transformers, cooling-tower fans and pumps, 34.5 kV substation feeders; 600V power & TC-ER tray cable; shielded I&C cable for new controls/DCS; grounding; switchyard control cable; data-center park MV distribution. Ref: https://frontier-companies.com/shippingport-power-station-featured-in-energy-oil-gas-magazine/ | https://www.businesswire.com/news/home/20250715103342/en/The-Frontier-Group-of-Companies-to-Transform-Bruce-Mansfield-Power-Plant-into-State-of-the-Art-Natural-Gas-Power-Plant-Supporting-Americas-Energy-Goals-and-Pennsylvanias-Economic-Growth | https://aligneddc.com/press-release/project-phoenix-data-center-shippingport-pa/
A32: VPN 4420 Natural Gas Generation Component | B32: VPN 4420 LLC | C32: Delayed | D32: VPN 4420 LLC; Texas Comptroller Chapter 313 Application #1993 (Pecos-Barstow-Toyah ISD) | E32: IPP | F32: Mark Siffin, CEO / project business contact | G32: VPN 4420 LLC | I32: Developer | K32: Dormant / speculative - 2022 Chapter 313 agreement; no investment or permits reported | M32: =P32*1000*Guide!$B$81 | P32: 1540 | R32: Pecos | S32: Reeves | T32: TX | U32: United States | W32: 47848 | X32: 48029 | Y32: 47299 | Z32: Power Generation | AA32: Generation | AB32: New Capacity/New Build | AC32: Load Interconnection | AD32: Generation | AE32: Natural gas generation - electrical BoP (MV/LV power, tray/control & instrumentation cable, substation) | AF32: Greenfield | AG32: Traditional | AH32: Natural Gas | AI32: Yes | AJ32: LOW PROBABILITY: Chapter 313 agreement executed Dec 19, 2022 ($1B, 10 jobs); 2023 report showed no jobs/investment; no TCEQ air permit found. Maefield link established via Chapter 313 filings (2024 compliance report posted 2026 lists Mark Siffin). Tentative award 6/30/2029. Same county has stronger leads: Project Kilby (Chevron/Microsoft), Prometheus Hyperscale + Istmo (1.5-2.5 GW, Aug 2026), LandBridge/NRG (1.1 GW), LandBridge/PowerBridge (2 GW). | AK32: Downgrade probability; watch for TCEQ air filings under VPN 4420; prioritize Kilby/Prometheus in Reeves County. | AL32: OVERVIEW: proposed Phase 1 technology campus (~6 million sq ft of data centers and semiconductor manufacturing) in Reeves County powered by up to three on-site natural-gas trigeneration plants (power, heating, cooling) totaling ~1.54 GW with CO2 capture equipment. TECHNOLOGY & EQUIPMENT: on-site gas trigeneration plants with CO2 capture (OEMs not published). SITE: GREENFIELD - Pecos-Barstow-Toyah ISD area, Reeves County (acreage not published). INTERCONNECTION: on-site / behind the meter. OWNERSHIP/STATUS: VPN 4420 LLC / Maefield Development (Mark Siffin); Chapter 313 agreement Dec 2022; no reported investment or permits as of latest filings - likely stalled. INVESTMENT: $1B qualified investment (313). W&C NEEDS (behind-the-meter / on-site generation): MV power cable (5-35 kV) collecting many turbine/engine units to on-site switching and plant substations and feeders to the data-center campus; 600V power & TC-ER tray cable for unit packages, MCCs, gas conditioning/compression, BESS and cooling; shielded instrumentation & control cable (unit controls, microgrid/SCADA); extensive bare copper grounding; switchgear/substation control cable; building wire for control and admin buildings. High unit count = high cable density per MW. Ref: https://comptroller.texas.gov/economy/development/prop-tax/ch313/agreement-docs-details.php?id=1993 | https://assets.comptroller.texas.gov/ch313/1993/1993-pecos-vpn-agmt.pdf

Sheet Leads
A1: Stephan Hardt | Power Generation
A2: Leads template
A3: One lead per row. Contact and project details are kept in the same record.
A4: Amber cells = dropdowns. * = required in the recording. Blank rows are ready for entry. See Guide for source limits.
A5: Contact Details | U5: Contact Address | Z5: Contact Tracking | AD5: Key Project Details | AN5: Market + Application | AX5: Project Address | BE5: Project Stakeholders | BP5: Project Product Offering | BX5: Additional Project Details | CB5: Project Metadata | CG5: Sales Update
A6: Last Name * | B6: First Name | C6: Company * | D6: Lead Status * | E6: Lead Source * | F6: Lead Owner | G6: Salutation | H6: Title | I6: Occupation | J6: Industry | K6: Phone | L6: Mobile | M6: Email | N6: Fax | O6: Create Project Record | P6: Recycle Date | Q6: Recycle Time | R6: Do Not Call | S6: Email Opt Out | T6: Sales Agent Contact | U6: Contact Street | V6: Contact City | W6: Contact State/Province | X6: Contact Zip/Postal Code | Y6: Contact Country | Z6: EVITP Certified | AA6: SSU Attendee | AB6: SSU Attended Date | AC6: MQL LOB | AD6: Project Name | AE6: Other Project Aliases | AF6: End User | AG6: Construction Stage | AH6: End User Type | AI6: Amount ($) | AJ6: Project Probability | AK6: Estimated Commissioning Date | AL6: Estimated Power Capacity (MW) | AM6: Estimated Voltage (KV) | AN6: Market | AO6: Segment | AP6: Application | AQ6: Demand Driver | AR6: OEM Category | AS6: Proposed Project Application | AT6: Brownfield/Greenfield | AU6: Power Needs | AV6: Primary Energy Source | AW6: AI Facility | AX6: Project Street | AY6: Project City | AZ6: Project State | BA6: Project ZIP | BB6: Project Country | BC6: Project County | BD6: Project Canadian Region | BE6: Site Owner | BF6: EPC | BG6: Developer | BH6: Preferred Electrical Distributor | BI6: OEM Project Partner | BJ6: General Contractor | BK6: Electrical Contractor | BL6: RTO/ISO/Regional Group | BM6: Utility Provider | BN6: Sold-To Party | BO6: Construction Equipment Provider | BP6: Medium Voltage | BQ6: 600V Insulated | BR6: Tray Cable | BS6: Building Wire | BT6: High Voltage Underground | BU6: Bare Overhead | BV6: Submarine | BW6: Substation | BX6: Total Transmission Line Miles | BY6: Transmission Line Endpoint 1 | BZ6: Transmission Line Endpoint 2 | CA6: Data Center Building Name | CB6: External Project ID | CC6: Data Center Building ID | CD6: End User ID | CE6: Site Owner ID | CF6: RTO/ISO/Regional Group ID | CG6: Sales Comments | CH6: Top Next Steps | CI6: Project Description | CJ6: Description
A7: Birmingham | B7: Daniel | C7: Invenergy | D7: New | E7: Sales | F7: Stephan Hardt | H7: Lead Developer | I7: Contractor | J7: Energy | K7: +1 312-582-1094 | M7: dbirmingham@invenergy.com | O7: Yes | AD7: Forest Junction Energy Center | AE7: Forest Junction Energy Center Project (Yes Energy); Forest Junction Energy Center LLC; MISO J4014; paired w/ Union Depot Energy Center (750 MW CC) | AF7: Invenergy | AG7: Advanced Development - pre-CPCN application (WI PSC REF#606657) | AH7: IPP | AI7: =AL7*1000*Guide!$B$81 | AK7: 48213 | AL7: 1203 | AM7: 345 | AN7: Power Generation | AO7: Generation | AP7: New Capacity/New Build | AQ7: New Load Growth | AR7: Generation | AS7: Natural gas generation - electrical BoP (MV/LV power, tray/control & instrumentation cable, substation) | AT7: Greenfield | AU7: Traditional | AV7: Natural Gas | AW7: No | AX7: E of Hwy 57, N of Hwy 10, Town of Brillion | AY7: Brillion (Town of) | AZ7: WI | BB7: United States | BC7: Calumet | BE7: Invenergy (private land lease) | BG7: Invenergy | BI7: GE Vernova (5x 7F.05 CTs, H35 generators) | BL7: Midcontinent Independent System Operator (MISO) | BM7: American Transmission Co (ATC); possible offtaker We Energies | BP7: Yes | BQ7: Yes | BR7: Yes | BS7: No | BT7: No | BU7: Yes | BV7: No | BW7: Yes | BX7: 1.2 | BY7: Forest Junction Energy Center | BZ7: ATC Forest Junction 345 kV Substation | CB7: 10019673557 | CG7: *RPBD* AWARD (PO) DATE BASIS: CPCN filing expected fall 2026 (PSC docket 5-CE-162), construction start Q4 2027, COD Dec 2031 -> BOP cable likely released in phases Q4 2028-Q2 2030 (award date set to COD-24 mo). EPC not named (Invenergy has used Kiewit elsewhere - unconfirmed). We Energies (Brendan Conway, spokesperson) may acquire; precedent: PSC approved Invenergy Red Oak Ridge/Foundry Ridge for We Energies Oct 15, 2026. Yes Energy shows 2030 COD; public sources Dec 2031. | CH7: Build relationship with Daniel Birmingham (Invenergy); watch PSC 5-CE-162 CPCN for EPC; get on EPC approved-vendor list in 2027. | CI7: *RPBD* OVERVIEW: Proposed ~1,203 MW natural-gas simple-cycle PEAKING plant by Invenergy, planned alongside the 750 MW Union Depot Energy Center combined cycle on an adjacent site (~1.95 GW total campus). Alternate site identified in Town of Woodville. TECHNOLOGY & EQUIPMENT: 5x GE 7F.05 combustion turbines with GE H35 generators, each with generator step-up transformer; designed for continuous duty but expected to run mainly at peak. SITE: GREENFIELD - privately owned agricultural land east of WI-57, north of US-10, Town of Brillion, Calumet County (acreage not yet published; see PSC engineering plan). INTERCONNECTION: three 345 kV overhead gen-tie lines to ATC's Forest Junction 345 kV substation (ATC also expanding 345 kV lines south to new Sheboygan River substation). OWNERSHIP/STATUS: Developer Invenergy; We Energies listed it in rate-case planning (possible acquirer, needs PSC approval). Engineering plan filed Aug 2026; CPCN application expected fall 2026 (PSC docket 5-CE-162); construction start targeted Q4 2027; COD ~Dec 2031. EPC not yet selected. INVESTMENT: Total project investment Not disclosed; est. W&C value $9,624,000 ($8/kW). W&C NEEDS (simple-cycle peaker): MV power cable (5-35 kV) for auxiliary transformers, MV switchgear, fuel-gas compressors and black-start/aux systems; 600V power & TC-ER tray cable for turbine packages, MCCs, fuel oil forwarding (if dual fuel) and SCR/ammonia systems; shielded instrumentation & control cable; bare copper grounding grid per unit and switchyard; switchyard control/relay cable; building wire for control/admin buildings. Less cable per MW than a CC (no HRSG/steam cycle). Plus overhead conductor for 3x 345 kV gen-ties; large opportunity if bundled with Union Depot CC. Ref: https://dailyreporter.com/2026/08/31/invenergy-proposes-two-natural-gas-plants-calumet-county/ | https://fox11online.com/news/local/calumet-county-power-plant-proposed-energy-centers-town-of-brillion-power-megawatts-gigawatts-we-energies-invenergy-town-of-woodville-forest-junction-union-depot | https://forestjunctionenergycenter.invenergy.com/ | https://www.nbc26.com/lakeshore/neighbors-push-back-against-proposed-natural-gas-facility-in-town-of-brillion | CJ7: *RPBD* Total project investment: Not disclosed. Est. W&C value: $9,624,000 ($8/kW).
A8: Pollock | B8: Keith | C8: Entergy Texas | D8: Recycle | E8: Sales | F8: Stephan Hardt | H8: Project Director, OCAPS | I8: End User | J8: Energy | O8: Yes | AD8: Orange County Advanced Power Station (OCAPS) | AE8: Orange County Advanced Power Station Project (Yes Energy); OCAPS; Sabine Power Plant site; PUCT Docket 52487 | AF8: Entergy Texas | AG8: In service ~Oct 14, 2026 (was Under Construction in Yes Energy) | AH8: IOU | AI8: =AL8*1000*Guide!$B$81 | AK8: 46309 | AL8: 1215 | AN8: Power Generation | AO8: Generation | AP8: New Capacity/New Build | AQ8: New Load Growth | AR8: Generation | AS8: Natural gas generation - electrical BoP (MV/LV power, tray/control & instrumentation cable, substation) | AT8: Brownfield | AU8: Traditional | AV8: Natural Gas | AW8: No | AX8: Entergy Sabine Power Plant site | AY8: Bridge City | AZ8: TX | BB8: United States | BC8: Orange | BE8: Entergy Texas | BF8: Mitsubishi Power / TIC / Sargent & Lundy (EPC consortium) | BG8: Entergy Texas | BI8: Mitsubishi Power (2x M501JAC GT, ST, HRSG) | BL8: Midcontinent Independent System Operator (MISO) | BM8: Entergy Texas | BP8: Yes | BQ8: Yes | BR8: Yes | BS8: No | BT8: No | BU8: No | BV8: No | BW8: Yes | CB8: 10017200239 | CG8: *RPBD* In service Oct 14, 2026 - new-build window passed (~2023-24). New-build award passed; aftermarket/MRO opportunity (first spring outage ~Apr 2027 - estimate, not sourced). Other contacts: David Borde (CEO, Entergy Texas); James Malone (Dir. Business Development, Sargent & Lundy). | CH8: Aftermarket/spares with Keith Pollock and Entergy fossil ops supply chain; use TIC/S&L relationship for Entergy program plants. | CI8: *RPBD* OVERVIEW: 1,215 MW natural-gas COMBINED-CYCLE plant, Entergy Texas' newest unit; entered commercial service Oct 14, 2026; serves ~230,000 homes in industrial Southeast Texas. TECHNOLOGY & EQUIPMENT: Mitsubishi Power powertrain - 2x M501JAC gas turbines, HRSGs and steam turbine (2x1 configuration); dual-fuel, hydrogen-capable (30% H2 at start, designed for up to 100%). SITE: BROWNFIELD - ~26.2-acre footprint inside/adjacent to Entergy Texas' existing Sabine Power Plant in Bridge City, Orange County (existing gas plant with transmission and water infrastructure). OWNERSHIP/EPC: Entergy Texas; EPC consortium Mitsubishi Power (powertrain), Sargent & Lundy (engineer of record), TIC - The Industrial Company (constructor). STATUS: Construction Apr 2023-2026, first fire Apr 2026, in service Oct 2026. INVESTMENT: Total project investment ~$1.2B (power-eng.com); Yes Energy $555M not confirmed; est. W&C value $9,720,000 ($8/kW). W&C NEEDS: New-build cable scope complete. Remaining: MRO/spares (MV, 600V, tray & instrumentation cable), outage and warranty/punch-list work; reference project for the same TIC/S&L/Mitsubishi team now building Entergy's LA/MS/AR plants. Ref: https://www.click2houston.com/news/local/2026/10/14/entergy-texas-orange-county-advanced-power-station-now-delivering-power-to-southeast-texas/ | https://www.power-eng.com/gas/turbines/entergy-texas-1-2-gw-ccgt-plant-is-now-online/ | https://www.sargentlundy.com/projects/orange-county-advanced-power-station/ | CJ8: *RPBD* Total project investment: ~$1.2B (power-eng.com); Yes Energy $555M not confirmed. Est. W&C value: $9,720,000 ($8/kW).
A9: Burke | B9: Jim | C9: Vistra Corp | D9: New | E9: Sales | F9: Stephan Hardt | H9: President & CEO | I9: End User | J9: Energy | O9: Yes | AD9: Vast Sands Power I (Vistra Permian Basin expansion) | AE9: Vast Sands Power I (TEF - Due Diligence) (Yes Energy); ERCOT 28INR0105 (+ Vast Sands II 28INR0109); Permian Power I & II; Permian Power I LLC | AF9: Vistra Corp (Luminant) | AG9: Advanced Development - FID Sep 2025; TEF loan Jun 2026 | AH9: IPP | AI9: =AL9*1000*Guide!$B$81 | AK9: 46874 | AL9: 440 | AN9: Power Generation | AO9: Generation | AP9: New Capacity/New Build | AQ9: New Load Growth | AR9: Generation | AS9: Natural gas generation - electrical BoP (MV/LV power, tray/control & instrumentation cable, substation) | AT9: Brownfield | AU9: Traditional | AV9: Natural Gas | AW9: No | AX9: 600 N Yucca Dr | AY9: Monahans | AZ9: TX | BA9: 79756 | BB9: United States | BC9: Ward | BE9: Vistra / Luminant Generation Co | BG9: Vistra (Permian Power I LLC) | BL9: Electric Reliability Council of Texas (ERCOT) | BM9: ERCOT (West Texas) | BP9: Yes | BQ9: Yes | BR9: Yes | BS9: No | BT9: No | BU9: No | BV9: No | BW9: Yes | CB9: 10018470514 | CG9: *RPBD* AWARD (PO) DATE BASIS: FID Sep 2025; $583M TEF loan (Jun 2026) with $172M drawn by 6/30/26 = heavy early spend; COD May/Jun 2028 -> cable window Dec 2026-Jun 2027, early packages may already be placed. EPC/OEM not public. No project-level contact public - Jim Burke is exec-level only (quoted in releases). TCEQ NAPD for permit 178462 should list applicant contact (Luminant Generation Co). | CH9: URGENT: identify EPC via TCEQ 178462 NAPD / Industrial Info; find Luminant project contact; quote both units (880 MW). | CI9: *RPBD* OVERVIEW: Vistra/Luminant expansion of the existing Permian Basin Power Plant in Monahans - two new large natural-gas SIMPLE-CYCLE units totaling 860 MW (ERCOT queue: Vast Sands Power I 28INR0105 and II 28INR0109, ~440 MW each), taking the site from 325 MW to 1,185 MW. Driven by Permian oil & gas load growth. TECHNOLOGY & EQUIPMENT: 2x dual-fuel (gas/oil) advanced-class combustion turbine generators with SCR and oxidation catalyst (TCEQ permit 178462); ~440 MW per unit implies H/J-class frames (OEM not published). SITE: BROWNFIELD - existing operating gas plant at 600 N Yucca Dr, Monahans, Ward County (existing 5x 65 MW CTs, gas supply and ERCOT interconnection in place); acreage not published. OWNERSHIP/STATUS: Permian Power I LLC (Vistra). FID Sep 29, 2025; $583M Texas Energy Fund loan Jun 2026 ($172M drawn by Jun 30, 2026); COD May/Jun 2028. EPC not public. INVESTMENT: Total project investment Not disclosed; financed in part by $583M Texas Energy Fund loan (3.0%, Jun 2026); est. W&C value $3,520,000 ($8/kW). W&C NEEDS (simple-cycle peaker): MV power cable (5-35 kV) for auxiliary transformers, MV switchgear, fuel-gas compressors and black-start/aux systems; 600V power & TC-ER tray cable for turbine packages, MCCs, fuel oil forwarding (if dual fuel) and SCR/ammonia systems; shielded instrumentation & control cable; bare copper grounding grid per unit and switchyard; switchyard control/relay cable; building wire for control/admin buildings. Less cable per MW than a CC (no HRSG/steam cycle). Dual-fuel adds fuel-oil system cabling. Ref: https://gov.texas.gov/news/post/governor-abbott-announces-texas-energy-fund-loan-for-860-mw-of-new-power-in-west-texas | https://investor.vistracorp.com/2025-09-29-Vistra-Announces-Plans-to-Build-New-Gas-Fueled-Dispatchable-Power-Units-in-the-Permian-Basin | https://www.gem.wiki/Permian_Power_power_station | https://www.tceq.texas.gov/downloads/permitting/air/bilingual/pending-permit-notices/178462-pls-english.pdf | CJ9: *RPBD* Total project investment: Not disclosed; financed in part by $583M Texas Energy Fund loan (3.0%, Jun 2026). Est. W&C value: $3,520,000 ($8/kW).
A10: Anderson | B10: Rick | C10: Georgia Power | D10: New | E10: Sales | F10: Stephan Hardt | H10: SVP & Senior Production Officer | I10: End User | J10: Energy | O10: Yes | AD10: Plant Yates Unit 9 (Yates CT Units 8-10) | AE10: Plant Yates Project (June 2027) (Yes Energy); Yates CT Units 8, 9, 10 | AF10: Georgia Power (Southern Company) | AG10: Under Construction - Unit 9 equipment on site Dec 2025 | AH10: IOU | AI10: =AL10*1000*Guide!$B$81 | AK10: 46568 | AL10: 482.8 | AN10: Power Generation | AO10: Generation | AP10: New Capacity/New Build | AQ10: New Load Growth | AR10: Generation | AS10: Natural gas generation - electrical BoP (MV/LV power, tray/control & instrumentation cable, substation) | AT10: Brownfield | AU10: Traditional | AV10: Natural Gas | AW10: No | AX10: 708 Dyer Road (third-party directory) | AY10: Newnan | AZ10: GA | BA10: 30263 | BB10: United States | BC10: Coweta | BE10: Georgia Power | BF10: Mitsubishi Power Americas + Black & Veatch Construction (EPC consortium, contract 1/12/2024) | BG10: Georgia Power | BI10: Mitsubishi Power M501JAC CTs; Mitsubishi Electric VP-X generators | BL10: Southeast (SE) | BM10: Georgia Power | BP10: Yes | BQ10: Yes | BR10: Yes | BS10: No | BT10: No | BU10: No | BV10: No | BW10: Yes | CB10: 10018823691 | CG10: *RPBD* LOW PROBABILITY: Unit 8 COD Q4 2026, Unit 9 Q2 2027, Unit 10 Q3 2027 (Southern Q2 2026 10-Q). Bulk cable likely bought 2024-25 by Mitsubishi/B&V consortium (award date set to COD-12 mo; already passed). Remaining: Unit 10 top-ups, change orders, spares. Other contacts: Cheryl Boddiford (SVP Mfg & Supply Chain, Mitsubishi Power); Rick Janik (B&V PM on Plant Barry Unit 8 - same EPC pairing, not confirmed for Yates). GA PSC docket 55931. | CH10: Relationship/spares play via B&V site procurement; position with Mitsubishi/B&V for next Georgia Power CT/CC builds. | CI10: *RPBD* OVERVIEW: Georgia Power's first new gas turbines in a decade - three simple-cycle PEAKING units (~1,300 MW total, ~442-463 MW each) at Plant Yates; this record is Unit 9 (COD Q2 2027). Unit 8 Q4 2026, Unit 10 Q3 2027. ~600 construction jobs. Driven by Georgia load growth (data centers/industrial). TECHNOLOGY & EQUIPMENT: 3x Mitsubishi Power M501JAC air-cooled combustion turbines with Mitsubishi Electric VP-X generators (assembled in Savannah, GA); dual-fuel gas/oil; ~30-minute start; hydrogen-capable with modifications. SITE: BROWNFIELD - existing Plant Yates generating site (former coal/gas station on the Chattahoochee River), Newnan, Coweta County, with existing transmission yard. OWNERSHIP/EPC: Georgia Power (Southern Company); EPC consortium Mitsubishi Power Americas + Black & Veatch Construction (contract Jan 12, 2024). Cost not public (PSC staff ~$1B for 3 units). GA PSC monitoring docket 55931. INVESTMENT: Total project investment Not public; PSC staff ~$1B for 3 units; est. W&C value $3,862,400 ($8/kW). W&C NEEDS (simple-cycle peaker): MV power cable (5-35 kV) for auxiliary transformers, MV switchgear, fuel-gas compressors and black-start/aux systems; 600V power & TC-ER tray cable for turbine packages, MCCs, fuel oil forwarding (if dual fuel) and SCR/ammonia systems; shielded instrumentation & control cable; bare copper grounding grid per unit and switchyard; switchyard control/relay cable; building wire for control/admin buildings. Less cable per MW than a CC (no HRSG/steam cycle). Window: bulk cable for all 3 units most likely purchased 2024-25; remaining top-ups, change orders, spares. Ref: https://www.georgiapower.com/news-hub/press-releases/turbine-generator-unit-9-plant-yates.html | https://www.energy.gov/sites/default/files/2026-07/20260622_EnvReview_Completion_Yates.pdf | https://www.modernpowersystems.com/news/progress-at-1-3-gw-plant-yates-gas-fired-plant/ | CJ10: *RPBD* Total project investment: Not public; PSC staff ~$1B for 3 units. Est. W&C value: $3,862,400 ($8/kW).
A11: Ruiz | B11: Carlos | C11: Entergy | D11: New | E11: Sales | F11: Stephan Hardt | H11: VP, Power Development - New Generation | I11: End User | J11: Energy | O11: Yes | AD11: Ironwood Power Station | AE11: Ironwood Power Station 1A Project (Yes Energy); Lake Catherine 5 (LC5); EIA 69750 | AF11: Entergy Arkansas | AG11: Under Construction - groundbreaking Aug 20, 2026 | AH11: IOU | AI11: =AL11*1000*Guide!$B$81 | AK11: 47118 | AL11: 446 | AN11: Power Generation | AO11: Generation | AP11: New Capacity/New Build | AQ11: Replacement / End-of-Life | AR11: Generation | AS11: Natural gas generation - electrical BoP (MV/LV power, tray/control & instrumentation cable, substation) | AT11: Brownfield | AU11: Traditional | AV11: Natural Gas | AW11: No | AX11: Lake Catherine Power Generation site | AY11: Jones Mill (Malvern) | AZ11: AR | BB11: United States | BC11: Hot Spring | BE11: Entergy Arkansas | BF11: TSL Power Partners (TIC/Kiewit + Sargent & Lundy) with Mitsubishi Power Americas (per TIC Entergy Program page) | BG11: Entergy Arkansas | BI11: Mitsubishi Power (implied by TSL/MPWA program) | BL11: Midcontinent Independent System Operator (MISO) | BM11: Entergy Arkansas | BP11: Yes | BQ11: Yes | BR11: Yes | BS11: No | BT11: No | BU11: No | BV11: No | BW11: Yes | CB11: 10019705142 | CG11: *RPBD* AWARD (PO) DATE BASIS: site construction Q2 2026-Q2 2028, groundbreaking Aug 20 2026, COD Q4 2028 -> bulk cable after underground/foundations ~Q1-Q2 2027. Best new-buy opportunity. TSL procures in its own name; S&L writes cable specs/BOMs. TSL address: 8900 Renner Blvd, Lenexa KS 66219. Other contacts: Laura Landreaux (CEO, Entergy AR); Louise Duncan (VP Power Plant Ops, Entergy AR); Jason Rees (Dir. Procurement, Entergy - LinkedIn, verify). Entergy supplier registration: esupplier@entergy.com. | CH11: Get on TSL Power Partners bidder list (Kiewit/TIC Lenexa) and S&L approved-manufacturer list; register with Entergy supplier program. | CI11: *RPBD* OVERVIEW: 446 MW natural-gas SIMPLE-CYCLE combustion turbine (Entergy Arkansas 'Next Generation Arkansas'), replacing the 50+ year-old Lake Catherine Unit 4 (retiring end-2027). Formerly 'Lake Catherine 5'. ~260 peak construction jobs; Entergy prioritizing Arkansas contractors (vendor fair Mar 18, 2026). TECHNOLOGY & EQUIPMENT: single advanced-class combustion turbine generator, hydrogen-capable (30% co-fire, future 100% conversion); Mitsubishi implied by the TSL/Mitsubishi Entergy program. SITE: BROWNFIELD - ~20 acres within the existing Lake Catherine Power Generation site, Jones Mill near Malvern, Hot Spring County; reuses existing gas, water and transmission infrastructure. OWNERSHIP/EPC: Entergy Arkansas; EPC TSL Power Partners (TIC/Kiewit + Sargent & Lundy) with Mitsubishi Power Americas (per TIC Entergy Program page). APSC CCN approved Apr 2025; site construction Q2 2026-Q2 2028; groundbreaking Aug 20, 2026; COD Q4 2028. Cost recovered via GAJA rider (not disclosed). INVESTMENT: Total project investment Not disclosed (GAJA rider); est. W&C value $3,568,000 ($8/kW). W&C NEEDS (simple-cycle peaker): MV power cable (5-35 kV) for auxiliary transformers, MV switchgear, fuel-gas compressors and black-start/aux systems; 600V power & TC-ER tray cable for turbine packages, MCCs, fuel oil forwarding (if dual fuel) and SCR/ammonia systems; shielded instrumentation & control cable; bare copper grounding grid per unit and switchyard; switchyard control/relay cable; building wire for control/admin buildings. Less cable per MW than a CC (no HRSG/steam cycle). Ref: https://www.entergy.com/news/entergy-arkansas-breaks-ground-on-ironwood-power-station | https://www.modernpowersystems.com/news/entergy-arkansas-starts-construction-on-446-mw-ironwood-power-station/ | https://www.entergy.com/news/ironwood-power-plant-vendor-fair-for-arkansas-contractors-announced | CJ11: *RPBD* Total project investment: Not disclosed (GAJA rider). Est. W&C value: $3,568,000 ($8/kW).
A12: Smith Jr. | B12: John Robert | C12: Duke Energy | D12: New | E12: Sales | F12: Stephan Hardt | H12: General Manager, New Gas Generation Development | I12: End User | J12: Energy | O12: Yes | AD12: Person County Combined Cycle 1 (CC1) | AE12: Person County Advanced CC1 (Yes Energy); Person County Energy Complex (Roxboro site); NCUC E-2 Sub 1318; sister CC2 E-2 Sub 1349 | AF12: Duke Energy Progress | AG12: Under Construction - groundbreaking Feb 2026; GTs arriving 2026 | AH12: IOU | AI12: =AL12*1000*Guide!$B$81 | AK12: 47118 | AL12: 1360 | AN12: Power Generation | AO12: Generation | AP12: New Capacity/New Build | AQ12: New Load Growth | AR12: Generation | AS12: Natural gas generation - electrical BoP (MV/LV power, tray/control & instrumentation cable, substation) | AT12: Brownfield | AU12: Traditional | AV12: Natural Gas | AW12: No | AX12: Semora Road, Roxboro Steam Plant property | AY12: Semora (Roxboro) | AZ12: NC | BA12: 27343 | BB12: United States | BC12: Person | BE12: Duke Energy Progress / NCEMC (co-owner ~225 MW) | BF12: Zachry Group | BG12: Duke Energy Progress | BI12: GE Vernova (advanced-class GTs) | BL12: Southeast (SE) | BM12: Duke Energy Progress | BP12: Yes | BQ12: Yes | BR12: Yes | BS12: No | BT12: No | BU12: Yes | BV12: No | BW12: Yes | BY12: Person County CC1 | BZ12: Duke Energy Progress grid (two new tie lines) | CB12: 10017400436 | CG12: *RPBD* AWARD (PO) DATE BASIS: Zachry EPC Aug 2025, groundbreaking Feb 13 2026, first GE Vernova GT on site Jul 23 2026, Zachry craft hiring from Jul 2026; COD Q4 2028 (SC ORS) -> bulk MV/600V/tray bid likely now; act immediately. CC2 (Q4 2029, likely Zachry) -> separate close ~12/15/2027. Other contacts: Ralph Biediger (EPC Group President, Zachry); Bill Norton (Duke spokesperson). Utility is Duke Energy Progress (not DEC). | CH12: Engage Zachry procurement now for CC1 (+CC2 combined buy); contact John Robert Smith Jr. (Duke PM&C). | CI12: *RPBD* OVERVIEW: 1,360 MW natural-gas COMBINED-CYCLE block (first of two identical blocks, 2,720 MW total) at Duke's 'Person County Energy Complex' (Roxboro plant), enabling retirement of Roxboro coal units 1 & 4. NCEMC co-owns ~225 MW. Nearby Microsoft-owned Person County Mega Park (~1,350 acres). TECHNOLOGY & EQUIPMENT: 2x1 advanced-class, hydrogen-capable CC - 2x GE Vernova gas turbines, 2x HRSGs, 1x GE Vernova steam turbine generator (~450 tons); first GT on site Jul 23, 2026. SITE: BROWNFIELD - ~50 acres of undeveloped land within the existing Roxboro coal plant property, Semora Road side, Semora/Roxboro, Person County. OWNERSHIP/EPC: Duke Energy Progress (majority) + NCEMC; full EPC Zachry Group (awarded Aug 2025). NCUC CPCN Oct 2025; groundbreaking Feb 13, 2026; COD Q4 2028 (CC2 Q4 2029). Cost ~$2.13B (CC1). Two new tie lines from the site. INVESTMENT: Total project investment ~$2.13B (CC1, DEP Class 3 estimate); est. W&C value $10,880,000 ($8/kW). W&C NEEDS (combined cycle): MV power cable (5-35 kV) from unit auxiliary/station service transformers to plant MV switchgear and large motors (boiler feed pumps, condensate & circulating water pumps, cooling tower/ACC fans, gas compressors); 600V power & TC-ER tray cable for MCCs, HRSG/steam-turbine auxiliaries, BOP and water treatment; shielded instrumentation & control cable (DCS, turbine controls, CEMS); bare copper grounding grid; switchyard control/relay cable; lighting, building wire and fire-alarm in admin/warehouse/control buildings. CC2 doubles the scope ~1 year later with the same EPC. Ref: https://zachrygroup.com/press-releases/Duke_Energy_Awards_EPC_Contract_for_the_first_Person_County_Combined_Cycle_Project_to_Zachry_Group.html | https://www.duke-energy.com/info/person | https://www.theassemblync.com/news/business/person-county-microsoft-data-center-nondisclosure-agreements/ | CJ12: *RPBD* Total project investment: ~$2.13B (CC1, DEP Class 3 estimate). Est. W&C value: $10,880,000 ($8/kW).
A13: Rufus | B13: Ernest | C13: Entergy | D13: New | E13: Sales | F13: Stephan Hardt | H13: Senior Manager, Capital Projects (Delta Blues & Vicksburg) | I13: End User | J13: Energy | O13: Yes | AD13: Delta Blues Advanced Power Station | AE13: Delta Blues Power Project (May 2028) (Yes Energy); EIA 67914; Superpower Mississippi; replaces Gerald Andrus plant | AF13: Entergy Mississippi | AG13: Under Construction - HRSG erection underway | AH13: IOU | AI13: =AL13*1000*Guide!$B$81 | AK13: 46874 | AL13: 754 | AN13: Power Generation | AO13: Generation | AP13: New Capacity/New Build | AQ13: Replacement / End-of-Life | AR13: Generation | AS13: Natural gas generation - electrical BoP (MV/LV power, tray/control & instrumentation cable, substation) | AT13: Brownfield | AU13: Traditional | AV13: Natural Gas | AW13: No | AX13: 85 Stokes King Road | AY13: Greenville | AZ13: MS | BA13: 38701 | BB13: United States | BC13: Washington | BE13: Entergy Mississippi | BF13: TSL Power Partners (Kiewit / TIC) | BG13: Entergy Mississippi | BI13: Mitsubishi Power M501JAC (per GEM) | BL13: Midcontinent Independent System Operator (MISO) | BM13: Entergy Mississippi | BP13: Yes | BQ13: Yes | BR13: Yes | BS13: No | BT13: No | BU13: Yes | BV13: No | BW13: Yes | BX13: 1.5 | BY13: Delta Blues Advanced Power Station | BZ13: Existing substation at Gerald Andrus station | CB13: 10018299981 | CG13: *RPBD* MAIN WINDOW LIKELY PASSED: HRSG erection May 2026 ("anchor bolts up"), COD May 2028 -> bulk cable likely bought; remaining late releases, change orders, I&C top-ups. EPC TSL Power Partners (Kiewit/TIC), Kiewit 200+ on site. Use as entry to TSL Entergy program buy for sister plants. Yes Energy 879 MW/$651M vs Entergy 754 MW/$1.2B. | CH13: Contact Ernest Rufus and TSL/TIC procurement now - target program buy for Vicksburg/Ironwood/Waterford. | CI13: *RPBD* OVERVIEW: 754 MW natural-gas COMBINED-CYCLE plant ('Superpower Mississippi'), replacing the aging Gerald Andrus Steam Electric Station; serves ~385,000 homes across Entergy Mississippi's 45 counties. TECHNOLOGY & EQUIPMENT: 1x1 combined cycle - Mitsubishi Power M501JAC gas turbine (per GEM), HRSG (modules being lifted May 2026), steam turbine; dual-fuel, hydrogen-blend capable. SITE: BROWNFIELD-ADJACENT - new footprint within ~1 mile of the Andrus plant, 85 Stokes King Road, Greenville, Washington County; reuses Andrus transmission and gas infrastructure (acreage not published). INTERCONNECTION: ~1.5 miles of new transmission line to the existing substation next to Andrus; new Delta Blues substation. OWNERSHIP/EPC: Entergy Mississippi; EPC TSL Power Partners (Kiewit Power Constructors / TIC; Kiewit 200+ on site). Groundbreaking Nov 2024; COD May 2028; ~$1.2B. INVESTMENT: Total project investment ~$1.2B (Entergy); Yes Energy $651M not confirmed; est. W&C value $6,032,000 ($8/kW). W&C NEEDS (combined cycle): MV power cable (5-35 kV) from unit auxiliary/station service transformers to plant MV switchgear and large motors (boiler feed pumps, condensate & circulating water pumps, cooling tower/ACC fans, gas compressors); 600V power & TC-ER tray cable for MCCs, HRSG/steam-turbine auxiliaries, BOP and water treatment; shielded instrumentation & control cable (DCS, turbine controls, CEMS); bare copper grounding grid; switchyard control/relay cable; lighting, building wire and fire-alarm in admin/warehouse/control buildings. Plus ~1.5 mi transmission line conductor and substation cable. Status: above-ground erection since May 2026 - bulk cable likely ordered. Ref: https://www.power-eng.com/gas/combined-cycle/entergy-mississippi-breaks-ground-on-754-mw-combined-cycle-plant/ | https://www.entergy.com/blog/delta-blues-reaches-important-milestone-in-construction | https://www.gem.wiki/Delta_Blues_Advanced_Power_Station | https://opcgis.deq.state.ms.us/ensearchonline/ai_info.aspx?ai=86260 | CJ13: *RPBD* Total project investment: ~$1.2B (Entergy); Yes Energy $651M not confirmed. Est. W&C value: $6,032,000 ($8/kW).
A14: Rufus | B14: Ernest | C14: Entergy | D14: New | E14: Sales | F14: Stephan Hardt | H14: Senior Manager, Capital Projects (Vicksburg role to confirm) | I14: End User | J14: Energy | O14: Yes | AD14: Vicksburg Advanced Power Station | AE14: Vicksburg Advanced Power Project (Aug 2028) (Yes Energy); EIA 69223; former Baxter Wilson site; Superpower Mississippi | AF14: Entergy Mississippi | AG14: Under Construction - groundbreaking Oct 2025 | AH14: IOU | AI14: =AL14*1000*Guide!$B$81 | AK14: 46966 | AL14: 754 | AN14: Power Generation | AO14: Generation | AP14: New Capacity/New Build | AQ14: New Load Growth | AR14: Generation | AS14: Natural gas generation - electrical BoP (MV/LV power, tray/control & instrumentation cable, substation) | AT14: Brownfield | AU14: Traditional | AV14: Natural Gas | AW14: No | AX14: 770 Kemp Bottom Rd (former Baxter Wilson site) | AY14: Vicksburg | AZ14: MS | BB14: United States | BC14: Warren | BE14: Entergy Mississippi | BF14: TSL Power Partners (TIC/Kiewit + Sargent & Lundy) with Mitsubishi Power Americas (per TIC Entergy Program page) | BG14: Entergy Mississippi | BI14: Unverified (Yes Energy: Mitsubishi) | BL14: Midcontinent Independent System Operator (MISO) | BM14: Entergy Mississippi | BP14: Yes | BQ14: Yes | BR14: Yes | BS14: No | BT14: No | BU14: No | BV14: No | BW14: Yes | CB14: 10019088992 | CG14: *RPBD* URGENT: groundbreaking Oct 21 2025, Baxter Wilson demolition Dec 2025, COD Aug 2028 -> cable window now through ~Feb 2027; may be partly placed if TSL bought with Delta Blues. Linked contextually to AWS $3B Vicksburg campus. Entergy MS media line 769-262-0745. | CH14: Engage TSL/TIC procurement now; confirm Ernest Rufus covers Vicksburg (confirmed on Delta Blues only) and ask for the named project buyer. | CI14: *RPBD* OVERVIEW: 754 MW natural-gas COMBINED-CYCLE plant, next phase of 'Superpower Mississippi'; ~560 construction jobs, 21 permanent. Contextually linked to Amazon/AWS's $3B Vicksburg data-center campus (AWS covers its service-extension costs). TECHNOLOGY & EQUIPMENT: combined cycle (gas turbine + HRSG + steam turbine), hydrogen-blend capable and carbon-capture enabled; turbine OEM not confirmed (Mitsubishi likely via TSL/Mitsubishi Entergy program). SITE: BROWNFIELD - former Baxter Wilson Steam Electric Station (1960s gas/oil plant, retired 2022; large structures demolished Dec 17, 2025), 770 Kemp Bottom Rd, Vicksburg, Warren County, on the Mississippi River; existing transmission/gas corridors (acreage not published). OWNERSHIP/EPC: Entergy Mississippi; EPC TSL Power Partners (TIC/Kiewit + Sargent & Lundy) with Mitsubishi Power Americas (per TIC Entergy Program page). Groundbreaking Oct 21, 2025; COD Aug 2028; ~$1.2B. INVESTMENT: Total project investment ~$1.2B (Entergy); Yes Energy $700M not confirmed; est. W&C value $6,032,000 ($8/kW). W&C NEEDS (combined cycle): MV power cable (5-35 kV) from unit auxiliary/station service transformers to plant MV switchgear and large motors (boiler feed pumps, condensate & circulating water pumps, cooling tower/ACC fans, gas compressors); 600V power & TC-ER tray cable for MCCs, HRSG/steam-turbine auxiliaries, BOP and water treatment; shielded instrumentation & control cable (DCS, turbine controls, CEMS); bare copper grounding grid; switchyard control/relay cable; lighting, building wire and fire-alarm in admin/warehouse/control buildings. Ref: https://www.entergymississippi.com/generation/vicksburg | https://www.powermag.com/entergy-mississippi-adding-third-gas-fired-power-plant-to-superpower-strategy/ | https://www.datacenterdynamics.com/en/news/amazon-to-build-3bn-data-center-campus-in-vicksburg-mississippi/ | CJ14: *RPBD* Total project investment: ~$1.2B (Entergy); Yes Energy $700M not confirmed. Est. W&C value: $6,032,000 ($8/kW).
A15: Niland | B15: John E. | C15: Invenergy | D15: New | E15: Sales | F15: Stephan Hardt | H15: VP, New Technology & Thermal Development | I15: Contractor | J15: Energy | O15: Yes | AD15: Sycamore Riverside Energy Center | AE15: Sullivan Generating Station (May 2027) (Yes Energy); Sullivan Generating Station 1 & 2 (PJM AB1-087/AB1-088); IURC Cause 46389 | AF15: Indiana Michigan Power (AEP) | AG15: Advanced Development - IURC CPCN order expected end-2026 | AH15: IOU | AI15: =AL15*1000*Guide!$B$81 | AK15: 47208 | AL15: 918 | AM15: 345 | AN15: Power Generation | AO15: Generation | AP15: New Capacity/New Build | AQ15: New Load Growth | AR15: Generation | AS15: Natural gas generation - electrical BoP (MV/LV power, tray/control & instrumentation cable, substation) | AT15: Brownfield | AU15: Traditional | AV15: Natural Gas | AW15: No | AX15: Adjacent to former I&M Breed Generating Station | AY15: Fairbanks Township | AZ15: IN | BB15: United States | BC15: Sullivan | BE15: Invenergy (to be acquired by I&M at COD) | BF15: The Boldt Company (constructor per Boldt project page - role to confirm) | BG15: Invenergy | BI15: GE Vernova (4x 7F.05 CTs) | BL15: PJM Interconnection (PJM) | BM15: Indiana Michigan Power (AEP) | BP15: Yes | BQ15: Yes | BR15: Yes | BS15: No | BT15: No | BU15: No | BV15: No | BW15: Yes | CB15: 10019254864 | CG15: *RPBD* AWARD (PO) DATE BASIS: Boldt lists construction Sep 2026-Feb 2029 (built at risk before IURC order expected end-2026); COD Mar 31 2029 -> cable window Q1-Q3 2027; Invenergy/Boldt buy, not I&M. Other contacts: Daniel Runyan (SVP Development, Invenergy); Steve Baker (President & COO, I&M); Timothy B. Gaul (Dir. Regulated Infrastructure Development, AEPSC); Timothy C. Kerns (Sterling Industrial - owner's engineer witness). PJM (not MISO), 918 MW SC (not 1,150 MW CC). Existing Salesforce opportunity (CRM: 930 MW combined cycle, award 10/1/2026) - update CRM to 918 MW simple cycle; merge Sullivan Generating Station 1 & 2 duplicates. | CH15: Engage Boldt procurement and Invenergy thermal construction now (Q4 2026-Q1 2027) for MV/600V/tray bid lists. | CI15: *RPBD* OVERVIEW: ~918-935 MW natural-gas SIMPLE-CYCLE PEAKING plant developed by Invenergy and to be acquired by Indiana Michigan Power (AEP) at COD (Mar 31, 2029) to meet data-center-driven load growth (AWS, Google, Microsoft). Formerly queued as Sullivan Generating Station 1 & 2 (1,150 MW CC concept). TECHNOLOGY & EQUIPMENT: 4x GE Vernova 7F.05 combustion turbines (~232 MW each), dual-fuel natural gas with ultra-low-sulfur distillate backup; gas via ~5.5-mile 24-inch ONEOK lateral. SITE: BROWNFIELD-ADJACENT - next to I&M's retired, demolished Breed coal plant, CR 925N, Fairbanks Township, Sullivan County; ~64-acre plant footprint within ~356-acre parcel (local meeting summary - verify). Invenergy holds land under purchase option. INTERCONNECTION: AEP/I&M Sullivan 345 kV station (new 345 kV breakers), PJM. OWNERSHIP/STATUS: Invenergy (developer) -> I&M; IURC Cause 46389 order expected end-2026; constructor The Boldt Company lists construction Sep 2026-Feb 2029; ~$500M capital (Invenergy). INVESTMENT: Total project investment ~$500M capital investment (Invenergy); est. W&C value $7,344,000 ($8/kW). W&C NEEDS (simple-cycle peaker): MV power cable (5-35 kV) for auxiliary transformers, MV switchgear, fuel-gas compressors and black-start/aux systems; 600V power & TC-ER tray cable for turbine packages, MCCs, fuel oil forwarding (if dual fuel) and SCR/ammonia systems; shielded instrumentation & control cable; bare copper grounding grid per unit and switchyard; switchyard control/relay cable; building wire for control/admin buildings. Less cable per MW than a CC (no HRSG/steam cycle). Dual-fuel adds fuel-oil system cabling. Ref: https://www.aep.com/news/stories/view/11850/ | https://sycamoreriverside.invenergy.com/about-project | https://www.pjm.com/pub/planning/project-queues/facilities/ab1087_fac.pdf | https://www.gem.wiki/Sycamore_Riverside_Energy_Center | CJ15: *RPBD* Total project investment: ~$500M capital investment (Invenergy). Est. W&C value: $7,344,000 ($8/kW).
A16: Pressler | B16: Nicholas D. | C16: Entergy Services LLC | D16: New | E16: Sales | F16: Stephan Hardt | H16: Director, Power Development | I16: End User | J16: Energy | O16: Yes | AD16: Franklin Farms Power Station (Units 1 & 2) | AE16: Titanium Advanced Power Station CCCT Project (Yes Energy / air permit); EIA 68214; MISO E0014; LPSC U-37425 | AF16: Entergy Louisiana | AG16: Under Construction - groundbreaking Dec 1, 2025 | AH16: IOU | AI16: =AL16*1000*Guide!$B$81 | AK16: 47088 | AL16: 1508 | AM16: 500 | AN16: Power Generation | AO16: Generation | AP16: New Capacity/New Build | AQ16: Load Interconnection | AR16: Generation | AS16: Natural gas generation - electrical BoP (MV/LV power, tray/control & instrumentation cable, substation) | AT16: Greenfield | AU16: Traditional | AV16: Natural Gas | AW16: Yes | AX16: Franklin Farms site, LA Hwy 183 | AY16: Holly Ridge | AZ16: LA | BB16: United States | BC16: Richland Parish | BE16: Entergy Louisiana (state-owned Franklin Farms site) | BF16: TSL Power Partners (TIC / Sargent & Lundy) with Mitsubishi Power Americas | BG16: Entergy Louisiana | BI16: Mitsubishi Power M501JAC (2x 1x1 CC) | BL16: Midcontinent Independent System Operator (MISO) | BM16: Entergy Louisiana | BP16: Yes | BQ16: Yes | BR16: Yes | BS16: No | BT16: No | BU16: No | BV16: No | BW16: Yes | CB16: 10019228423 | CG16: *RPBD* AWARD (PO) DATE BASIS: groundbreaking Dec 1 2025, COD Dec 2028; IMI valve order Sep 2026 says detailed engineering still active -> cable window Dec 2026-Jun 2027, early MV/grounding packages possibly Q4 2026. EPC TSL Power Partners/Kiewit + Mitsubishi. Other contacts: Phillip May (CEO, Entergy LA); Carlos Ruiz (VP Power Development, Entergy); Jim Niemiec (VP & Chief Supply Chain Officer, Entergy); media Brandon Scardigli 504-576-4132. Separate 500 kV transmission opportunity. | CH16: Engage TSL/TIC procurement now; contact Nicholas Pressler; open separate 500 kV transmission opportunity. | CI16: *RPBD* OVERVIEW: ~1,508 MW natural-gas COMBINED-CYCLE station (two units) built to power Meta's Hyperion AI data-center campus; Meta pays the plants' full revenue requirement for 15 years. Air permit name 'Titanium Advanced Power Station'. ~7 more Hyperion plants (~5.2 GW) proposed, LPSC vote Dec 2026. TECHNOLOGY & EQUIPMENT: 2x 1x1 combined-cycle blocks - Mitsubishi Power M501JAC gas turbines, HRSGs, steam turbines (~754-780 MW each); hydrogen-capable (30% co-fire), carbon-capture ready; IMI valve package (Sep 2026). SITE: GREENFIELD - former agricultural land on the state-owned Franklin Farms megasite (~1,400-2,250 acres total incl. Meta campus) along LA Hwy 183 near Holly Ridge, Richland Parish. INTERCONNECTION: Entergy 500 kV system - ~100 miles of new 500 kV lines (~$1.2B), eight new 230 kV lines, Sterlington 500 kV upgrades. OWNERSHIP/EPC: Entergy Louisiana; EPC TSL Power Partners (TIC/Kiewit + Sargent & Lundy) with Mitsubishi Power. LPSC approval Aug 2025; groundbreaking Dec 1, 2025; COD Dec 2028; ~$2.39B for both units. INVESTMENT: Total project investment ~$2.39B (Franklin Farms 1 & 2, LPSC testimony); est. W&C value $12,064,000 ($8/kW). W&C NEEDS (combined cycle): MV power cable (5-35 kV) from unit auxiliary/station service transformers to plant MV switchgear and large motors (boiler feed pumps, condensate & circulating water pumps, cooling tower/ACC fans, gas compressors); 600V power & TC-ER tray cable for MCCs, HRSG/steam-turbine auxiliaries, BOP and water treatment; shielded instrumentation & control cable (DCS, turbine controls, CEMS); bare copper grounding grid; switchyard control/relay cable; lighting, building wire and fire-alarm in admin/warehouse/control buildings. Separate opportunity: HV/500 kV transmission conductor and substation cable. Ref: https://www.entergy.com/news/entergy-louisiana-breaks-ground-on-new-state-of-the-art-generation-facilities-to-power-reliability-growth-and-innovation | https://www.ticus.com/entergy-program/ | https://www.gem.wiki/Franklin_Farms_power_station | https://www.datacenterdynamics.com/en/news/entergy-breaks-ground-on-two-natural-gas-plants-for-metas-2gw-data-center-in-richland-parish-louisiana/ | CJ16: *RPBD* Total project investment: ~$2.39B (Franklin Farms 1 & 2, LPSC testimony). Est. W&C value: $12,064,000 ($8/kW).
A17: Pressler | B17: Nicholas D. | C17: Entergy Services LLC | D17: New | E17: Sales | F17: Stephan Hardt | H17: Director, Power Development | I17: End User | J17: Energy | O17: Yes | AD17: Waterford 5 Power Station | AE17: Waterford 5 Project (June 2029) (Yes Energy); EIA 69184; MISO E0029; Waterford 5 & 6 | AF17: Entergy Louisiana | AG17: Advanced Development - site prep since Nov 2025; construction late 2026 | AH17: IOU | AI17: =AL17*1000*Guide!$B$81 | AK17: 47270 | AL17: 754 | AM17: 500 | AN17: Power Generation | AO17: Generation | AP17: New Capacity/New Build | AQ17: Load Interconnection | AR17: Generation | AS17: Natural gas generation - electrical BoP (MV/LV power, tray/control & instrumentation cable, substation) | AT17: Brownfield | AU17: Traditional | AV17: Natural Gas | AW17: Yes | AX17: Entergy Waterford generating site | AY17: Killona / Taft | AZ17: LA | BB17: United States | BC17: St. Charles Parish | BE17: Entergy Louisiana | BF17: TSL Power Partners (TIC + Sargent & Lundy) - implied by LPSC Waterford 6 filing | BG17: Entergy Louisiana | BI17: Mitsubishi Power M501JAC (per GEM) | BL17: Midcontinent Independent System Operator (MISO) | BM17: Entergy Louisiana | BP17: Yes | BQ17: Yes | BR17: Yes | BS17: No | BT17: No | BU17: Yes | BV17: No | BW17: Yes | BX17: 0.25 | BY17: Waterford 5 Power Station | BZ17: Waterford 500 kV Substation | CB17: 10019089005 | CG17: *RPBD* AWARD (PO) DATE BASIS: site prep since Nov 2025, main construction late 2026, COD 2029 -> cable window mid-2027-mid-2028. Waterford 6 (754 MW, ~Jul 2030, LPSC vote Dec 16 2026, same EPC) - pitch combined WF5+6 buy (~$3.75B program). Other contact: Michelle Berg (Entergy, parish council briefing - secondary source). | CH17: Pitch combined Waterford 5+6 cable package to TSL; contact Nicholas Pressler. | CI17: *RPBD* OVERVIEW: ~754-820 MW natural-gas COMBINED-CYCLE unit approved with Franklin Farms to support Meta's Hyperion load; paired with proposed Waterford 6 (754 MW, ~Jul 2030, LPSC vote Dec 16, 2026) - ~$3.75B WF5+6 program, 700+ construction jobs 2026-2030. TECHNOLOGY & EQUIPMENT: 1x1 combined cycle - Mitsubishi Power M501JAC gas turbine, HRSG, steam turbine (EIA: 2 generators, 820 MW nameplate). SITE: BROWNFIELD - existing Entergy Waterford generating complex at Killona/Taft, St. Charles Parish, on the Mississippi River (home to Waterford 1 & 2 gas/oil units and Waterford 3 nuclear); soft soils require ~100,000 truckloads of surcharge fill (site prep since Nov 2025). INTERCONNECTION: Waterford 500 kV substation via ~0.25-mile 500 kV gen-tie (MISO E0029). OWNERSHIP/EPC: Entergy Louisiana; EPC TSL Power Partners (TIC + Sargent & Lundy) per LPSC Waterford 6 filing. Main construction late 2026; COD 2029. Cost ~ $1.2B implied. INVESTMENT: Total project investment ~$1.2B implied (similar to each Franklin Farms unit); Yes Energy $1.75B not confirmed; est. W&C value $6,032,000 ($8/kW). W&C NEEDS (combined cycle): MV power cable (5-35 kV) from unit auxiliary/station service transformers to plant MV switchgear and large motors (boiler feed pumps, condensate & circulating water pumps, cooling tower/ACC fans, gas compressors); 600V power & TC-ER tray cable for MCCs, HRSG/steam-turbine auxiliaries, BOP and water treatment; shielded instrumentation & control cable (DCS, turbine controls, CEMS); bare copper grounding grid; switchyard control/relay cable; lighting, building wire and fire-alarm in admin/warehouse/control buildings. Plus 500 kV gen-tie; bundle Waterford 5 + 6 as one cable package. Ref: https://www.entergylouisiana.com/waterford5-6 | https://www.interconnection.fyi/project/miso-e0029 | https://www.entergy.com/blog/the-dirt-on-dirt-from-digging-soil-to-boosting-louisianas-economy | CJ17: *RPBD* Total project investment: ~$1.2B implied (similar to each Franklin Farms unit); Yes Energy $1.75B not confirmed. Est. W&C value: $6,032,000 ($8/kW).
A18: Davis-Handy | B18: Brandi | C18: AES Indiana | D18: New | E18: Sales | F18: Stephan Hardt | H18: President | I18: End User | J18: Energy | O18: Yes | AD18: AES Petersburg Unit 4 Repowered | AE18: Petersburg Generating Station Unit 4 coal-to-gas conversion; IURC Cause 46022 (Units 3 & 4) | AF18: AES Indiana | AG18: Under Construction - Unit 4 conversion outage 2026 | AH18: IOU | AI18: =AL18*1000*Guide!$B$81 | AK18: 46387 | AL18: 526 | AN18: Power Generation | AO18: Generation | AP18: New Capacity/New Build | AQ18: Regulatory / Policy | AR18: Generation | AS18: Natural gas generation - electrical BoP (MV/LV power, tray/control & instrumentation cable, substation) | AT18: Brownfield | AU18: Traditional | AV18: Natural Gas | AW18: No | AX18: State Road 57 (between IN-57 and White River) | AY18: Petersburg | AZ18: IN | BA18: 47567 | BB18: United States | BC18: Pike | BE18: AES Indiana | BF18: Babcock & Wilcox (EPC) with CDM Smith (BOP EPC) | BG18: AES Indiana | BI18: Babcock & Wilcox (burners, ignitors, controls) | BL18: Midcontinent Independent System Operator (MISO) | BM18: AES Indiana | BP18: Yes | BQ18: Yes | BR18: Yes | BS18: No | BT18: No | BU18: No | BV18: No | BW18: Yes | CG18: AWARD (PO) DATE BASIS: B&W full NTP Nov 2024, CDM Smith BOP NTP Aug 2025; Unit 4 outage Jun-Oct 2026, COD end-2026 (B&W: Q1 2027) -> BOP cable likely bought Q3-Q4 2025; window passed. Remaining: Unit 4 punch-list/change orders. MW (526) from CRM - unverified. Other contacts: Chris Riker (SVP, B&W Thermal); Todd Hillman (SVP, AES Indiana). | CH18: Chase remaining Unit 4 fill-in orders via B&W Construction / CDM Smith; leverage for future B&W coal-to-gas conversions. | CI18: OVERVIEW: Coal-to-natural-gas repowering of AES Indiana's Petersburg Unit 4 (with Unit 3), ending coal at the plant; IURC approved 5-0 Nov 2024 within AES's ~$1.1B Pike County package (incl. nearby 250 MW solar + 180 MWh storage). TECHNOLOGY & EQUIPMENT: boiler fuel switch on existing 1986 coal unit (not new CTs) - new B&W gas burners, ignitors and controls; gas heaters, flue-gas recirculation for NOx, process piping; new 1-mile Midwestern Gas Transmission lateral. SITE: BROWNFIELD - existing Petersburg coal generating station on the White River, Petersburg, Pike County. INTERCONNECTION: existing unit interconnection (no new gen-tie), MISO. OWNERSHIP/STATUS: AES Indiana; EPC Babcock & Wilcox (B&W Construction Co.), BOP by CDM Smith; Unit 3 outage Feb-May 2026, Unit 4 outage Jun-Oct 2026, COD end-2026/Q1 2027. INVESTMENT: ~$293M (excl. AFUDC). W&C NEEDS (coal-to-gas boiler conversion): MV power cable for new gas heaters, FGR fans and modified auxiliaries; 600V power & TC-ER tray cable for new burner management, ignitors, valves and BOP; shielded instrumentation & control cable for burner management system/DCS tie-ins; grounding for new gas yard. Retrofit scope - smaller than a new build, outage-driven buying. Ref: https://www.babcock.com/home/about/corporate/news/babcock-and-wilcox-receives-full-notice-to-proceed-on-246-million-contract-for-indiana-power-plant-coal-to-gas-fuel-switching-project | https://www.cdmsmith.com/en/projects/aes-coal-to-gas | https://aesindiana.com/press-release/aes-indiana-receives-approval-repower-remaining-petersburg-units-coal-natural-gas | CJ18: Total project investment: ~$293M best estimate excl. AFUDC (IURC testimony; ~$246M B&W contract covers Units 3 & 4). Est. W&C value: $4,208,000 ($8/kW).
A19: Choi | B19: Logan | C19: Trumbull Energy Center | D19: Recycle | E19: Sales | F19: Stephan Hardt | H19: President & CEO | I19: End User | J19: Energy | O19: Yes | AD19: Trumbull Energy Center | AE19: Trumbull Energy Center (adjacent to Lordstown Energy Center); Clean Energy Future-Trumbull; PJM AB1-105 | AF19: Clean Energy Future, LLC (KOSPO / KIND / Siemens Energy owners) | AG19: Operating - COD Jan 2026; completion ceremony Jun 24, 2026 | AH19: IPP | AI19: =AL19*1000*Guide!$B$81 | AK19: 46053 | AL19: 950 | AM19: 345 | AN19: Power Generation | AO19: Generation | AP19: New Capacity/New Build | AQ19: New Load Growth | AR19: Generation | AS19: Natural gas generation - electrical BoP (MV/LV power, tray/control & instrumentation cable, substation) | AT19: Greenfield | AU19: Traditional | AV19: Natural Gas | AW19: No | AX19: 7733 Tod Ave SW (third-party database) | AY19: Lordstown | AZ19: OH | BA19: 44481 | BB19: United States | BC19: Trumbull | BE19: Trumbull Energy Center owners (KOSPO, KIND, Siemens Energy) | BF19: Gemma Power Systems (Argan) | BG19: Clean Energy Future, LLC | BI19: Siemens Energy (2x SGT6-8000H GT, SST6-5000 ST); Hanwha fuel-gas compressors | BL19: PJM Interconnection (PJM) | BM19: FirstEnergy (ATSI) | BP19: Yes | BQ19: Yes | BR19: Yes | BS19: No | BT19: No | BU19: No | BV19: No | BW19: Yes | CG19: Operating since Jan 2026 - new-build window passed (cable bought ~2023 after Nov 2022 NTP). Re-target as MRO/outage account (Hanwha/Siemens O&M) and use Gemma relationship for Argan pipeline (CPV Basin Ranch, Sandow Lakes). Developer is Clean Energy Future (William Siderewicz), not CPV. MW 940-977 by source. | CH19: Move to Closed/Operating; pursue MRO with plant team; leverage Gemma for current CCGT jobs. | CI19: OVERVIEW: ~940-953 MW (EIA 977 MW nameplate) baseload merchant combined-cycle plant next to the Lordstown Energy Center; commercial operation Jan 2026, completion celebrated Jun 24, 2026; framed around Midwest AI/data-center demand (no named offtaker). TECHNOLOGY & EQUIPMENT: dual-fuel 2x2x1 combined cycle - 2x Siemens Energy SGT6-8000H gas turbines, 2x HRSGs, 1x Siemens SST6-5000 steam turbine; 3x Hanwha fuel-gas compressors (9-yr maintenance contract). SITE: ~127 acres in Lordstown, Trumbull County (7733 Tod Ave SW, Warren OH 44481 - third-party). INTERCONNECTION: PJM AB1-105, Highland-Hanna 345 kV line (ATSI/FirstEnergy). OWNERSHIP/STATUS: owners KOSPO, KIND and Siemens Energy; developer Clean Energy Future LLC; EPC Gemma Power Systems (full NTP Nov 2022). INVESTMENT: ~$1.2B. W&C NEEDS: new-build scope complete; MRO/spares (MV, 600V, tray, instrumentation cable) for outages. Ref: https://www.tribtoday.com/news/local-news/2026/06/trumbull-energy-center-complete/ | https://www.gemmapower.com/our-work/combined-cycle/trumbull-energy-center/ | https://www.interconnection.fyi/project/pjm-ab1-105 | CJ19: Total project investment: ~$1.2B. Est. W&C value: $7,600,000 ($8/kW).
A20: Zamarin | B20: Chad | C20: Williams | D20: Recycle | E20: Sales | F20: Stephan Hardt | H20: President & CEO | I20: End User | J20: Energy | O20: Yes | AD20: Socrates South Power Generation | AE20: Socrates South (Williams Power Innovation); OPSB 25-0185-EL-BLN | AF20: Will-Power OH, LLC (Williams) | AG20: Operating - placed in service late Jul 2026 | AH20: IPP | AI20: =AL20*1000*Guide!$B$81 | AK20: 46234 | AL20: 200 | AN20: Power Generation | AO20: Generation | AP20: New Capacity/New Build | AQ20: Load Interconnection | AR20: Generation | AS20: Natural gas generation - electrical BoP (MV/LV power, tray/control & instrumentation cable, substation) | AT20: Greenfield | AU20: Traditional | AV20: Natural Gas | AW20: Yes | AX20: New Albany International Business Park (near Morse Rd & Mink St) | AY20: New Albany | AZ20: OH | BB20: United States | BC20: Licking | BE20: Will-Power OH, LLC | BG20: Williams (Power Innovation JV; Blackstone 49%) | BI20: Solar Titan 250 / PGM 130, Siemens SGT-400, Caterpillar 3520 engines (filed fleet) | BL20: None - behind the meter (off-grid) | BM20: None (islanded microgrid serving Meta) | BP20: Yes | BQ20: Yes | BR20: Yes | BS20: No | BT20: No | BU20: No | BV20: No | BW20: Yes | CG20: Operating since late Jul 2026 (~14 months site-to-power) - window passed. Use as reference case to get on Williams approved-vendor list for its next Power Innovation behind-the-meter projects (Blackstone JV covers 5 projects). EPC not public (check OPSB dockets). | CH20: Mark Closed; pursue Williams Power Innovation follow-on sites; find EPC via OPSB 25-0185 docket. | CI20: OVERVIEW: 200 MW behind-the-meter gas generation plant dedicated to Meta (Sidecat LLC) at the New Albany data-center campus (Prometheus AI cluster) under a 10-yr fixed-price deal (+5-yr option); in service late Jul 2026, on time and on budget. TECHNOLOGY & EQUIPMENT: simple-cycle aeroderivative/industrial turbines + reciprocating engines - filed fleet 3x Solar Titan 250, 9x PGM 130, 3x Siemens SGT-400, 15x Caterpillar 3520 engines, 8x Cat C15 500 kW diesel backup (split between North/South not public). SITE: GREENFIELD - ~20 acres in New Albany International Business Park, Licking County; two 24-inch gas laterals. INTERCONNECTION: no grid connection (OPSB condition) - on-site switching/internal substations feed Meta's adjacent campus. OWNERSHIP/STATUS: Will-Power OH LLC (Williams); Blackstone holds 49% of Power Innovation JV. INVESTMENT: ~$1.6B (North + South + pipeline). W&C NEEDS (behind-the-meter / on-site generation): MV power cable (5-35 kV) collecting many turbine/engine units to on-site switching and plant substations and feeders to the data-center campus; 600V power & TC-ER tray cable for unit packages, MCCs, gas conditioning/compression, BESS and cooling; shielded instrumentation & control cable (unit controls, microgrid/SCADA); extensive bare copper grounding; switchgear/substation control cable; building wire for control and admin buildings. High unit count = high cable density per MW. Status: built - MRO and follow-on sites. Ref: https://www.sec.gov/Archives/edgar/data/0000107263/000010726326000026/wmb-20260630.htm | https://www.power-eng.com/onsite-power/onsite-gas-turbines-reciprocating-engines-to-power-meta-data-center/ | https://www.williams.com/wp-content/uploads/sites/14/2026/02/Socrates-North-and-South-Fact-Sheet-1.pdf | CJ20: Total project investment: ~$1.6B for Socrates North + South incl. pipeline (Williams Q1 2025). Est. W&C value: $1,600,000 ($8/kW).
A21: Zamarin | B21: Chad | C21: Williams | D21: New | E21: Sales | F21: Stephan Hardt | H21: President & CEO | I21: End User | J21: Energy | O21: Yes | AD21: Socrates North Power Generation | AE21: Socrates North (Williams Power Innovation); OPSB 25-0188-EL-BGN | AF21: Will-Power OH, LLC (Williams) | AG21: Under Construction - in service expected Q4 2026 | AH21: IPP | AI21: =AL21*1000*Guide!$B$81 | AK21: 46387 | AL21: 200 | AN21: Power Generation | AO21: Generation | AP21: New Capacity/New Build | AQ21: Load Interconnection | AR21: Generation | AS21: Natural gas generation - electrical BoP (MV/LV power, tray/control & instrumentation cable, substation) | AT21: Greenfield | AU21: Traditional | AV21: Natural Gas | AW21: Yes | AX21: New Albany, Licking County (~20-acre site) | AY21: New Albany | AZ21: OH | BB21: United States | BC21: Licking | BE21: Will-Power OH, LLC | BG21: Williams (Power Innovation JV; Blackstone 49%) | BI21: Same turbine/recip fleet as Socrates South + BESS (~173 MW reported) | BL21: None - behind the meter (off-grid) | BM21: None (islanded microgrid serving Meta) | BP21: Yes | BQ21: Yes | BR21: Yes | BS21: No | BT21: No | BU21: No | BV21: No | BW21: Yes | CG21: AWARD (PO) DATE BASIS: OPSB approval Sep 18, 2025 + ~14-month fast track -> main cable likely awarded Q3-Q4 2025; window passed. Only possible open scope: BESS amendment (check OPSB docket timing). Williams 10-Q gives 556 MW combined North+South. | CH21: Check OPSB 25-0188 BESS amendment for remaining cable; target Williams next Power Innovation sites. | CI21: OVERVIEW: second 200 MW behind-the-meter gas plant for Meta's New Albany campus (Phase 2), on track for Q4 2026 per Williams; BESS amendment pending. TECHNOLOGY & EQUIPMENT: simple-cycle aeroderivative/industrial gas turbines + reciprocating engines (same design as Socrates South) plus planned battery storage (~173 MW reported across project). SITE: GREENFIELD - ~20 acres, New Albany, Licking County. INTERCONNECTION: behind the meter, no grid connection; on-site substation. OWNERSHIP/STATUS: Will-Power OH LLC (Williams); OPSB approved Sep 18, 2025. INVESTMENT: part of ~$1.6B program. W&C NEEDS (behind-the-meter / on-site generation): MV power cable (5-35 kV) collecting many turbine/engine units to on-site switching and plant substations and feeders to the data-center campus; 600V power & TC-ER tray cable for unit packages, MCCs, gas conditioning/compression, BESS and cooling; shielded instrumentation & control cable (unit controls, microgrid/SCADA); extensive bare copper grounding; switchgear/substation control cable; building wire for control and admin buildings. High unit count = high cable density per MW. Plus BESS DC/AC collection cable if amendment proceeds. Ref: https://opsb.ohio.gov/cases/25-0188-el-bgn | https://investor.williams.com/news-releases/news-release-details/williams-delivers-strong-second-quarter-2026-results-announces | CJ21: Total project investment: Included in ~$1.6B Socrates program. Est. W&C value: $1,600,000 ($8/kW).
A22: Hessen | B22: Corey | C22: Homer City Redevelopment | D22: New | E22: Sales | F22: Stephan Hardt | H22: CEO | I22: End User | J22: Energy | O22: Yes | AD22: Homer City Energy Campus | AE22: Homer City Generation, L.P.; legacy Homer City Generating Station site | AF22: Homer City Redevelopment (Homer City Generation, L.P.) | AG22: Under Construction - HRSGs installed, first GT set Oct 2026; 2,000+ workers | AH22: IPP | AI22: =AL22*1000*Guide!$B$81 | AK22: 46752 | AL22: 4400 | AN22: Power Generation | AO22: Generation | AP22: New Capacity/New Build | AQ22: Load Interconnection | AR22: Generation | AS22: Natural gas generation - electrical BoP (MV/LV power, tray/control & instrumentation cable, substation) | AT22: Brownfield | AU22: Traditional | AV22: Natural Gas | AW22: Yes | AX22: Former Homer City Generating Station | AY22: Homer City | AZ22: PA | BB22: United States | BC22: Indiana | BE22: Homer City Redevelopment (Knighthead Capital-led) | BF22: Kiewit Power Constructors Co. | BG22: Homer City Redevelopment (Knighthead Capital) | BI22: GE Vernova (7x 7HA.02 gas turbines) | BL22: PJM Interconnection (PJM) | BM22: FirstEnergy (Penelec area) | BP22: Yes | BQ22: Yes | BR22: Yes | BS22: No | BT22: No | BU22: No | BV22: No | BW22: Yes | CG22: AWARD (PO) DATE BASIS: Kiewit on site since Oct 2025, HRSG delivery Sep-Oct 2026, first GT set Oct 2026, first power late 2027/early 2028 -> main power-block cable POs very likely placed; remaining releases/change orders through Q1 2027. Bigger long-tail: Amazon 36-building data-center campus plan (construction from Dec 2026, build-out to 2036; tabled by county Sep 2026). Other contacts: Brian Reinhart (VP, Kiewit Power Constructors); Kiewit vendor inbox HomerCity.Info@Kiewit.com; press@homercityredevelopment.com. | CH22: Call Kiewit procurement for remaining power-block MV/LV/control releases; pivot to Amazon data-center phases. | CI22: OVERVIEW: ~4.4-4.5 GW natural-gas power plant + AI data-center campus - the largest gas-powered data-center campus in the U.S. - on the former Homer City coal station; Amazon Data Services has filed a preliminary plan for a 36-building data-center campus (phased Dec 2026-2036). TECHNOLOGY & EQUIPMENT: 7x GE Vernova 7HA.02 hydrogen-capable gas turbines in combined cycle with HRSGs (15 HRSG components delivered Sep-Oct 2026); GIS switchgear building (first steel Apr 2026); possible additional simple-cycle units (unverified). SITE: BROWNFIELD - ~3,200-acre former Homer City coal generating station, Indiana County; demolition/excavation completed Jun 2026; reuses legacy transmission lines and substations. INTERCONNECTION: PJM via new GIS switchyard (existing PJM/NYISO ties); supplies campus behind-the-meter and grid. OWNERSHIP/STATUS: Homer City Redevelopment (Knighthead Capital), EQT gas supply; EPC Kiewit Power Constructors (on site Oct 2025, 1,000 workers Mar 2026, 2,000+ Oct 2026); first power late 2027/early 2028. INVESTMENT: >$10B. W&C NEEDS (combined cycle, 7 blocks): MV power cable to aux transformers, MV switchgear and large motors; 600V power & TC-ER tray cable for HRSG/ST auxiliaries and BOP; shielded I&C cable; bare copper grounding; GIS/switchyard control cable; building wire - plus data-center campus MV distribution, building wire and grounding for 36 buildings (separate long-tail opportunity). Ref: https://www.businesswire.com/news/home/20260401716982/en/Homer-City-Redevelopment-Crosses-the-First-Steel-Threshold | https://www.gevernova.com/news/press-releases/homer-city-redevelopment-kiewit-announce-country-largest-natural-gas-powered-data-center-support-ai-hpc-demand | https://marcellusdrilling.com/2026/10/homer-city-update-first-turbine-set-amazon-plan-now-under-review/ | CJ22: Total project investment: >$10B initial capital for power infrastructure and site readiness. Est. W&C value: $35,200,000 ($8/kW).
A23: Ross III | B23: Edward "Ned" | C23: Sandow Lakes Energy Company | D23: New | E23: Sales | F23: Stephan Hardt | H23: Executive Vice President | I23: End User | J23: Energy | O23: Yes | AD23: Sandow Lakes Energy Station | AE23: SL Energy Power Plant I, LLC; ERCOT/EIA 68504; Sandow Lakes CC (CRM Luminant Phase 1/2 duplicates) | AF23: Sandow Lakes Energy Company (SLEC) | AG23: EPC NTP Apr 2025; construction status unclear (sold Apr 2026 per Xebec bio) | AH23: IPP | AI23: =AL23*1000*Guide!$B$81 | AK23: 47088 | AL23: 1200 | AM23: 345 | AN23: Power Generation | AO23: Generation | AP23: New Capacity/New Build | AQ23: Load Interconnection | AR23: Generation | AS23: Natural gas generation - electrical BoP (MV/LV power, tray/control & instrumentation cable, substation) | AT23: Brownfield | AU23: Traditional | AV23: Natural Gas | AW23: Yes | AX23: Former Alcoa Sandow Lakes Ranch | AY23: Rockdale | AZ23: TX | BB23: United States | BC23: Lee / Milam | BE23: SLEC / Xebec (project reportedly sold Apr 2026 - buyer not public) | BF23: Gemma Power Systems (Argan) | BG23: Sandow Lakes Energy Company LLC | BI23: Siemens Energy (2x SGT6-9000HL GT); NEM Energy HRSGs | BL23: Electric Reliability Council of Texas (ERCOT) | BM23: Oncor (private-use, ~80 MW temporary grid export) | BP23: Yes | BQ23: Yes | BR23: Yes | BS23: No | BT23: No | BU23: Yes | BV23: No | BW23: Yes | BX23: 12.2 | BY23: Sandow Lakes Energy Station | BZ23: Nearest 345 kV line (~12.2 mi est.) | CG23: AWARD (PO) DATE BASIS: Gemma EPC Feb 2025, NTP Apr 2025, completion 2028 -> cable window Dec 2026-Dec 2027, target ~Q1 2027. RISK: Xebec bio says project sold Apr 2026 (buyer unknown) - confirm owner/schedule. Luminant link only historical (old Sandow coal plant) - merge CRM Luminant duplicates. Other contacts: Tommy Hodges (COO, SL Energy Power Plant I LLC - tommyh@slenergyco.com, TCEQ 2025 filing); Charles E. Collins IV (CEO, Gemma). | CH23: Ask Gemma Power Systems who owns the project now and current schedule; position for MV/LV/control packages Q1 2027. | CI23: OVERVIEW: 1,200 MW net natural-gas combined-cycle plant built mainly to serve private (likely data-center/industrial) customers in the 'Texas Triangle'; only ~80 MW temporary grid export in permits. TECHNOLOGY & EQUIPMENT: 2x Siemens Energy SGT6-9000HL H-class, hydrogen-adaptable gas turbines (two ~645 MW units / 1x1 blocks), NEM Energy HRSGs (Siemens Energy USA client), steam turbines. SITE: BROWNFIELD/industrial - former Alcoa Sandow aluminum smelter and Luminant Sandow coal plant area on the Sandow Lakes Ranch (~33,000 acres, ~28,800 after Apr 2026 sale), Rockdale area, Lee/Milam County. INTERCONNECTION: ERCOT; nearest 345 kV line ~12.2 miles (estimate); Oncor territory. OWNERSHIP/STATUS: SLEC (SL Energy Power Plant I LLC), Xebec affiliate - reportedly sold Apr 2026; EPC Gemma Power Systems (NTP Apr 2025); COD Dec 2028. INVESTMENT: ~$1.2B. W&C NEEDS (combined cycle): MV power cable to aux transformers, MV switchgear and large motors; 600V power & TC-ER tray cable for HRSG/ST auxiliaries and BOP; shielded I&C cable; bare copper grounding; switchyard control cable; private-customer MV feeders; possible 345 kV line. Ref: https://www.businesswire.com/news/home/20250206210188/en/Argan-Inc.s-Gemma-Power-Systems-Executes-EPC-Contract-for-a-1.2-GW-Power-Project-in-Texas | https://www.powermag.com/new-1-2-gw-natural-gas-fired-plant-announced-for-texas/ | https://interchange.puc.texas.gov/Documents/56455_62_1398423.PDF | CJ23: Total project investment: ~$1.2B. Est. W&C value: $9,600,000 ($8/kW).
A24: Davis | B24: Lee | C24: Kindle Energy | D24: New | E24: Sales | F24: Stephan Hardt | H24: CEO | I24: End User | J24: Energy | O24: Yes | AD24: Wolf Summit Energy Center | AE24: ESC Harrison County; Kindle Energy / Blackstone Energy Transition Partners | AF24: Kindle Energy (Blackstone Energy Transition Partners) | AG24: Under Construction - groundbreaking Apr 22, 2026; concrete phase mid-2026 | AH24: IPP | AI24: =AL24*1000*Guide!$B$81 | AK24: 46934 | AL24: 610 | AN24: Power Generation | AO24: Generation | AP24: New Capacity/New Build | AQ24: New Load Growth | AR24: Generation | AS24: Natural gas generation - electrical BoP (MV/LV power, tray/control & instrumentation cable, substation) | AT24: Greenfield | AU24: Traditional | AV24: Natural Gas | AW24: No | AX24: Pinnickinnick Hill area, near Clarksburg | AY24: Clarksburg (Wolf Summit) | AZ24: WV | BB24: United States | BC24: Harrison | BE24: Kindle Energy / Blackstone | BF24: Kindle Energy EPCM (four principal contractors - names not published) | BG24: Kindle Energy | BI24: GE Vernova (7HA.02 gas turbine) | BL24: PJM Interconnection (PJM) | BM24: Offtake: Old Dominion Electric Cooperative (ODEC) | BP24: Yes | BQ24: Yes | BR24: Yes | BS24: No | BT24: No | BU24: No | BV24: No | BW24: Yes | CG24: AWARD (PO) DATE BASIS: FID Nov 2025, groundbreaking Apr 2026, concrete pours mid-2026, COD 2028 -> cable window open now, target Dec 2026-Mar 2027 (if COD 2027 per ENR, act immediately). Delivered as Kindle EPCM with four principal contractors (names not published) - identify the electrical contractor. CRM 579 MW not supported; sources say ~600-625 MW (610 MW used). Project contact: info@wolf-summit.com, (304) 576-8717. Other: Chris Cosby (CEO, ODEC); Bilal Khan (SMD, Blackstone). | CH24: Ask Kindle (EPCM) which principal contractor holds electrical; use Kindle Energy / project line (304) 576-8717 / WV Building Trades; position MV, control & I&C cable before bulk electrical buy. | CI24: OVERVIEW: ~600 MW natural-gas combined-cycle plant - West Virginia's first gas power plant - backed by $1.2B from Blackstone Energy Transition Partners, developed/operated by Kindle Energy, fully contracted to Old Dominion Electric Cooperative; ~500 construction jobs. TECHNOLOGY & EQUIPMENT: GE Vernova 7HA.02 gas turbine in combined cycle (likely 1x1 with HRSG and steam turbine - inferred); GE Vernova Financial Services also financing. SITE: Pinnickinnick Hill area near Clarksburg/Wolf Summit, Harrison County (PILOT/lease Jan 2025); acreage not published. INTERCONNECTION: PJM grid sale to ODEC; substation/voltage not published. OWNERSHIP/STATUS: FID Nov 2025; groundbreaking Apr 22, 2026; site prep and roadwork Jun 2026; COD 2028. Kindle EPCM with four principal contractors (not published). INVESTMENT: $1.2B. W&C NEEDS (combined cycle): MV power cable to aux transformers, MV switchgear and large motors; 600V power & TC-ER tray cable for HRSG/ST auxiliaries and BOP; shielded I&C cable; bare copper grounding; switchyard control cable; building wire. Ref: https://www.businesswire.com/news/home/20260422186042/en/Kindle-Energy-Breaks-Ground-on-Blackstone-Backed-$1.2-Billion-Natural-Gas-Power-Generation-Facility-in-West-Virginia | https://wolf-summit.com/ | https://www.powermag.com/blackstone-investing-1-2-billion-for-600-mw-gas-fired-plant-in-west-virginia/ | CJ24: Total project investment: $1.2B (Blackstone). Est. W&C value: $4,880,000 ($8/kW).
A25: Gaudette | B25: Robert J. | C25: NRG Energy | D25: New | E25: Sales | F25: Stephan Hardt | H25: EVP & President, Business & Wholesale Operations | I25: End User | J25: Energy | O25: Yes | AD25: Cedar Bayou Unit 5 | AE25: Cedar Bayou 5; NRG Cedar Bayou Generating Station expansion | AF25: NRG Energy | AG25: Under Construction - on track (NRG Q1 2026); TEF loan closed | AH25: IPP | AI25: =AL25*1000*Guide!$B$81 | AK25: 46965 | AL25: 689 | AN25: Power Generation | AO25: Generation | AP25: New Capacity/New Build | AQ25: New Load Growth | AR25: Generation | AS25: Natural gas generation - electrical BoP (MV/LV power, tray/control & instrumentation cable, substation) | AT25: Brownfield | AU25: Traditional | AV25: Natural Gas | AW25: No | AX25: Existing Cedar Bayou Generating Station | AY25: Baytown | AZ25: TX | BB25: United States | BC25: Chambers | BE25: NRG Energy | BG25: NRG Energy | BI25: Mitsubishi Power (M501JAC gas turbine, per TCEQ permit) | BL25: Electric Reliability Council of Texas (ERCOT) | BM25: ERCOT (CenterPoint area - unconfirmed) | BP25: Yes | BQ25: Yes | BR25: Yes | BS25: No | BT25: No | BU25: No | BV25: No | BW25: Yes | CG25: AWARD (PO) DATE BASIS: TEF loan closed Q3 2025, under construction, COD mid-2028 (NRG) -> cable window Jul 2026-Jul 2027, target Nov 2026-Feb 2027. EPC not public (NRG GE Vernova/Kiewit venture is for 7HA units, not this Mitsubishi unit). CRM correction: 689 MW (NRG) vs 721 MW (state), Mitsubishi not GE, COD mid-2028 not 2029. Owner contact on 2026 TDLR project registration: Dudley D. Zahn (NRG / Cedar Bayou 5 LLC, 713-537-3290; email historical). | CH25: Engage NRG construction/procurement to identify Cedar Bayou 5 EPC/BOP electrical contractor now. | CI25: OVERVIEW: 689 MW (NRG; state cites 721 MW) natural-gas combined-cycle unit added at NRG's existing Cedar Bayou Generating Station, one of NRG's largest Texas assets, backed by a Texas Energy Fund loan. TECHNOLOGY & EQUIPMENT: 1x1 combined cycle - Mitsubishi Power M501JAC J-class gas turbine (TCEQ permit), HRSG and steam turbine (OEMs not published). SITE: BROWNFIELD - existing operating Cedar Bayou plant on Galveston Bay, Baytown, Chambers County (existing gas, water and transmission). INTERCONNECTION: ERCOT grid unit; voltage not published. OWNERSHIP/STATUS: NRG Energy; TEF loan announced Sep 26, 2025; under construction; COD mid/summer 2028. INVESTMENT: $936M. W&C NEEDS (combined cycle): MV power cable to aux transformers, MV switchgear and large motors; 600V power & TC-ER tray cable for HRSG/ST auxiliaries and BOP; shielded I&C cable; bare copper grounding; switchyard control cable. Ref: https://gov.texas.gov/news/post/governor-abbott-announces-texas-energy-fund-loan-to-721-mw-natural-gas-facility-in-southeast-texas | https://www.utilitydive.com/news/nrg-close-to-completing-415-mw-gas-plant-backed-by-texas-energy-fund/819587/ | https://www.texastribune.org/2025/09/26/texas-energy-fund-loan-nrg-baytown | CJ25: Total project investment: $936M ($562M Texas Energy Fund loan, 3%, 20 yr). Est. W&C value: $5,512,000 ($8/kW).
A26: Podurgiel | B26: Peter | C26: CPV Group | D26: New | E26: Sales | F26: Stephan Hardt | H26: President, Low Carbon Generation | I26: End User | J26: Energy | O26: Yes | AD26: CPV Basin Ranch Energy Center | AE26: CPV Basin Ranch Holdings LLC; ERCOT 25INR0008 (BASRANCH) | AF26: CPV Group (OPC Energy / Kenon) | AG26: Under Construction - Gemma full NTP Oct 30, 2025; groundbreaking Nov 20, 2025 | AH26: IPP | AI26: =AL26*1000*Guide!$B$81 | AK26: 47088 | AL26: 1350 | AM26: 345 | AN26: Power Generation | AO26: Generation | AP26: New Capacity/New Build | AQ26: New Load Growth | AR26: Generation | AS26: Natural gas generation - electrical BoP (MV/LV power, tray/control & instrumentation cable, substation) | AT26: Greenfield | AU26: Traditional | AV26: Natural Gas | AW26: No | AX26: Near Barstow, Ward County | AY26: Barstow | AZ26: TX | BB26: United States | BC26: Ward | BE26: CPV Basin Ranch Holdings LLC (CPV 100%) | BF26: Gemma Power Systems (Argan); engineer POWER Engineers | BG26: CPV Group | BI26: GE Vernova (2x 7HA.03 gas turbines) | BL26: Electric Reliability Council of Texas (ERCOT) | BM26: Oncor (345 kV switchyard) | BP26: Yes | BQ26: Yes | BR26: Yes | BS26: No | BT26: No | BU26: Yes | BV26: No | BW26: Yes | BY26: CPV Basin Ranch Energy Center | BZ26: Oncor 345 kV switchyard (tap Riverton-Sand Lake 345 kV) | CG26: AWARD (PO) DATE BASIS: full NTP Oct 2025, construction since Nov 2025, COD Dec 2028 (ERCOT; CPV says 2029) -> target Q1 2027; early packages may already be placed. CRM correction: utility is Oncor (not AEP Texas). Other contacts: Sherman Knight (CEO, CPV); Charles E. Collins IV (CEO, Gemma); David Watson (Argan company contact, 301-315-0027). | CH26: Get in front of Gemma procurement now for MV/LV power, control & I&C packages before Q1 2027. | CI26: OVERVIEW: 1,350 MW natural-gas combined-cycle plant in the Permian Basin, CPV's first Texas project, backed by a ~$1.1B Texas Energy Fund loan; CPV bought the remaining 30% in Feb 2026 (100% owner). TECHNOLOGY & EQUIPMENT: two 1x1 combined-cycle blocks with GE Vernova 7HA.03 gas turbines, HRSGs and steam turbines; permitted carbon-capture option for later phases (CPV Basin Ranch Capture LLC). SITE: GREENFIELD - near Barstow, Ward County (acreage not published). INTERCONNECTION: 345 kV into an Oncor switchyard tapping the Riverton-Sand Lake 345 kV line; ERCOT. OWNERSHIP/STATUS: CPV Group (OPC Energy/Kenon); EPC Gemma Power Systems, detailed engineering POWER Engineers; groundbreaking Nov 20, 2025; COD Dec 2028-2029. INVESTMENT: ~$2B. W&C NEEDS (combined cycle): MV power cable to aux transformers, MV switchgear and large motors; 600V power & TC-ER tray cable for HRSG/ST auxiliaries and BOP; shielded I&C cable; bare copper grounding; 345 kV switchyard control cable; future carbon-capture plant cabling. Ref: https://cpv.com/2025/11/20/cpv-basin-ranch-energy-center-breaks-ground-in-ward-county-texas/ | https://www.businesswire.com/news/home/20251030500209/en/Argan-Inc.s-Gemma-Power-Systems-Receives-Full-Notice-to-Proceed-on-EPC-Contract-for-1350-MW-Combined-Cycle-Power-Plant-in-Texas | https://cpv.com/our-fleet/cpv-basin-ranch-energy-center/ | CJ26: Total project investment: ~$2B (~$1.1B Texas Energy Fund loan, 3%). Est. W&C value: $10,800,000 ($8/kW).
A27: Podurgiel | B27: Peter | C27: CPV Group | D27: New | E27: Sales | F27: Stephan Hardt | H27: President (per Aug 2026 release) | I27: End User | J27: Energy | O27: Yes | AD27: CPV Shay Energy Center | AE27: CPV Shay, LLC; CPV Shay Clean Energy Center | AF27: CPV Group (OPC Energy / Kenon) | AG27: Development - WV PSC siting Apr 2024; air permit applied Jan 2026; EQT gas deal Aug 2026 | AH27: IPP | AI27: =AL27*1000*Guide!$B$81 | AK27: 48213 | AL27: 2100 | AM27: 500 | AN27: Power Generation | AO27: Generation | AP27: New Capacity/New Build | AQ27: New Load Growth | AR27: Generation | AS27: Natural gas generation - electrical BoP (MV/LV power, tray/control & instrumentation cable, substation) | AT27: Greenfield | AU27: Traditional | AV27: Natural Gas | AW27: No | AX27: WV Route 18, ~5 mi SE of West Union | AY27: West Union (Blandville) | AZ27: WV | BB27: United States | BC27: Doddridge | BE27: CPV Shay, LLC | BG27: CPV Group | BI27: GE Vernova (3x 7HA.03 gas turbines) | BL27: PJM Interconnection (PJM) | BM27: Monongahela Power (FirstEnergy) | BP27: Yes | BQ27: Yes | BR27: Yes | BS27: No | BT27: No | BU27: Yes | BV27: No | BW27: Yes | BX27: 9 | BY27: CPV Shay Energy Center | BZ27: Mon Power Flint Run 500 kV Substation | CG27: AWARD (PO) DATE BASIS: construction start est. Q1 2027, COD est. 2031 (CPV fact sheet Mar 2026) -> award window ~2029-2030. Could accelerate if selected in PJM Reliability Backstop procurement (auction postponed after FERC order Sep 29, 2026). EPC not yet named. CRM COD 12/31/2029 updated to 2031. Other: Toby Rice (CEO, EQT). | CH27: Track WVDEP air permit and EPC award (likely 2027); spec in early with engineer. | CI27: OVERVIEW: ~2,060-2,100 MW natural-gas combined-cycle plant with amine-based carbon capture capability (90-95% capture target), one of the largest gas plants planned in PJM; 10-yr EQT gas supply (>100 BCF/yr) signed Aug 2026. TECHNOLOGY & EQUIPMENT: three 1x1 combined-cycle blocks with GE Vernova 7HA.03 gas turbines (~687 MW each), HRSGs and steam turbines; post-combustion amine carbon capture plant (can run with or without capture). SITE: GREENFIELD - 54-acre footprint within a 230-acre parcel along WV Route 18, ~5 miles SE of West Union, Doddridge County. INTERCONNECTION: new ~9-mile 500 kV line to Mon Power's Flint Run 500 kV substation; PJM. OWNERSHIP/STATUS: CPV Shay LLC; WV PSC siting certificate Apr 2024; WVDEP air permit application Jan 2026; construction start est. 2027; COD est. 2031. INVESTMENT: ~$3-3.3B. W&C NEEDS (combined cycle x3 + carbon capture): MV power cable to aux transformers, MV switchgear and large motors (incl. capture-plant compressors/blowers/pumps); 600V power & TC-ER tray cable; shielded I&C cable; bare copper grounding; 500 kV switchyard control cable; 9-mile 500 kV transmission conductor. Ref: https://cpv.com/our-fleet/cpv-shay-energy-center/ | https://cpv.com/2026/08/12/cpv-secures-10-year-gas-netback-with-eqt-to-supply-2-gw-cpv-shay-energy-center/ | https://cpv.com/wp-content/uploads/2026/03/CPV-Shay-Energy-Center-Project-Fact-Sheet-March-2026-1.pdf | CJ27: Total project investment: ~$3B-$3.3B. Est. W&C value: $16,800,000 ($8/kW).
A28: TBD | C28: CPV Group | D28: New | E28: Sales | F28: Stephan Hardt | H28: Project development contact | I28: End User | J28: Energy | O28: Yes | AD28: CPV Clean Energy Future - Oregon (Oregon Energy Center) | AE28: CPV Oregon Energy Center; Clean Energy Future - Oregon; OPSB 17-0530-EL-BGN | AF28: CPV Group (CPV Oregon Holdings) | AG28: Stalled / at risk - PJM queue reportedly withdrawn (Aurora, Feb 2026); OPSB certificate may have lapsed | AH28: IPP | AI28: =AL28*1000*Guide!$B$81 | AK28: 48213 | AL28: 1475 | AM28: 345 | AN28: Power Generation | AO28: Generation | AP28: New Capacity/New Build | AQ28: New Load Growth | AR28: Generation | AS28: Natural gas generation - electrical BoP (MV/LV power, tray/control & instrumentation cable, substation) | AT28: Brownfield | AU28: Traditional | AV28: Natural Gas | AW28: No | AX28: North of Parkway Rd between N. Wynn and N. Lallendorf | AY28: Oregon | AZ28: OH | BB28: United States | BC28: Lucas | BE28: CPV Oregon Holdings | BG28: CPV Group | BI28: Not found (original design: 2 CTs in combined cycle) | BL28: PJM Interconnection (PJM) | BM28: FirstEnergy / Toledo Edison area (unverified) | BP28: Yes | BQ28: Yes | BR28: Yes | BS28: No | BT28: No | BU28: No | BV28: No | BW28: Yes | CG28: ON HOLD: OPSB certificate (955 MW, 2017) extended to ~mid-2026; selected for PJM RRI May 2025 and redesigned to 1,475 MW / 2031 COD; Aurora (Feb 2026) reports queue request withdrawn after $878/kW cost estimate (single source). Neighboring Oregon Clean Energy Center (870 MW) now owned by I&M/AEP (Mar 2026) - not CPV. ALTERNATIVE CPV LEAD: CPV Walker Energy Center, Fayette County OH (1,450-1,465 MW CC, ~150 acres, construction Q2 2028, COD Q4 2031, AES Ohio 345 kV). Other contact: Joel Mazur (City Administrator, Oregon OH). | CH28: Confirm with CPV whether Oregon is alive; open new lead for CPV Walker Energy Center (Fayette Co., OH). | CI28: OVERVIEW: planned ~1,475 MW natural-gas combined-cycle plant (redesigned from the 955 MW certificate) by CPV, selected for PJM's Reliability Resource Initiative (May 2025) with a 2031 target - currently stalled (queue reportedly withdrawn). TECHNOLOGY & EQUIPMENT: combined cycle; original design two combustion turbines + HRSGs + steam turbine; OEM for redesign not published. SITE: BROWNFIELD-ADJACENT industrial parcel next to the existing 870 MW Oregon Clean Energy Center (now I&M/AEP), north of Parkway Rd, Oregon, Lucas County. INTERCONNECTION: 138 kV and 345 kV lines (955 MW case); PJM. OWNERSHIP/STATUS: CPV Oregon Holdings (transfer Jan 2024); OPSB extensions Dec 2023 and May 2025; status uncertain. INVESTMENT: not published for redesign. W&C NEEDS (combined cycle, if revived): MV power cable, 600V power & TC-ER tray cable, shielded I&C cable, grounding, switchyard control cable. Ref: https://opsb.ohio.gov/news/opsb-extends-certificate-for-lucas-county-natural-gas-fired-power-plant | https://www.presspublications.com/stories/natural-gas-power-plant-oregon-ohio-reliability-resource-initiative-pjm,58407 | https://www.recordherald.com/2026/05/04/cpv-walker-energy-center-begins-state-review-for-new-power-plant/ | CJ28: Total project investment: Not found for 1,475 MW redesign (original 955 MW ~$900M). Est. W&C value: $11,800,000 ($8/kW).
A29: Kinnamon | B29: John | C29: EmberClear Corp. | D29: New | E29: Sales | F29: Stephan Hardt | H29: VP, LLEC Project Leader | I29: End User | J29: Energy | O29: Yes | AD29: Lincoln Land Energy Center (LLEC) | AE29: Lincoln Land Energy Center LLC; MISO 62022_GEN1/GEN2 | AF29: EmberClear Corp. | AG29: Dormant / at risk - construction not started; IEPA permit expires Jan 1, 2027; data-center offtaker withdrew Aug 2026 | AH29: IPP | AI29: =AL29*1000*Guide!$B$81 | AK29: 47635 | AL29: 1190 | AM29: 345 | AN29: Power Generation | AO29: Generation | AP29: New Capacity/New Build | AQ29: New Load Growth | AR29: Generation | AS29: Natural gas generation - electrical BoP (MV/LV power, tray/control & instrumentation cable, substation) | AT29: Greenfield | AU29: Traditional | AV29: Natural Gas | AW29: No | AX29: ~0.5 mile south of the Village of Pawnee | AY29: Pawnee | AZ29: IL | BB29: United States | BC29: Sangamon | BE29: EmberClear (Lincoln Land Energy Center LLC) | BF29: Bechtel (partner via BDC Power Holdings - contract not confirmed) | BG29: EmberClear Corp. (with Kindle Energy, Siemens Energy, Bechtel) | BI29: Siemens Energy (gas turbines) | BL29: Midcontinent Independent System Operator (MISO) | BM29: Ameren Illinois (Illinois Rivers 345 kV substation) | BP29: Yes | BQ29: Yes | BR29: Yes | BS29: No | BT29: No | BU29: No | BV29: No | BW29: Yes | CG29: ON HOLD: IEPA construction permit (2022, extended twice) expires Jan 1, 2027; construction not begun; EmberClear/Kindle not responding to press; Eagle Rock Partners abandoned its Christian County data center (offtaker) Aug 12, 2026. CRM correction: RTO is MISO Zone 4 (Ameren), not PJM; EIA COD Jun 2030. Re-check after Jan 1, 2027. | CH29: Re-check IEPA permit status after Jan 1, 2027; move to dormant if not extended; watch for Kindle/Blackstone revival. | CI29: OVERVIEW: ~1,190 MW (EIA/MISO 1,277 MW) natural-gas combined-cycle plant near Pawnee, IL, developed by EmberClear with Siemens Energy, Siemens Financial Services, Bechtel (BDC Power Holdings) and Kindle Energy; designed for 30% hydrogen blend with path to 100%. Linked data-center offtaker (Eagle Rock Meridian Technology Park, ~1 GW) withdrew Aug 2026. TECHNOLOGY & EQUIPMENT: two combined-cycle blocks (2x ~560-638 MW) with Siemens Energy gas turbines, HRSGs and steam turbines. SITE: GREENFIELD - 160 acres, half a mile south of the Village of Pawnee, Sangamon County. INTERCONNECTION: adjacent to Ameren's Illinois Rivers 345 kV substation; MISO Zone 4 (interconnection agreement 2023). OWNERSHIP/STATUS: EmberClear (Lincoln Land Energy Center LLC); IEPA permit expires Jan 1, 2027; EIA COD Jun 2030. INVESTMENT: ~$1.4-1.5B. W&C NEEDS (combined cycle, if revived): MV power cable, 600V power & TC-ER tray cable, shielded I&C cable, grounding, 345 kV switchyard control cable. Ref: https://emberclear.com/lincoln-land-2/ | https://www.illinoistimes.com/news/data-center-development-linked-to-power-plant-construction/ | https://www.springfieldbusinessjournal.com/news/data-center-developer-abandons-plans-for-christian-county/ | CJ29: Total project investment: ~$1.4B-$1.5B+. Est. W&C value: $9,520,000 ($8/kW).
A30: Droog | B30: Daniel | C30: Chevron | D30: New | E30: Sales | F30: Stephan Hardt | H30: VP, Power Solutions | I30: End User | J30: Energy | O30: Yes | AD30: Project Kilby (Chevron West Texas Power) | AE30: Kilby Power Plant; Energy Forge One LLC; Kilby Chevron West Texas Natural Gas (CRM); TCEQ 181895/PSDTX1684 | AF30: Chevron (Energy Forge One LLC) / Joulent (Engine No. 1, National Grid Ventures) | AG30: Pre-FID - Microsoft 20-yr PPA Jun 22, 2026; FID targeted end-2026; TCEQ air permit pending | AH30: IPP | AI30: =AL30*1000*Guide!$B$81 | AK30: 46934 | AL30: 2670 | AN30: Power Generation | AO30: Generation | AP30: New Capacity/New Build | AQ30: Load Interconnection | AR30: Generation | AS30: Natural gas generation - electrical BoP (MV/LV power, tray/control & instrumentation cable, substation) | AT30: Greenfield | AU30: Traditional | AV30: Natural Gas | AW30: Yes | AX30: SE of Pecos off US-285 / FM 112 (~2 mi W) | AY30: Pecos (Verhalen area) | AZ30: TX | BA30: 79780 | BB30: United States | BC30: Reeves | BE30: Energy Forge One LLC (Chevron) | BF30: Bechtel (Kilby job 26776 - procurement/early works published; full NTP to confirm) | BG30: Energy Forge One LLC - Chevron / Joulent 50:50 JV (Joulent: Engine No. 1; National Grid Ventures 35%) | BI30: GE Vernova 7HA turbines (7 reserved) + Solar Turbines Titan 350/130 (Caterpillar) | BL30: None - behind the meter (co-located, ERCOT region) | BM30: None - dedicated to Microsoft | BP30: Yes | BQ30: Yes | BR30: Yes | BS30: No | BT30: No | BU30: No | BV30: No | BW30: Yes | CG30: AWARD (PO) DATE BASIS: PPA signed Jun 2026, FID targeted end-2026, first power 2028 with phased ramp to ~2.67 GW (~2029-30) -> award window Jun 2026-Jun 2027, target ~Q1 2027 (early-power Titan 130 units drive first packages). CRM COD 6/30/2027 corrected to 2028. Bechtel May 2026 Project Opportunity Report lists Kilby job 26776 with procurement (Birju Vasani, bvasani@bechtel.com) and subcontracts (Mark Bingaman, mabingam@bechtel.com, 713-235-1662) prequalification contacts; full NTP not confirmed. Full capacity 2031 per kilby.com. Other contacts: Jeff Gustavson (President, Chevron New Energies); Chris James (Founder & CEO, Engine No. 1 / Joulent). | CH30: Prequalify with Bechtel now: Birju Vasani (procurement) and Mark Bingaman (subcontracts) for Kilby job 26776; get specified before FID (Dec 2026); engage Chevron Power Solutions (Daniel Droog). | CI30: OVERVIEW: ~2.67 GW (permit ~2.87 GW, possible scale to 5 GW) off-grid natural-gas power plant dedicated to Microsoft's up-to-2 GW Pecos AI data-center campus under a 20-year PPA (Jun 22, 2026); developed by Chevron (Energy Forge One) with Engine No. 1's Joulent and National Grid Ventures ($1.75B for 35% of Joulent). TECHNOLOGY & EQUIPMENT: ~46 gas turbines - GE Vernova 7HA (7 reserved; permit analysis 5x 7HA.02) plus Solar Turbines Titan 350 (12) and Titan 130 (29, added Dec 2025 for early power); SCR and oxidation catalysts; combined/simple-cycle split not confirmed. SITE: GREENFIELD - Reeves County, SE of Pecos near Verhalen (Pecos TX 79780), off US-285 / FM 112; Microsoft campus ~7,000 acres (tracker, unverified). INTERCONNECTION: behind-the-meter, co-located with Microsoft campus (ERCOT region, no grid export disclosed). OWNERSHIP/STATUS: Energy Forge One LLC (Chevron/Joulent 50:50); EPC Bechtel (job 26776, procurement/early works); pre-FID; TCEQ air permit draft Apr 2026, public meeting Jun 10, 2026, pending; FID end-2026; first power 2028. INVESTMENT: ~$7-9B (analyst estimates). W&C NEEDS (behind-the-meter / on-site generation): MV power cable (5-35 kV) collecting many turbine/engine units to on-site switching and plant substations and feeders to the data-center campus; 600V power & TC-ER tray cable for unit packages, MCCs, gas conditioning/compression, BESS and cooling; shielded instrumentation & control cable (unit controls, microgrid/SCADA); extensive bare copper grounding; switchgear/substation control cable; building wire for control and admin buildings. High unit count = high cable density per MW. Very large scope: 46 turbine packages plus data-center campus feeders. Ref: https://www.chevron.com/newsroom/2026/q2/chevron-signs-20-year-power-agreement-with-microsoft-for-west-texas-data-center | https://www.tceq.texas.gov/downloads/permitting/air/bilingual/pending-permit-notices/181895-pls-english.pdf | https://blogs.microsoft.com/blog/2026/06/22/powering-the-next-wave-of-ai-expanding-capacity-with-our-new-datacenter-in-pecos/ | CJ30: Total project investment: Not disclosed (~$7B Bloomberg to ~$9B TD Securities estimates). Est. W&C value: $21,360,000 ($8/kW).
A31: Cox | B31: Chris | C31: The Frontier Group of Companies | D31: New | E31: Sales | F31: Stephan Hardt | H31: VP, Power Generation | I31: End User | J31: Energy | O31: Yes | AD31: Shippingport Power Station Phase II | AE31: Shippingport Power Station, LLC; former Bruce Mansfield Power Plant conversion; Shippingport Industrial Park | AF31: The Frontier Group of Companies (FGC) | AG31: Development / permitting - DEP fuel-yard stormwater permit comment to Nov 23, 2026; PJM approval expected mid-2028 | AH31: IPP | AI31: =AL31*1000*Guide!$B$81 | AK31: 47208 | AL31: 2550 | AM31: 345 | AN31: Power Generation | AO31: Generation | AP31: New Capacity/New Build | AQ31: Load Interconnection | AR31: Generation | AS31: Natural gas generation - electrical BoP (MV/LV power, tray/control & instrumentation cable, substation) | AT31: Brownfield | AU31: Traditional | AV31: Natural Gas | AW31: Yes | AX31: Shippingport Industrial Park (former Bruce Mansfield plant) | AY31: Shippingport | AZ31: PA | BB31: United States | BC31: Beaver | BE31: Shippingport Power Station, LLC (Frontier) | BF31: Frontier Group (self-performs); Wood - owner's engineer; construction package contractors to confirm | BG31: The Frontier Group of Companies | BI31: Existing Foster Wheeler boilers / 3x GE steam turbine-generators (refurbished); new gas turbines (OEM not disclosed) | BL31: PJM Interconnection (PJM) | BM31: Penn Power / FirstEnergy (Bruce Mansfield 345 kV substation) | BP31: Yes | BQ31: Yes | BR31: Yes | BS31: No | BT31: No | BU31: No | BV31: No | BW31: Yes | CG31: AWARD (PO) DATE BASIS: Frontier targets PJM approval mid-2028 and units online early 2029 with ~3-year construction -> award window Mar 2027-Mar 2028, target ~Q2 2027. CRM COD 12/31/2030 updated to early 2029. Capacity conflicts: 2,550 MW export / 2.7 GW conversion + 900 MW Phase I = 3.6 GW. Aligned Data Centers broke ground on 2 GW Project Phoenix (~$10B) Sep 10, 2026 next door. Other contacts: David Franjoine (Founder & CEO); Robert Zuchlewski (COO); Anthony Basil (Project Manager) and Peter Violante (Dir. Logistics & BD) - Shippingport assignment not confirmed. Owner's engineer: Wood. | CH31: Meet Chris Cox (Frontier) on Phase II steam-unit refurbishment and 34.5 kV substation cable packages. | CI31: OVERVIEW: conversion of the former 2.5-2.7 GW Bruce Mansfield coal plant (operated 1976-2019) into a natural-gas power station; Phase I adds ~900 MW new simple-cycle gas turbines + switchyard, Phase II (this record) converts the coal units (~2.7 GW) - up to ~3.6 GW total available to the park; EQT gas supply ~800 MMcf/d via new 7.2-mile National Fuel lateral. TECHNOLOGY & EQUIPMENT: refurbish 3x existing GE steam turbine-generators (~850 MW each) re-powered with new gas turbines (repowering), new cooling towers, transformers and switchgear, on-site gas receiving station and 34.5 kV substation; coal handling demolished. SITE: BROWNFIELD - former Bruce Mansfield coal plant in the 660-acre Shippingport Industrial Park, Shippingport Borough, Beaver County; 14.5-acre gas fuel yard. Aligned Data Centers' 2 GW Project Phoenix campus under construction on site. INTERCONNECTION: PJM Cycle 01 (existing Bruce Mansfield 345 kV substation, Penn Power/FirstEnergy) plus behind-the-meter supply to the park. OWNERSHIP/STATUS: Frontier Group (self-performs engineering and construction; Wood owner's engineer); permitting underway; PJM approval mid-2028; units online early 2029; >1,500 construction workers. INVESTMENT: >$1.8B. W&C NEEDS (repowered steam units + new GTs): MV power cable for new GT/aux transformers, cooling-tower fans and pumps, 34.5 kV substation feeders; 600V power & TC-ER tray cable; shielded I&C cable for new controls/DCS; grounding; switchyard control cable; data-center park MV distribution. Ref: https://frontier-companies.com/shippingport-power-station-featured-in-energy-oil-gas-magazine/ | https://www.businesswire.com/news/home/20250715103342/en/The-Frontier-Group-of-Companies-to-Transform-Bruce-Mansfield-Power-Plant-into-State-of-the-Art-Natural-Gas-Power-Plant-Supporting-Americas-Energy-Goals-and-Pennsylvanias-Economic-Growth | https://aligneddc.com/press-release/project-phoenix-data-center-shippingport-pa/ | CJ31: Total project investment: >$1.8B (Frontier Oct 2026; other Frontier pages cite $1.6B+ to ~$3.2B for full conversion). Est. W&C value: $20,400,000 ($8/kW).
A32: Siffin | B32: Mark | C32: Maefield Development / VPN 4420 LLC | D32: New | E32: Sales | F32: Stephan Hardt | H32: CEO / project business contact | I32: End User | J32: Energy | K32: +1 347-703-0093 | M32: siffin@maefield.com | O32: Yes | AD32: VPN 4420 Natural Gas Generation Component | AE32: VPN 4420 LLC; Texas Comptroller Chapter 313 Application #1993 (Pecos-Barstow-Toyah ISD) | AF32: VPN 4420 LLC | AG32: Dormant / speculative - 2022 Chapter 313 agreement; no investment or permits reported | AH32: IPP | AI32: =AL32*1000*Guide!$B$81 | AK32: 47848 | AL32: 1540 | AN32: Power Generation | AO32: Generation | AP32: New Capacity/New Build | AQ32: Load Interconnection | AR32: Generation | AS32: Natural gas generation - electrical BoP (MV/LV power, tray/control & instrumentation cable, substation) | AT32: Greenfield | AU32: Traditional | AV32: Natural Gas | AW32: Yes | AX32: Pecos-Barstow-Toyah ISD area | AY32: Pecos | AZ32: TX | BB32: United States | BC32: Reeves | BE32: VPN 4420 LLC | BG32: VPN 4420 LLC / Maefield Development (link per Chapter 313 filings) | BL32: None - on-site trigeneration (behind the meter) | BM32: None - on-site | BP32: Yes | BQ32: Yes | BR32: Yes | BS32: No | BT32: No | BU32: No | BV32: No | BW32: Yes | CG32: LOW PROBABILITY: Chapter 313 agreement executed Dec 19, 2022 ($1B, 10 jobs); 2023 report showed no jobs/investment; no TCEQ air permit found. Maefield link established via Chapter 313 filings (2024 compliance report posted 2026 lists Mark Siffin). Tentative award 6/30/2029. Same county has stronger leads: Project Kilby (Chevron/Microsoft), Prometheus Hyperscale + Istmo (1.5-2.5 GW, Aug 2026), LandBridge/NRG (1.1 GW), LandBridge/PowerBridge (2 GW). | CH32: Downgrade probability; watch for TCEQ air filings under VPN 4420; prioritize Kilby/Prometheus in Reeves County. | CI32: OVERVIEW: proposed Phase 1 technology campus (~6 million sq ft of data centers and semiconductor manufacturing) in Reeves County powered by up to three on-site natural-gas trigeneration plants (power, heating, cooling) totaling ~1.54 GW with CO2 capture equipment. TECHNOLOGY & EQUIPMENT: on-site gas trigeneration plants with CO2 capture (OEMs not published). SITE: GREENFIELD - Pecos-Barstow-Toyah ISD area, Reeves County (acreage not published). INTERCONNECTION: on-site / behind the meter. OWNERSHIP/STATUS: VPN 4420 LLC / Maefield Development (Mark Siffin); Chapter 313 agreement Dec 2022; no reported investment or permits as of latest filings - likely stalled. INVESTMENT: $1B qualified investment (313). W&C NEEDS (behind-the-meter / on-site generation): MV power cable (5-35 kV) collecting many turbine/engine units to on-site switching and plant substations and feeders to the data-center campus; 600V power & TC-ER tray cable for unit packages, MCCs, gas conditioning/compression, BESS and cooling; shielded instrumentation & control cable (unit controls, microgrid/SCADA); extensive bare copper grounding; switchgear/substation control cable; building wire for control and admin buildings. High unit count = high cable density per MW. Ref: https://comptroller.texas.gov/economy/development/prop-tax/ch313/agreement-docs-details.php?id=1993 | https://assets.comptroller.texas.gov/ch313/1993/1993-pecos-vpn-agmt.pdf | CJ32: Total project investment: $1B qualified investment (Chapter 313 agreement, Phase 1). Est. W&C value: $12,320,000 ($8/kW).

Sheet Project Products
A1: Stephan Hardt | Power Generation
A2: Project products
A3: Use one row per product. Repeat the Project Name to select several products for the same project.
A4: Enter the project on Projects first. Product labels ending in ... were truncated in the recording.
A6: Project Name | B6: Product | C6: Notes
A7: Forest Junction Energy Center | B7: G00 - MEDIUM VOLTAGE POWER... | C7: MV power cable: 42% of W&C = $4,042,080
A8: Forest Junction Energy Center | B8: J10 - INDUSTRIAL ARMORED CAB... | C8: Tray cable (TC) - control & instrumentation: 43% of W&C = $4,138,320
A9: Forest Junction Energy Center | B9: H00 - INDUSTRIAL SINGLE COND... | C9: PV / LV single-conductor power: 10% of W&C = $962,400
A10: Forest Junction Energy Center | B10: M20 - SUBSTATION | C10: Other - substation / switchyard: 5% of W&C = $481,200
A11: Forest Junction Energy Center | B11: P10 - BARE AL | C11: Bare overhead conductor - gen-tie (not in $8/kW split)
A12: Orange County Advanced Power Station (OCAPS) | B12: G00 - MEDIUM VOLTAGE POWER... | C12: MV power cable: 42% of W&C = $4,082,400
A13: Orange County Advanced Power Station (OCAPS) | B13: J10 - INDUSTRIAL ARMORED CAB... | C13: Tray cable (TC) - control & instrumentation: 43% of W&C = $4,179,600
A14: Orange County Advanced Power Station (OCAPS) | B14: H00 - INDUSTRIAL SINGLE COND... | C14: PV / LV single-conductor power: 10% of W&C = $972,000
A15: Orange County Advanced Power Station (OCAPS) | B15: M20 - SUBSTATION | C15: Other - substation / switchyard: 5% of W&C = $486,000
A16: Vast Sands Power I (Vistra Permian Basin expansion) | B16: G00 - MEDIUM VOLTAGE POWER... | C16: MV power cable: 42% of W&C = $1,478,400
A17: Vast Sands Power I (Vistra Permian Basin expansion) | B17: J10 - INDUSTRIAL ARMORED CAB... | C17: Tray cable (TC) - control & instrumentation: 43% of W&C = $1,513,600
... A117: VPN 4420 Natural Gas Generation Component | B117: M20 - SUBSTATION | C117: Other - substation / switchyard: 5% of W&C = $616,000

Sheet Dropdowns
A1: Stephan Hardt | Power Generation
A2: Dropdown options
A3: Edit values from row 7 downward. Keep each list contiguous; up to 100 choices per column.
A4: Only visible choices are preloaded. Partial or unseen lists allow other values to be typed.
A5: Project Stage | B5: Lead Status | C5: End User Type | D5: Main Decision Influencer | E5: Market | F5: Segment | G5: Application | H5: Demand Driver | I5: OEM Category | J5: Brownfield/Greenfield | K5: Power Needs | L5: Primary Energy Source | M5: AI Facility | N5: Checkbox fields | O5: Occupation | P5: Industry | Q5: Lead Source | R5: Project Country | S5: Salutation | T5: Win/Loss Reason | U5: Solutions | V5: Canada Province/Territory | W5: Project Canadian Region | X5: Product
A6: Shown menu | B6: Visible status path | C6: Shown menu | D6: Shown menu | E6: Partial list | F6: Shown menu; one context | G6: Shown menu; one context | H6: Shown menu; one context | I6: Shown menu; one context | J6: Shown menu | K6: Shown menu | L6: Shown menu; one context | M6: Shown menu | N6: Excel representation | O6: Partial list | P6: Partial list | Q6: Current value only | R6: Current value only | S6: Options not shown | T6: Options not shown | U6: Options not shown | V6: Options not shown | W6: Options not shown | X6: Visible codes; labels truncated
A7: --None-- | B7: New | C7: --None-- | D7: --None-- | E7: --None-- | F7: --None-- | G7: --None-- | H7: --None-- | I7: --None-- | J7: --None-- | K7: --None-- | L7: --None-- | M7: --None-- | N7: Yes | O7: Contractor | P7: Apparel | Q7: Sales | R7: United States | S7: --None-- | T7: --None-- | U7: --None-- | V7: --None-- | W7: --None-- | X7: A00 - CU COMMERCIAL BUILD...
A8: Open | B8: Initial Contact | C8: IOU | D8: IOU | E8: Airports | F8: Transmission | G8: New Capacity/New Build | H8: New Load Growth | I8: Generation | J8: Brownfield | K8: Traditional | L8: Solar | M8: Yes | N8: No | O8: Contractor-Field | P8: Banking | X8: A10 - CU RESIDENTIAL BUILDI...
A9: In Progress | B9: Sales Discovery | C9: IPP | D9: Public Power / Coop | E9: Battery Storage | F9: Distribution | G9: Reconductoring/Uprate Substation (New/Expansion) | H9: Load Interconnection | I9: Switchgear/Protection | J9: Greenfield | K9: Behind the Meter | L9: Wind | M9: No | O9: Contractor-Office | P9: Biotechnology | X9: A50 - AL COMMERCIAL BUILDI...
A10: Delayed | B10: Pass to Agent | C10: MUNI | D10: IPP | E10: Clean Energy | F10: Generation | G10: Interconnection/POI | H10: Grid Hardening / Resiliency | I10: Modular/Packaged Solutions | L10: BESS | O10: Distributor | P10: Chemicals | X10: A60 - AL RESIDENTIAL BUILDI...
A11: Closed | B11: Recycle | C11: COOP | D11: EPC | E11: Data Center | G11: Undergrounding | H11: Grid Modernization | L11: Natural Gas | O11: Distributor-Counter Sales | P11: Communications | X11: B00 - MC/FLEX & LIQUIDTIGHT
B12: Reject | C12: PP | D12: Developer | E12: EV | G12: Feeder Expansion | H12: Replacement / End-of-Life | O12: Distributor-Inside Sales | P12: Construction | X12: C00 - TOOLS & EQUIPMENT
B13: Converted | D13: Owner/End User | E13: Factory Automation | G13: Electrical BoP/Switchyard | H13: Regulatory / Policy | O13: Distributor-Management | P13: Consulting | X13: C50 - DELETE - DO NOT USE
D14: Design / Build | E14: Healthcare | O14: Distributor-Outside Sales | P14: Data Centers | X14: C60 - COMPONENTS
E15: Mass Transit/Rail | O15: Distributor-Purchasing | P15: Education | X15: D00 - VOICE, DATA & ELECTR...
E16: Mining | O16: Distributor-Warehouse | P16: Electronics | X16: D11 - CU TRANSIT
E17: Power Generation | O17: End User | P17: Energy | X17: D30 - CORD
O18: Engineer | X18: E00 - LEAD WIRE PRODUCTS
O19: General Contractor | X19: E10 - COPPER FAB
O20: Inspector | X20: E20 - SPECIALTY MARKET PRO...
O21: Internal | X21: G00 - MEDIUM VOLTAGE POWER...
O22: K-12 | X22: H00 - INDUSTRIAL SINGLE COND...
O23: Local Government | X23: J10 - INDUSTRIAL ARMORED CAB...
O24: Military | X24: K00 - CU TELEPHONE POWER...
O25: Senator | X25: M10 - CIC
O26: Southwire | X26: M20 - SUBSTATION
O27: Technical | X27: M30 - PROOF POSITIVE
O28: University | X28: N00 - HV UNDERGROUND CABLE
O29: Other | X29: P10 - BARE AL
X30: P20 - INSULATED AL 600V UTI...
X31: P30 - CAMP
X32: P40 - MEDIUM VOLTAGE PRIM...
X33: P50 - BARE CU
X34: P60 - INSULATED CU UTILITY...
X35: P70 - STEEL WIRE & CABLE
X36: P80 - UTILITY ACCESSORIES

Sheet Guide
A1: Stephan Hardt | Power Generation
A2: Using the template
A3: Fields and visible choices transcribed from the two supplied Salesforce recordings.
A5: Action / topic | B5: Where | C5: Format / behavior | D5: Instructions
A6: Enter records | B6: Projects and Leads | C6: Rows 7–206 | D6: Use one row per record. Required fields turn pale red if a started row is missing them.
A7: Use dropdowns | B7: Amber cells | C7: Click a cell to select | D7: Source choices remain editable on Dropdowns. Blank and --None-- are distinct.
A8: Add choices | B8: Dropdowns | C8: Rows 7–106 | D8: Append below the last option without gaps. Lists update through named ranges.
A9: Select products | B9: Project Products | C9: Rows 7–506 | D9: Repeat a project name for each product. Lead product checkboxes use Yes/No columns.
A10: Enter dates | B10: Date columns | C10: MM/DD/YY | D10: Enter real Excel dates. Enter Project Probability as a percentage, such as 50%.
A11: Extend records | B11: After prepared rows | C11: Copy a full input row | D11: Insert a table row and copy the preceding row to preserve validation and formatting. Extend ProjectNames in Name Manager beyond row 206 when needed.
A12: Preserve identifiers | B12: IDs, phones and ZIPs | C12: Stored as text | D12: Leading zeros and punctuation are preserved.
A13: Read long notes | B13: Comments and descriptions | C13: Use the formula bar | D13: Increase row height as needed to show longer text.
A14: Lookup fields | B14: Accounts and contacts | C14: Manual entry | D14: The recordings do not provide the full account/contact/owner lists. These remain text fields.
A15: Dependent lists | B15: Market classifications | C15: Independent dropdowns | D15: Salesforce dependencies are not shown. Options shown under Power Generation are not rules for other markets.
A16: Unavailable options | B16: Lists marked partial | C16: Typing allowed | D16: Market, Occupation, Industry, Lead Source, Country, Salutation, Win/Loss Reason, Solutions and Canadian lists are incomplete or not opened. Add confirmed values when available.
... A76: Leads | B76: Sales Update | C76: CG–CJ | D76: 4 fields
A81: Whole-plant cable benchmark ($/kW) | B81: 8 | C81: Change this one cell to update every Amount ($) on Projects and Leads.

Sheet Research Sources
A1: Project | B1: Source link
A2: Forest Junction Energy Center | B2: https://dailyreporter.com/2026/08/31/invenergy-proposes-two-natural-gas-plants-calumet-county/
A3: Forest Junction Energy Center | B3: https://fox11online.com/news/local/calumet-county-power-plant-proposed-energy-centers-town-of-brillion-power-megawatts-gigawatts-we-energies-invenergy-town-of-woodville-forest-junction-union-depot
A4: Forest Junction Energy Center | B4: https://forestjunctionenergycenter.invenergy.com/
A5: Forest Junction Energy Center | B5: https://www.nbc26.com/lakeshore/neighbors-push-back-against-proposed-natural-gas-facility-in-town-of-brillion
A6: Orange County Advanced Power Station (OCAPS) | B6: https://www.click2houston.com/news/local/2026/10/14/entergy-texas-orange-county-advanced-power-station-now-delivering-power-to-southeast-texas/
A7: Orange County Advanced Power Station (OCAPS) | B7: https://www.power-eng.com/gas/turbines/entergy-texas-1-2-gw-ccgt-plant-is-now-online/
A8: Orange County Advanced Power Station (OCAPS) | B8: https://www.sargentlundy.com/projects/orange-county-advanced-power-station/
A9: Vast Sands Power I (Vistra Permian Basin expansion) | B9: https://gov.texas.gov/news/post/governor-abbott-announces-texas-energy-fund-loan-for-860-mw-of-new-power-in-west-texas
A10: Vast Sands Power I (Vistra Permian Basin expansion) | B10: https://investor.vistracorp.com/2025-09-29-Vistra-Announces-Plans-to-Build-New-Gas-Fueled-Dispatchable-Power-Units-in-the-Permian-Basin
A11: Vast Sands Power I (Vistra Permian Basin expansion) | B11: https://www.gem.wiki/Permian_Power_power_station
A12: Vast Sands Power I (Vistra Permian Basin expansion) | B12: https://www.tceq.texas.gov/downloads/permitting/air/bilingual/pending-permit-notices/178462-pls-english.pdf
... A136: Project Kilby (Chevron West Texas Power) | B136: https://kilby.com/contact/

Sheet Named Contacts
A1: Project | B1: Name | C1: Title | D1: Organization | E1: Role on project | F1: Published business contact | G1: Source | H1: Confidence | I1: Verified email | J1: Verified phone | K1: Contact note | L1: Contact source | M1: Checked on
A2: Forest Junction Energy Center | B2: Daniel Birmingham | C2: Lead Developer | D2: Invenergy | E2: Developer lead | G2: https://www.nbc26.com/lakeshore/two-natural-gas-power-plants-proposed-in-brillion | H2: News quote | I2: dbirmingham@invenergy.com | J2: +1 312-582-1094 | K2: Published business contact; cross-project DNR record. Forest Junction role listed by developer. | L2: https://apps.dnr.wi.gov/warp_ext/am_permittracking2.aspx?id=38822 | M2: 2026-10-29
A3: Forest Junction Energy Center | B3: Brendan Conway | C3: Spokesperson | D3: We Energies | E3: Possible acquirer | G3: https://www.wpr.org/news/energy-developer-planning-2-gigawatt-natural-gas-plants-northeast-wisconsin | H3: News quote | K3: Original lead suggestion; assignment/contact details not independently confirmed in this review. | M3: 2026-10-29
A4: Orange County Advanced Power Station (OCAPS) | B4: Keith Pollock | C4: Project Director, OCAPS | D4: Entergy Texas | E4: Owner project lead | G4: https://www.entergy.com/news/construction-nears-completion-on-entergy-texas-orange-county-advanced-power-station | H4: Official release | K4: Original lead suggestion; assignment/contact details not independently confirmed in this review. | M4: 2026-10-29
A5: Orange County Advanced Power Station (OCAPS) | B5: David Borde | C5: CEO | D5: Entergy Texas | E5: Executive | G5: https://www.entergy.com/news/entergy-texas-orange-county-advanced-power-station-begins-delivering-reliable-power-to-southeast-texas | H5: Official release | K5: Original lead suggestion; assignment/contact details not independently confirmed in this review. | M5: 2026-10-29
A6: Orange County Advanced Power Station (OCAPS) | B6: James Malone | C6: Director of Business Development | D6: Sargent & Lundy | E6: Engineer of record | G6: https://www.sargentlundy.com/projects/orange-county-advanced-power-station/ | H6: Company website | K6: Original lead suggestion; assignment/contact details not independently confirmed in this review. | M6: 2026-10-29
A7: Orange County Advanced Power Station (OCAPS) | B7: Kendra James | C7: Media Relations | D7: Entergy Texas | E7: Media | F7: Media line 281-297-2353 | G7: https://www.entergy.com/news/media-kit | H7: Official website | K7: Original media line not independently reconfirmed; not a project procurement number. | M7: 2026-10-29
A8: Vast Sands Power I (Vistra Permian Basin expansion) | B8: Jim Burke | C8: President & CEO | D8: Vistra Corp | E8: Executive (no project contact public) | G8: https://gov.texas.gov/news/post/governor-abbott-announces-texas-energy-fund-loan-for-860-mw-of-new-power-in-west-texas | H8: Official release | K8: Original lead suggestion; assignment/contact details not independently confirmed in this review. | M8: 2026-10-29
A9: Plant Yates Unit 9 (Yates CT Units 8-10) | B9: Rick Anderson | C9: SVP & Senior Production Officer | D9: Georgia Power | E9: Owner executive | G9: https://www.georgiapower.com/news-hub/press-releases/first-new-natural-gas-turbine-delivered-to-georgia-power-plant-yates.html | H9: Official release | K9: Original lead suggestion; assignment/contact details not independently confirmed in this review. | M9: 2026-10-29
A10: Plant Yates Unit 9 (Yates CT Units 8-10) | B10: Cheryl Boddiford | C10: SVP, North American Manufacturing & Supply Chain Mgmt | D10: Mitsubishi Power | E10: EPC consortium (OEM) | G10: https://power.mhi.com/regions/amer/news/250819 | H10: Official release | K10: Original lead suggestion; assignment/contact details not independently confirmed in this review. | M10: 2026-10-29
A11: Plant Yates Unit 9 (Yates CT Units 8-10) | B11: Rick Janik | C11: Project Manager (Plant Barry Unit 8) | D11: Black & Veatch | E11: Same EPC pairing at Southern Co. - not confirmed for Yates | G11: https://www.bv.com/en-US/projects/gas-fired-power-plant-project-defies-challenges-to-deliver-safe-reliable-power | H11: Company website - indirect | K11: Original source concerns Plant Barry; Yates assignment NOT verified. | M11: 2026-10-29
A12: Ironwood Power Station | B12: Carlos Ruiz | C12: VP, Power Development - New Generation | D12: Entergy | E12: Owner new-generation executive | G12: https://apps.apsc.arkansas.gov/pdf/24/24-072-U_67_1.pdf | H12: Regulatory filing | K12: Original lead suggestion; assignment/contact details not independently confirmed in this review. | M12: 2026-10-29
A13: Ironwood Power Station | B13: Laura Landreaux | C13: President & CEO | D13: Entergy Arkansas | E13: Executive | G13: https://www.arkansasonline.com/news/2026/aug/21/entergy-breaks-ground-on-ironwood-power-station/ | H13: News | K13: Original lead suggestion; assignment/contact details not independently confirmed in this review. | M13: 2026-10-29
A14: Ironwood Power Station | B14: Louise Duncan | C14: VP, Power Plant Operations | D14: Entergy Arkansas | E14: Plant operations | G14: https://adeq.state.ar.us/downloads/WebDatabases/PermitsOnline/NPDES/PermitInformation/AR0001147_Certificate%20of%20Service%20Letter_20260430.pdf | H14: Regulatory document | K14: Original lead suggestion; assignment/contact details not independently confirmed in this review. | M14: 2026-10-29
A15: Ironwood Power Station | B15: Clay McMaster | C15: Environmental/permit contact, Lake Catherine | D15: Entergy | E15: Permitting | F15: wmcmast@entergy.com (ADEQ permit) | G15: https://adeq.state.ar.us/downloads/WebDatabases/PermitsOnline/Air/1717-AOP-R9.pdf | H15: Regulatory document | K15: Original lead suggestion; assignment/contact details not independently confirmed in this review. | M15: 2026-10-29
A16: Ironwood Power Station | B16: Kendall Thornton | C16: Stakeholder Engagement Coordinator | D16: Entergy Arkansas | E16: Groundbreaking organizer | G16: https://arkansasstatechamber.com/team-member/kendall-thornton/ | H16: Org website | K16: Original lead suggestion; assignment/contact details not independently confirmed in this review. | M16: 2026-10-29
A17: Ironwood Power Station | B17: Jason Rees | C17: Director of Procurement | D17: Entergy | E17: Procurement | G17: https://www.linkedin.com/in/reesjason/ | H17: LinkedIn - verify | K17: LinkedIn-derived suggestion; current procurement assignment not independently confirmed. | M17: 2026-10-29
A18: Ironwood Power Station | B18: Entergy Supplier Registration | C18: - | D18: Entergy | E18: Supplier onboarding | F18: esupplier@entergy.com; 844-387-9675 | G18: https://www.entergy.com/suppliers/how | H18: Official website | I18: esupplier@entergy.com | J18: +1 844-387-9675 | K18: Shared supplier support; not a project buyer. | L18: https://supplier.entergy.com/psc/supprd/SUPPLIER/ERP/c/SCP_PUBLIC_MENU_FL.SCP_PUB_FAQ_CMP_FL.GBL | M18: 2026-10-29
